Workbook
Name UPDATE: 'Data Sheet'!$E$1

Sheet Profit & Loss
A1: ='Data Sheet'!B1 -> DABUR INDIA LTD | H1: =UPDATE | M1: SCREENER.IN
A3: Narration | B3: ='Data Sheet'!B16 -> 42094 | C3: ='Data Sheet'!C16 -> 42460 | D3: ='Data Sheet'!D16 -> 42825 | E3: ='Data Sheet'!E16 -> 43190 | F3: ='Data Sheet'!F16 -> 43555 | G3: ='Data Sheet'!G16 -> 43921 | H3: ='Data Sheet'!H16 -> 44286 | I3: ='Data Sheet'!I16 -> 44651 | ... K3: ='Data Sheet'!K16 -> 45382 | L3: Trailing | M3: Best Case | N3: Worst Case
A4: Sales | B4: ='Data Sheet'!B17 -> 7795.49 | C4: ='Data Sheet'!C17 -> 7779.66 | D4: ='Data Sheet'!D17 -> 7613.59 | E4: ='Data Sheet'!E17 -> 7721.85 | F4: ='Data Sheet'!F17 -> 8514.99 | G4: ='Data Sheet'!G17 -> 8684.64 | H4: ='Data Sheet'!H17 -> 9561.65 | I4: ='Data Sheet'!I17 -> 10888.68 | ... K4: ='Data Sheet'!K17 -> 12404.01 | L4: =SUM(Quarters!H4:K4) -> 12622.65 | M4: =$K4+M23*K4 -> 13528.154 | N4: =$K4+N23*L4 -> 13072.546
A5: Expenses | B5: =SUM('Data Sheet'!B18,'Data Sheet'!B20:B24, -1*'Data Sheet'!B19) -> 6475.27 | C5: =SUM('Data Sheet'!C18,'Data Sheet'!C20:C24, -1*'Data Sheet'!C19) -> 6261.38 | D5: =SUM('Data Sheet'!D18,'Data Sheet'!D20:D24, -1*'Data Sheet'!D19) -> 6101.98 | E5: =SUM('Data Sheet'!E18,'Data Sheet'!E20:E24, -1*'Data Sheet'!E19) -> 6104.41 | F5: =SUM('Data Sheet'!F18,'Data Sheet'!F20:F24, -1*'Data Sheet'!F19) -> 6775.43 | G5: =SUM('Data Sheet'!G18,'Data Sheet'!G20:G24, -1*'Data Sheet'!G19) -> 6892.3 | H5: =SUM('Data Sheet'!H18,'Data Sheet'!H20:H24, -1*'Data Sheet'!H19) -> 7559.98 | I5: =SUM('Data Sheet'!I18,'Data Sheet'!I20:I24, -1*'Data Sheet'!I19) -> 8636.67 | ... K5: =SUM('Data Sheet'!K18,'Data Sheet'!K20:K24, -1*'Data Sheet'!K19) -> 10004.29 | L5: =SUM(Quarters!H5:K5) -> 10173.12 | M5: =M4-M6 -> 10880.911 | N5: =N4-N6 -> 10535.71
A6: Operating Profit | B6: =B4-B5 -> 1320.22 | C6: =C4-C5 -> 1518.28 | D6: =D4-D5 -> 1511.61 | E6: =E4-E5 -> 1617.44 | F6: =F4-F5 -> 1739.56 | G6: =G4-G5 -> 1792.34 | H6: =H4-H5 -> 2001.67 | I6: =I4-I5 -> 2252.01 | ... K6: =K4-K5 -> 2399.72 | L6: =SUM(Quarters!H6:K6) -> 2449.53 | M6: =M4*M24 -> 2647.2426 | N6: =N4*N24 -> 2536.836
A7: Other Income | B7: ='Data Sheet'!B25 -> 154.24 | C7: ='Data Sheet'!C25 -> 217.19 | D7: ='Data Sheet'!D25 -> 295.93 | E7: ='Data Sheet'!E25 -> 290.88 | F7: ='Data Sheet'!F25 -> 221.79 | G7: ='Data Sheet'!G25 -> 205.29 | H7: ='Data Sheet'!H25 -> 325.29 | I7: ='Data Sheet'!I25 -> 308.16 | ... K7: ='Data Sheet'!K25 -> 482.41 | L7: =SUM(Quarters!H7:K7) -> 502.52 | M7: 0 | N7: 0
A8: Depreciation | B8: ='Data Sheet'!B26 -> 114.98 | C8: ='Data Sheet'!C26 -> 133.19 | D8: ='Data Sheet'!D26 -> 142.86 | E8: ='Data Sheet'!E26 -> 162.18 | F8: ='Data Sheet'!F26 -> 176.9 | G8: ='Data Sheet'!G26 -> 220.45 | H8: ='Data Sheet'!H26 -> 240.13 | I8: ='Data Sheet'!I26 -> 252.89 | ... K8: ='Data Sheet'!K26 -> 399.21 | L8: =SUM(Quarters!H8:K8) -> 411.69 | M8: =+$L8 -> 411.69 | N8: =+$L8 -> 411.69
A9: Interest | B9: ='Data Sheet'!B27 -> 40.12 | C9: ='Data Sheet'!C27 -> 48.48 | D9: ='Data Sheet'!D27 -> 54.03 | E9: ='Data Sheet'!E27 -> 53.05 | F9: ='Data Sheet'!F27 -> 59.58 | G9: ='Data Sheet'!G27 -> 49.54 | H9: ='Data Sheet'!H27 -> 30.81 | I9: ='Data Sheet'!I27 -> 38.6 | ... K9: ='Data Sheet'!K27 -> 124.18 | L9: =SUM(Quarters!H9:K9) -> 132.53 | M9: =+$L9 -> 132.53 | N9: =+$L9 -> 132.53
A10: Profit before tax | B10: ='Data Sheet'!B28 -> 1319.36 | C10: ='Data Sheet'!C28 -> 1553.8 | D10: ='Data Sheet'!D28 -> 1610.65 | E10: ='Data Sheet'!E28 -> 1693.09 | F10: ='Data Sheet'!F28 -> 1724.87 | G10: ='Data Sheet'!G28 -> 1727.64 | H10: ='Data Sheet'!H28 -> 2056.02 | I10: ='Data Sheet'!I28 -> 2268.68 | ... K10: ='Data Sheet'!K28 -> 2358.74 | L10: =SUM(Quarters!H10:K10) -> 2407.83 | M10: =M6+M7-SUM(M8:M9) -> 2103.0226 | N10: =N6+N7-SUM(N8:N9) -> 1992.616
A11: Tax | B11: ='Data Sheet'!B29 -> 250.89 | C11: ='Data Sheet'!C29 -> 299.9 | D11: ='Data Sheet'!D29 -> 330.34 | E11: ='Data Sheet'!E29 -> 335.35 | F11: ='Data Sheet'!F29 -> 278.62 | G11: ='Data Sheet'!G29 -> 279.72 | H11: ='Data Sheet'!H29 -> 361.07 | I11: ='Data Sheet'!I29 -> 526.38 | ... K11: ='Data Sheet'!K29 -> 547.43 | L11: =SUM(Quarters!H11:K11) -> 558.78 | M11: =IF($L10>0,$L11/$L10,0) -> 0.23206788 | N11: =IF($L10>0,$L11/$L10,0) -> 0.23206788
A12: Net profit | B12: ='Data Sheet'!B30 -> 1065.83 | C12: ='Data Sheet'!C30 -> 1251.15 | D12: ='Data Sheet'!D30 -> 1276.94 | E12: ='Data Sheet'!E30 -> 1354.39 | F12: ='Data Sheet'!F30 -> 1442.33 | G12: ='Data Sheet'!G30 -> 1444.96 | H12: ='Data Sheet'!H30 -> 1693.3 | I12: ='Data Sheet'!I30 -> 1739.22 | ... K12: ='Data Sheet'!K30 -> 1842.68 | L12: =SUM(Quarters!H12:K12) -> 1878.92 | M12: =M10-M11*M10 -> 1614.9786 | N12: =N10-N11*N10 -> 1530.1938
A13: EPS | B13: =IF('Data Sheet'!B93>0,B12/'Data Sheet'!B93,0) -> 6.0679192 | C13: =IF('Data Sheet'!C93>0,C12/'Data Sheet'!C93,0) -> 7.1124439 | D13: =IF('Data Sheet'!D93>0,D12/'Data Sheet'!D93,0) -> 7.2491626 | E13: =IF('Data Sheet'!E93>0,E12/'Data Sheet'!E93,0) -> 7.6888447 | F13: =IF('Data Sheet'!F93>0,F12/'Data Sheet'!F93,0) -> 8.1658269 | G13: =IF('Data Sheet'!G93>0,G12/'Data Sheet'!G93,0) -> 8.1770132 | H13: =IF('Data Sheet'!H93>0,H12/'Data Sheet'!H93,0) -> 9.5807401 | I13: =IF('Data Sheet'!I93>0,I12/'Data Sheet'!I93,0) -> 9.8377736 | ... K13: =IF('Data Sheet'!K93>0,K12/'Data Sheet'!K93,0) -> 10.398871 | L13: =IF('Data Sheet'!$B6>0,'Profit & Loss'!L12/'Data Sheet'!$B6,0) -> 10.601529 | M13: =IF('Data Sheet'!$B6>0,'Profit & Loss'!M12/'Data Sheet'!$B6,0) -> 9.1122785 | N13: =IF('Data Sheet'!$B6>0,'Profit & Loss'!N12/'Data Sheet'!$B6,0) -> 8.6338931
A14: Price to earning | B14: =IF(B15>0,B15/B13,"") -> 43.762943 | C14: =IF(C15>0,C15/C13,"") -> 35.135602 | D14: =IF(D15>0,D15/D13,"") -> 38.259591 | E14: =IF(E15>0,E15/E13,"") -> 42.711228 | F14: =IF(F15>0,F15/F13,"") -> 50.062291 | G14: =IF(G15>0,G15/G13,"") -> 55.038434 | H14: =IF(H15>0,H15/H13,"") -> 56.415266 | I14: =IF(I15>0,I15/I13,"") -> 54.504202 | ... K14: =IF(K15>0,K15/K13,"") -> 50.308344 | L14: =IF(L13>0,L15/L13,0) -> 59.019788 | M14: =M25 -> 59.019788 | N14: =N25 -> 49.25193
A15: Price | B15: ='Data Sheet'!B90 -> 265.55 | C15: ='Data Sheet'!C90 -> 249.9 | D15: ='Data Sheet'!D90 -> 277.35 | E15: ='Data Sheet'!E90 -> 328.4 | F15: ='Data Sheet'!F90 -> 408.8 | G15: ='Data Sheet'!G90 -> 450.05 | H15: ='Data Sheet'!H90 -> 540.5 | I15: ='Data Sheet'!I90 -> 536.2 | ... K15: ='Data Sheet'!K90 -> 523.15 | L15: ='Data Sheet'!B8 -> 625.7 | M15: =M13*M14 -> 537.80475 | N15: =N13*N14 -> 425.2359
A17: RATIOS:
A18: Dividend Payout | B18: =IF('Data Sheet'!B30>0, 'Data Sheet'!B31/'Data Sheet'!B30, 0) -> 0.32960228 | C18: =IF('Data Sheet'!C30>0, 'Data Sheet'!C31/'Data Sheet'!C30, 0) -> 0.31634896 | D18: =IF('Data Sheet'!D30>0, 'Data Sheet'!D31/'Data Sheet'!D30, 0) -> 0.31038263 | E18: =IF('Data Sheet'!E30>0, 'Data Sheet'!E31/'Data Sheet'!E30, 0) -> 0.81286779 | F18: =IF('Data Sheet'!F30>0, 'Data Sheet'!F31/'Data Sheet'!F30, 0) -> 0.33676759 | G18: =IF('Data Sheet'!G30>0, 'Data Sheet'!G31/'Data Sheet'!G30, 0) -> 0.36688213 | H18: =IF('Data Sheet'!H30>0, 'Data Sheet'!H31/'Data Sheet'!H30, 0) -> 0.49578929 | I18: =IF('Data Sheet'!I30>0, 'Data Sheet'!I31/'Data Sheet'!I30, 0) -> 0.52857603 | ... K18: =IF('Data Sheet'!K30>0, 'Data Sheet'!K31/'Data Sheet'!K30, 0) -> 0.52890355
A19: OPM | B19: =IF(B6>0,B6/B4,0) -> 0.1693569 | C19: =IF(C6>0,C6/C4,0) -> 0.1951602 | D19: =IF(D6>0,D6/D4,0) -> 0.19854103 | E19: =IF(E6>0,E6/E4,0) -> 0.20946276 | F19: =IF(F6>0,F6/F4,0) -> 0.20429384 | G19: =IF(G6>0,G6/G4,0) -> 0.20638046 | H19: =IF(H6>0,H6/H4,0) -> 0.20934358 | I19: =IF(I6>0,I6/I4,0) -> 0.20682121 | ... L19: =IF(L6>0,L6/L4,0) -> 0.1940583
G22: TRENDS: | H22: 10 YEARS | I22: 7 YEARS | J22: 5 YEARS | K22: 3 YEARS | L22: RECENT | M22: BEST | N22: WORST
G23: Sales Growth | H23: =IF(B4=0,"",POWER($K4/B4,1/9)-1) -> 0.052963186 | I23: =IF(D4=0,"",POWER($K4/D4,1/7)-1) -> 0.072214814 | J23: =IF(F4=0,"",POWER($K4/F4,1/5)-1) -> 0.078141077 | K23: =IF(H4=0,"",POWER($K4/H4, 1/3)-1) -> 0.090627444 | L23: =IF(ISERROR(MAX(IF(J4=0,"",(K4-J4)/J4),IF(K4=0,"",(L4-K4)/K4))),"",MAX(IF(J4=0,"",(K4-J4)/J4),IF(K4=0,"",(L4-K4)/K4))) -> 0.075813386 | M23: =MAX(K23:L23) -> 0.090627444 | N23: =MIN(H23:L23) -> 0.052963186
G24: OPM | H24: =IF(SUM(B4:$K$4)=0,"",SUMPRODUCT(B19:$K$19,B4:$K$4)/SUM(B4:$K$4)) -> 0.19801556 | I24: =IF(SUM(E4:$K$4)=0,"",SUMPRODUCT(E19:$K$19,E4:$K$4)/SUM(E4:$K$4)) -> 0.20150187 | J24: =IF(SUM(G4:$K$4)=0,"",SUMPRODUCT(G19:$K$19,G4:$K$4)/SUM(G4:$K$4)) -> 0.19989553 | K24: =IF(SUM(I4:$K$4)=0, "", SUMPRODUCT(I19:$K$19,I4:$K$4)/SUM(I4:$K$4)) -> 0.19568395 | L24: =L19 -> 0.1940583 | M24: =MAX(K24:L24) -> 0.19568395 | N24: =MIN(H24:L24) -> 0.1940583
G25: Price to Earning | H25: =IF(ISERROR(AVERAGEIF(B14:$L14,">0")),"",AVERAGEIF(B14:$L14,">0")) -> 49.25193 | I25: =IF(ISERROR(AVERAGEIF(E14:$L14,">0")),"",AVERAGEIF(E14:$L14,">0")) -> 53.076637 | J25: =IF(ISERROR(AVERAGEIF(G14:$L14,">0")),"",AVERAGEIF(G14:$L14,">0")) -> 55.306596 | K25: =IF(ISERROR(AVERAGEIF(I14:$L14,">0")),"",AVERAGEIF(I14:$L14,">0")) -> 55.096469 | L25: =L14 -> 59.019788 | M25: =MAX(K25:L25) -> 59.019788 | N25: =MIN(H25:L25) -> 49.25193

Sheet Quarters
A1: ='Profit & Loss'!A1 -> DABUR INDIA LTD | E1: =UPDATE | J1: SCREENER.IN
A3: Narration | B3: ='Data Sheet'!B41 -> 44651 | C3: ='Data Sheet'!C41 -> 44742 | D3: ='Data Sheet'!D41 -> 44834 | E3: ='Data Sheet'!E41 -> 44926 | F3: ='Data Sheet'!F41 -> 45016 | G3: ='Data Sheet'!G41 -> 45107 | H3: ='Data Sheet'!H41 -> 45199 | I3: ='Data Sheet'!I41 -> 45291 | ... K3: ='Data Sheet'!K41 -> 45473
A4: Sales | B4: ='Data Sheet'!B42 -> 2517.81 | C4: ='Data Sheet'!C42 -> 2822.43 | D4: ='Data Sheet'!D42 -> 2986.49 | E4: ='Data Sheet'!E42 -> 3043.17 | F4: ='Data Sheet'!F42 -> 2677.8 | G4: ='Data Sheet'!G42 -> 3130.47 | H4: ='Data Sheet'!H42 -> 3203.84 | I4: ='Data Sheet'!I42 -> 3255.06 | ... K4: ='Data Sheet'!K42 -> 3349.11
A5: Expenses | B5: ='Data Sheet'!B43 -> 2065.44 | C5: ='Data Sheet'!C43 -> 2279.11 | D5: ='Data Sheet'!D43 -> 2386.09 | E5: ='Data Sheet'!E43 -> 2434.05 | F5: ='Data Sheet'!F43 -> 2268.15 | G5: ='Data Sheet'!G43 -> 2525.94 | H5: ='Data Sheet'!H43 -> 2542.97 | I5: ='Data Sheet'!I43 -> 2587.64 | ... K5: ='Data Sheet'!K43 -> 2694.28
A6: Operating Profit | B6: ='Data Sheet'!B50 -> 452.37 | C6: ='Data Sheet'!C50 -> 543.32 | D6: ='Data Sheet'!D50 -> 600.4 | E6: ='Data Sheet'!E50 -> 609.12 | F6: ='Data Sheet'!F50 -> 409.65 | G6: ='Data Sheet'!G50 -> 604.53 | H6: ='Data Sheet'!H50 -> 660.87 | I6: ='Data Sheet'!I50 -> 667.42 | ... K6: ='Data Sheet'!K50 -> 654.83
A7: Other Income | B7: ='Data Sheet'!B44 -> 14.14 | C7: ='Data Sheet'!C44 -> 100.55 | D7: ='Data Sheet'!D44 -> 123.28 | E7: ='Data Sheet'!E44 -> 100.84 | F7: ='Data Sheet'!F44 -> 120.72 | G7: ='Data Sheet'!G44 -> 109.78 | H7: ='Data Sheet'!H44 -> 116.9 | I7: ='Data Sheet'!I44 -> 127.37 | ... K7: ='Data Sheet'!K44 -> 129.4
A8: Depreciation | B8: ='Data Sheet'!B45 -> 65.05 | C8: ='Data Sheet'!C45 -> 67.6 | D8: ='Data Sheet'!D45 -> 70.47 | E8: ='Data Sheet'!E45 -> 70.89 | F8: ='Data Sheet'!F45 -> 102 | G8: ='Data Sheet'!G45 -> 96.64 | H8: ='Data Sheet'!H45 -> 98.32 | I8: ='Data Sheet'!I45 -> 96.89 | ... K8: ='Data Sheet'!K45 -> 109.12
A9: Interest | B9: ='Data Sheet'!B46 -> 11.75 | C9: ='Data Sheet'!C46 -> 12.15 | D9: ='Data Sheet'!D46 -> 15.06 | E9: ='Data Sheet'!E46 -> 18.91 | F9: ='Data Sheet'!F46 -> 32.12 | G9: ='Data Sheet'!G46 -> 24.31 | H9: ='Data Sheet'!H46 -> 28.14 | I9: ='Data Sheet'!I46 -> 36.49 | ... K9: ='Data Sheet'!K46 -> 32.66
A10: Profit before tax | B10: ='Data Sheet'!B47 -> 389.71 | C10: ='Data Sheet'!C47 -> 564.12 | D10: ='Data Sheet'!D47 -> 638.15 | E10: ='Data Sheet'!E47 -> 620.16 | F10: ='Data Sheet'!F47 -> 396.25 | G10: ='Data Sheet'!G47 -> 593.36 | H10: ='Data Sheet'!H47 -> 651.31 | I10: ='Data Sheet'!I47 -> 661.41 | ... K10: ='Data Sheet'!K47 -> 642.45
A11: Tax | B11: ='Data Sheet'!B48 -> 95.37 | C11: ='Data Sheet'!C48 -> 123.06 | D11: ='Data Sheet'!D48 -> 147.29 | E11: ='Data Sheet'!E48 -> 143.51 | F11: ='Data Sheet'!F48 -> 103.49 | G11: ='Data Sheet'!G48 -> 136.75 | H11: ='Data Sheet'!H48 -> 144.27 | I11: ='Data Sheet'!I48 -> 154.97 | ... K11: ='Data Sheet'!K48 -> 148.1
A12: Net profit | B12: ='Data Sheet'!B49 -> 294.22 | C12: ='Data Sheet'!C49 -> 440.32 | D12: ='Data Sheet'!D49 -> 490.06 | E12: ='Data Sheet'!E49 -> 475.94 | F12: ='Data Sheet'!F49 -> 300.83 | G12: ='Data Sheet'!G49 -> 463.88 | H12: ='Data Sheet'!H49 -> 515.05 | I12: ='Data Sheet'!I49 -> 514.22 | ... K12: ='Data Sheet'!K49 -> 500.12
A14: OPM | B14: =IF(B4>0,B6/B4,"") -> 0.17966804 | C14: =IF(C4>0,C6/C4,"") -> 0.19250079 | D14: =IF(D4>0,D6/D4,"") -> 0.20103868 | E14: =IF(E4>0,E6/E4,"") -> 0.2001597 | F14: =IF(F4>0,F6/F4,"") -> 0.15298006 | G14: =IF(G4>0,G6/G4,"") -> 0.19311158 | H14: =IF(H4>0,H6/H4,"") -> 0.20627435 | I14: =IF(I4>0,I6/I4,"") -> 0.20504077 | ... K14: =IF(K4>0,K6/K4,"") -> 0.19552359

Sheet Balance Sheet
A1: ='Profit & Loss'!A1 -> DABUR INDIA LTD | E1: =UPDATE | J1: SCREENER.IN
A3: Narration | B3: ='Data Sheet'!B56 -> 42094 | C3: ='Data Sheet'!C56 -> 42460 | D3: ='Data Sheet'!D56 -> 42825 | E3: ='Data Sheet'!E56 -> 43190 | F3: ='Data Sheet'!F56 -> 43555 | G3: ='Data Sheet'!G56 -> 43921 | H3: ='Data Sheet'!H56 -> 44286 | I3: ='Data Sheet'!I56 -> 44651 | ... K3: ='Data Sheet'!K56 -> 45382
A4: Equity Share Capital | B4: ='Data Sheet'!B57 -> 175.65 | C4: ='Data Sheet'!C57 -> 175.91 | D4: ='Data Sheet'!D57 -> 176.15 | E4: ='Data Sheet'!E57 -> 176.15 | F4: ='Data Sheet'!F57 -> 176.63 | G4: ='Data Sheet'!G57 -> 176.71 | H4: ='Data Sheet'!H57 -> 176.74 | I4: ='Data Sheet'!I57 -> 176.79 | ... K4: ='Data Sheet'!K57 -> 177.2
A5: Reserves | B5: ='Data Sheet'!B58 -> 3178.49 | C5: ='Data Sheet'!C58 -> 3994.7 | D5: ='Data Sheet'!D58 -> 4671.24 | E5: ='Data Sheet'!E58 -> 5530.37 | F5: ='Data Sheet'!F58 -> 5455.05 | G5: ='Data Sheet'!G58 -> 6429.04 | H5: ='Data Sheet'!H58 -> 7486.79 | I5: ='Data Sheet'!I58 -> 8204.51 | ... K5: ='Data Sheet'!K58 -> 9689.1
A6: Borrowings | B6: ='Data Sheet'!B59 -> 733.56 | C6: ='Data Sheet'!C59 -> 805.22 | D6: ='Data Sheet'!D59 -> 975 | E6: ='Data Sheet'!E59 -> 937.59 | F6: ='Data Sheet'!F59 -> 699.37 | G6: ='Data Sheet'!G59 -> 521.99 | H6: ='Data Sheet'!H59 -> 509.06 | I6: ='Data Sheet'!I59 -> 1030.1 | ... K6: ='Data Sheet'!K59 -> 1365.09
A7: Other Liabilities | B7: ='Data Sheet'!B60 -> 2018.58 | C7: ='Data Sheet'!C60 -> 1956.47 | D7: ='Data Sheet'!D60 -> 1909.85 | E7: ='Data Sheet'!E60 -> 2057.52 | F7: ='Data Sheet'!F60 -> 2105.59 | G7: ='Data Sheet'!G60 -> 2208.84 | H7: ='Data Sheet'!H60 -> 2660.63 | I7: ='Data Sheet'!I60 -> 2872.46 | ... K7: ='Data Sheet'!K60 -> 3884.97
A8: Total | B8: ='Data Sheet'!B61 -> 6106.28 | C8: ='Data Sheet'!C61 -> 6932.3 | D8: ='Data Sheet'!D61 -> 7732.24 | E8: ='Data Sheet'!E61 -> 8701.63 | F8: ='Data Sheet'!F61 -> 8436.64 | G8: ='Data Sheet'!G61 -> 9336.58 | H8: ='Data Sheet'!H61 -> 10833.22 | I8: ='Data Sheet'!I61 -> 12283.86 | ... K8: ='Data Sheet'!K61 -> 15116.36
A10: Net Block | B10: ='Data Sheet'!B62 -> 1877.13 | C10: ='Data Sheet'!C62 -> 1667.4 | D10: ='Data Sheet'!D62 -> 1958.4 | E10: ='Data Sheet'!E62 -> 2028.11 | F10: ='Data Sheet'!F62 -> 1969.06 | G10: ='Data Sheet'!G62 -> 2252.68 | H10: ='Data Sheet'!H62 -> 2242.92 | I10: ='Data Sheet'!I62 -> 2307.9 | ... K10: ='Data Sheet'!K62 -> 3815
A11: Capital Work in Progress | B11: ='Data Sheet'!B63 -> 50.3 | C11: ='Data Sheet'!C63 -> 44.8 | D11: ='Data Sheet'!D63 -> 42.1 | E11: ='Data Sheet'!E63 -> 41.51 | F11: ='Data Sheet'!F63 -> 63.76 | G11: ='Data Sheet'!G63 -> 146.57 | H11: ='Data Sheet'!H63 -> 147.3 | I11: ='Data Sheet'!I63 -> 167.5 | ... K11: ='Data Sheet'!K63 -> 232.23
A12: Investments | B12: ='Data Sheet'!B64 -> 1813.37 | C12: ='Data Sheet'!C64 -> 2690.74 | D12: ='Data Sheet'!D64 -> 3240.16 | E12: ='Data Sheet'!E64 -> 3805.17 | F12: ='Data Sheet'!F64 -> 3358.76 | G12: ='Data Sheet'!G64 -> 2800.26 | H12: ='Data Sheet'!H64 -> 4159.63 | I12: ='Data Sheet'!I64 -> 6219.62 | ... K12: ='Data Sheet'!K64 -> 6932.69
A13: Other Assets | B13: ='Data Sheet'!B65 -> 2365.48 | C13: ='Data Sheet'!C65 -> 2529.36 | D13: ='Data Sheet'!D65 -> 2491.58 | E13: ='Data Sheet'!E65 -> 2826.84 | F13: ='Data Sheet'!F65 -> 3045.06 | G13: ='Data Sheet'!G65 -> 4137.07 | H13: ='Data Sheet'!H65 -> 4283.37 | I13: ='Data Sheet'!I65 -> 3588.84 | ... K13: ='Data Sheet'!K65 -> 4136.44
A14: Total | B14: ='Data Sheet'!B66 -> 6106.28 | C14: ='Data Sheet'!C66 -> 6932.3 | D14: ='Data Sheet'!D66 -> 7732.24 | E14: ='Data Sheet'!E66 -> 8701.63 | F14: ='Data Sheet'!F66 -> 8436.64 | G14: ='Data Sheet'!G66 -> 9336.58 | H14: ='Data Sheet'!H66 -> 10833.22 | I14: ='Data Sheet'!I66 -> 12283.86 | ... K14: ='Data Sheet'!K66 -> 15116.36
A16: Working Capital | B16: =B13-B7 -> 346.9 | C16: =C13-C7 -> 572.89 | D16: =D13-D7 -> 581.73 | E16: =E13-E7 -> 769.32 | F16: =F13-F7 -> 939.47 | G16: =G13-G7 -> 1928.23 | H16: =H13-H7 -> 1622.74 | I16: =I13-I7 -> 716.38 | ... K16: =K13-K7 -> 251.47
A17: Debtors | B17: ='Data Sheet'!B67 -> 710.84 | C17: ='Data Sheet'!C67 -> 809.2 | D17: ='Data Sheet'!D67 -> 650.42 | E17: ='Data Sheet'!E67 -> 706.08 | F17: ='Data Sheet'!F67 -> 833.56 | G17: ='Data Sheet'!G67 -> 813.89 | H17: ='Data Sheet'!H67 -> 561.58 | I17: ='Data Sheet'!I67 -> 646.15 | ... K17: ='Data Sheet'!K67 -> 898.72
A18: Inventory | B18: ='Data Sheet'!B68 -> 973.27 | C18: ='Data Sheet'!C68 -> 1096.5 | D18: ='Data Sheet'!D68 -> 1106.71 | E18: ='Data Sheet'!E68 -> 1256.18 | F18: ='Data Sheet'!F68 -> 1300.53 | G18: ='Data Sheet'!G68 -> 1379.57 | H18: ='Data Sheet'!H68 -> 1734.28 | I18: ='Data Sheet'!I68 -> 1911.37 | ... K18: ='Data Sheet'!K68 -> 1946.97
A20: Debtor Days | B20: =IF('Profit & Loss'!B4>0,'Balance Sheet'!B17/('Profit & Loss'!B4/365),0) -> 33.282911 | C20: =IF('Profit & Loss'!C4>0,'Balance Sheet'!C17/('Profit & Loss'!C4/365),0) -> 37.965412 | D20: =IF('Profit & Loss'!D4>0,'Balance Sheet'!D17/('Profit & Loss'!D4/365),0) -> 31.181519 | E20: =IF('Profit & Loss'!E4>0,'Balance Sheet'!E17/('Profit & Loss'!E4/365),0) -> 33.375318 | F20: =IF('Profit & Loss'!F4>0,'Balance Sheet'!F17/('Profit & Loss'!F4/365),0) -> 35.731034 | G20: =IF('Profit & Loss'!G4>0,'Balance Sheet'!G17/('Profit & Loss'!G4/365),0) -> 34.206352 | H20: =IF('Profit & Loss'!H4>0,'Balance Sheet'!H17/('Profit & Loss'!H4/365),0) -> 21.437377 | I20: =IF('Profit & Loss'!I4>0,'Balance Sheet'!I17/('Profit & Loss'!I4/365),0) -> 21.659627 | ... K20: =IF('Profit & Loss'!K4>0,'Balance Sheet'!K17/('Profit & Loss'!K4/365),0) -> 26.445706
A21: Inventory Turnover | B21: =IF('Balance Sheet'!B18>0,'Profit & Loss'!B4/'Balance Sheet'!B18,0) -> 8.0095862 | C21: =IF('Balance Sheet'!C18>0,'Profit & Loss'!C4/'Balance Sheet'!C18,0) -> 7.0949932 | D21: =IF('Balance Sheet'!D18>0,'Profit & Loss'!D4/'Balance Sheet'!D18,0) -> 6.8794806 | E21: =IF('Balance Sheet'!E18>0,'Profit & Loss'!E4/'Balance Sheet'!E18,0) -> 6.1470888 | F21: =IF('Balance Sheet'!F18>0,'Profit & Loss'!F4/'Balance Sheet'!F18,0) -> 6.547323 | G21: =IF('Balance Sheet'!G18>0,'Profit & Loss'!G4/'Balance Sheet'!G18,0) -> 6.2951789 | H21: =IF('Balance Sheet'!H18>0,'Profit & Loss'!H4/'Balance Sheet'!H18,0) -> 5.5133254 | I21: =IF('Balance Sheet'!I18>0,'Profit & Loss'!I4/'Balance Sheet'!I18,0) -> 5.6967934 | ... K21: =IF('Balance Sheet'!K18>0,'Profit & Loss'!K4/'Balance Sheet'!K18,0) -> 6.3709302
A23: Return on Equity | B23: =IF(SUM('Balance Sheet'!B4:B5)>0,'Profit & Loss'!B12/SUM('Balance Sheet'!B4:B5),"") -> 0.31776551 | C23: =IF(SUM('Balance Sheet'!C4:C5)>0,'Profit & Loss'!C12/SUM('Balance Sheet'!C4:C5),"") -> 0.29999209 | D23: =IF(SUM('Balance Sheet'!D4:D5)>0,'Profit & Loss'!D12/SUM('Balance Sheet'!D4:D5),"") -> 0.26342836 | E23: =IF(SUM('Balance Sheet'!E4:E5)>0,'Profit & Loss'!E12/SUM('Balance Sheet'!E4:E5),"") -> 0.2373408 | F23: =IF(SUM('Balance Sheet'!F4:F5)>0,'Profit & Loss'!F12/SUM('Balance Sheet'!F4:F5),"") -> 0.25611008 | G23: =IF(SUM('Balance Sheet'!G4:G5)>0,'Profit & Loss'!G12/SUM('Balance Sheet'!G4:G5),"") -> 0.21874276 | H23: =IF(SUM('Balance Sheet'!H4:H5)>0,'Profit & Loss'!H12/SUM('Balance Sheet'!H4:H5),"") -> 0.22095562 | I23: =IF(SUM('Balance Sheet'!I4:I5)>0,'Profit & Loss'!I12/SUM('Balance Sheet'!I4:I5),"") -> 0.20751196 | ... K23: =IF(SUM('Balance Sheet'!K4:K5)>0,'Profit & Loss'!K12/SUM('Balance Sheet'!K4:K5),"") -> 0.18676505
A24: Return on Capital Emp | C24: =IF((B4+B5+B6+C4+C5+C6)>0,('Profit & Loss'!C10+'Profit & Loss'!C9)*2/(B4+B5+B6+C4+C5+C6),"") -> 0.35356644 | D24: =IF((C4+C5+C6+D4+D5+D6)>0,('Profit & Loss'!D10+'Profit & Loss'!D9)*2/(C4+C5+C6+D4+D5+D6),"") -> 0.30832489 | E24: =IF((D4+D5+D6+E4+E5+E6)>0,('Profit & Loss'!E10+'Profit & Loss'!E9)*2/(D4+D5+D6+E4+E5+E6),"") -> 0.28013316 | F24: =IF((E4+E5+E6+F4+F5+F6)>0,('Profit & Loss'!F10+'Profit & Loss'!F9)*2/(E4+E5+E6+F4+F5+F6),"") -> 0.27505634 | G24: =IF((F4+F5+F6+G4+G5+G6)>0,('Profit & Loss'!G10+'Profit & Loss'!G9)*2/(F4+F5+F6+G4+G5+G6),"") -> 0.26409209 | H24: =IF((G4+G5+G6+H4+H5+H6)>0,('Profit & Loss'!H10+'Profit & Loss'!H9)*2/(G4+G5+G6+H4+H5+H6),"") -> 0.27278235 | I24: =IF((H4+H5+H6+I4+I5+I6)>0,('Profit & Loss'!I10+'Profit & Loss'!I9)*2/(H4+H5+H6+I4+I5+I6),"") -> 0.26242963 | J24: =IF((I4+I5+I6+J4+J5+J6)>0,('Profit & Loss'!J10+'Profit & Loss'!J9)*2/(I4+I5+I6+J4+J5+J6),"") -> 0.23487751 | K24: =IF((J4+J5+J6+K4+K5+K6)>0,('Profit & Loss'!K10+'Profit & Loss'!K9)*2/(J4+J5+J6+K4+K5+K6),"") -> 0.23228262

Sheet Cash Flow
A1: ='Balance Sheet'!A1 -> DABUR INDIA LTD | E1: =UPDATE | J1: SCREENER.IN
A3: Narration | B3: ='Data Sheet'!B81 -> 42094 | C3: ='Data Sheet'!C81 -> 42460 | D3: ='Data Sheet'!D81 -> 42825 | E3: ='Data Sheet'!E81 -> 43190 | F3: ='Data Sheet'!F81 -> 43555 | G3: ='Data Sheet'!G81 -> 43921 | H3: ='Data Sheet'!H81 -> 44286 | I3: ='Data Sheet'!I81 -> 44651 | ... K3: ='Data Sheet'!K81 -> 45382
A4: Cash from Operating Activity | B4: ='Data Sheet'!B82 -> 1047.21 | C4: ='Data Sheet'!C82 -> 1186.99 | D4: ='Data Sheet'!D82 -> 1226.94 | E4: ='Data Sheet'!E82 -> 1091.5 | F4: ='Data Sheet'!F82 -> 1499.13 | G4: ='Data Sheet'!G82 -> 1613.62 | H4: ='Data Sheet'!H82 -> 2114.67 | I4: ='Data Sheet'!I82 -> 1802.33 | ... K4: ='Data Sheet'!K82 -> 2013.47
A5: Cash from Investing Activity | B5: ='Data Sheet'!B83 -> -875.9 | C5: ='Data Sheet'!C83 -> -730.33 | D5: ='Data Sheet'!D83 -> -807.07 | E5: ='Data Sheet'!E83 -> -540.93 | F5: ='Data Sheet'!F83 -> 337.58 | G5: ='Data Sheet'!G83 -> -516.63 | H5: ='Data Sheet'!H83 -> -1404.22 | I5: ='Data Sheet'!I83 -> -1273.45 | ... K5: ='Data Sheet'!K83 -> -971.04
A6: Cash from Financing Activity | B6: ='Data Sheet'!B84 -> -416.77 | C6: ='Data Sheet'!C84 -> -374.31 | D6: ='Data Sheet'!D84 -> -338.97 | E6: ='Data Sheet'!E84 -> -577.11 | F6: ='Data Sheet'!F84 -> -1888.2 | G6: ='Data Sheet'!G84 -> -1042.97 | H6: ='Data Sheet'!H84 -> -613.41 | I6: ='Data Sheet'!I84 -> -490.49 | ... K6: ='Data Sheet'!K84 -> -1161.18
A7: Net Cash Flow | B7: ='Data Sheet'!B85 -> -245.46 | C7: ='Data Sheet'!C85 -> 82.35 | D7: ='Data Sheet'!D85 -> 80.9 | E7: ='Data Sheet'!E85 -> -26.54 | F7: ='Data Sheet'!F85 -> -51.49 | G7: ='Data Sheet'!G85 -> 54.02 | H7: ='Data Sheet'!H85 -> 97.04 | I7: ='Data Sheet'!I85 -> 38.39 | ... K7: ='Data Sheet'!K85 -> -118.75

Sheet Customization
A1: How to use it?
A3: You can customize this workbook as you want.
B4: You can add custom formating, add conditional formating, add your own formulas… do ANYTHING.
B5: Please don't edit the "Data Sheet" only.
A7: After customization, you can upload this back on Screener.
B8: Upload on: | C8: https://www.screener.in/excel/
A10: Download your customized workbooks now onwards.
B11: Now whenever you will "Export to excel" from Screener, it will export your customized file.
A14: TESTING:
B15: This is a testing feature currently.
B16: You can report any formula errors on the worksheet at: support@screener.in

Sheet Data Room>

Sheet Raw FS
B2: Particulars | C2: 42064 | D2: 42430 | E2: 42795 | F2: 43160 | G2: 43525 | H2: 43891 | I2: 44256 | J2: 44621 | K2: 44986 | L2: 45352
B3: Equity Capital | C3: 176 | D3: 176 | E3: 176 | F3: 176 | G3: 177 | H3: 177 | I3: 177 | J3: 177 | K3: 177 | L3: 177
B4: Reserves | C4: 3178 | D4: 3995 | E4: 4671 | F4: 5530 | G4: 5455 | H4: 6429 | I4: 7487 | J4: 8205 | K4: 8796 | L4: 9689
B5: Borrowings -
B6: Short Term Borrowing | C6: 211 | D6: 342 | E6: 470 | F6: 364 | G6: 26 | H6: 163 | I6: 1 | J6: 250 | K6: 299 | L6: 536
B7: Long Term Borrowing | C7: 523 | D7: 450 | E7: 440 | F7: 464 | G7: 498 | H7: 304 | I7: 349 | J7: 617 | K7: 700 | L7: 622
B8: Lease Liabilities | C8: 0 | D8: 0 | E8: 0 | F8: 0 | G8: 0 | H8: 0 | I8: 159 | J8: 162 | K8: 175 | L8: 207
B9: Other Borrowings | C9: 0 | D9: 13 | E9: 64 | F9: 109 | G9: 175 | H9: 55 | I9: 0 | J9: 0 | K9: 0 | L9: 0
B10: Other Liabilities -
B11: Non controlling int | C11: 18 | D11: 22 | E11: 25 | F11: 27 | G11: 31 | H11: 36 | I11: 37 | J11: 41 | K11: 468 | L11: 437 | O11: If this sheet is touched then its over for me
B12: Trade Payables | C12: 1096 | D12: 1330 | E12: 1310 | F12: 1410 | G12: 1455 | H12: 1482 | I12: 1915 | J12: 2018 | K12: 2187 | L12: 2422
B13: Advance from Customers | C13: 42 | D13: 35 | E13: 18 | F13: 25 | G13: 28 | H13: 30 | I13: 43 | J13: 37 | K13: 9 | L13: 33
B14: Other liability items | C14: 863 | D14: 569 | E14: 557 | F14: 596 | G14: 591 | H14: 660 | I14: 666 | J14: 777 | K14: 842 | L14: 994
B15: Total Liabilities | C15: =SUM(C3:C14) -> 6107 | D15: =SUM(D3:D14) -> 6932 | E15: =SUM(E3:E14) -> 7731 | F15: =SUM(F3:F14) -> 8701 | G15: =SUM(G3:G14) -> 8436 | H15: =SUM(H3:H14) -> 9336 | I15: =SUM(I3:I14) -> 10834 | J15: =SUM(J3:J14) -> 12284 | ... L15: =SUM(L3:L14) -> 15117
B17: Fixed Assets -
B18: Land | C18: 92 | D18: 80 | E18: 98 | F18: 108 | G18: 108 | H18: 103 | I18: 93 | J18: 123 | K18: 141 | L18: 145
B19: Building | C19: 622 | D19: 629 | E19: 714 | F19: 763 | G19: 788 | H19: 1054 | I19: 1057 | J19: 1144 | K19: 1279 | L19: 1513
B20: Plant Machinery | C20: 985 | D20: 1122 | E20: 1303 | F20: 1431 | G20: 1527 | H20: 1719 | I20: 1862 | J20: 2074 | K20: 2408 | L20: 2775
B21: Equipments | C21: 53 | D21: 58 | E21: 62 | F21: 59 | G21: 68 | H21: 69 | I21: 73 | J21: 78 | K21: 88 | L21: 93
B22: Furniture n fittings | C22: 81 | D22: 89 | E22: 94 | F22: 104 | G22: 113 | H22: 126 | I22: 129 | J22: 134 | K22: 148 | L22: 159
B23: Vehicles | C23: 31 | D23: 35 | E23: 35 | F23: 42 | G23: 44 | H23: 45 | I23: 45 | J23: 47 | K23: 43 | L23: 44
B24: Intangible Assets | C24: 634 | D24: 425 | E24: 425 | F24: 426 | G24: 367 | H24: 374 | I24: 375 | J24: 291 | K24: 1322 | L24: 1321 | O24: `
B25: Other fixed assets | C25: 43 | D25: 46 | E25: 112 | F25: 113 | G25: 125 | H25: 139 | I25: 146 | J25: 149 | K25: 154 | L25: 164
B26: Gross Block | C26: 2541 | D26: 2484 | E26: 2843 | F26: 3046 | G26: 3139 | H26: 3629 | I26: 3779 | J26: 4041 | K26: 5583 | L26: 6215
B27: Accumulated Depreciation | C27: 664 | D27: 816 | E27: 884 | F27: 1018 | G27: 1170 | H27: 1377 | I27: 1536 | J27: 1733 | K27: 2004 | L27: 2400
B28: CWIP | C28: 50 | D28: 45 | E28: 42 | F28: 42 | G28: 64 | H28: 147 | I28: 147 | J28: 168 | K28: 175 | L28: 232
B29: Investments | C29: 1813 | D29: 2691 | E29: 3240 | F29: 3805 | G29: 3359 | H29: 2800 | I29: 4160 | J29: 6220 | K29: 6265 | L29: 6933
B30: Other Assets -
B31: Inventories | C31: 973 | D31: 1096 | E31: 1107 | F31: 1256 | G31: 1301 | H31: 1380 | I31: 1734 | J31: 1911 | K31: 2024 | L31: 1947
B32: Trade receivables | C32: 711 | D32: 809 | E32: 650 | F32: 706 | G32: 834 | H32: 814 | I32: 562 | J32: 646 | K32: 849 | L32: 899
B33: Cash Equivalents | C33: 276 | D33: 220 | E33: 305 | F33: 306 | G33: 328 | H33: 811 | I33: 1329 | J33: 570 | K33: 326 | L33: 666
B34: Short term loans | C34: 63 | D34: 19 | E34: 14 | F34: 17 | G34: 22 | H34: 23 | I34: 20 | J34: 24 | K34: 33 | L34: 45
B35: Other asset items | C35: 343 | D35: 385 | E35: 416 | F35: 542 | G35: 561 | H35: 1109 | I35: 639 | J35: 437 | K35: 401 | L35: 579
B36: Total Assets | C36: =C15 -> 6107 | D36: =D15 -> 6932 | E36: =E15 -> 7731 | F36: =F15 -> 8701 | G36: =G15 -> 8436 | H36: =H15 -> 9336 | I36: =I15 -> 10834 | J36: =J15 -> 12284 | ... L36: =L15 -> 15117
B38: Cash Flow Statements
B39: Particulars | E39: 42064 | F39: 42430 | G39: 42795 | H39: 43160 | I39: 43525 | J39: 43891 | K39: 44256 | L39: 44621 | M39: 44986 | N39: 45352
B40: Cash from operating activities | E40: 1047 | F40: 1187 | G40: 1227 | H40: 1092 | I40: 1499 | J40: 1614 | K40: 2115 | L40: 1802 | M40: 1488 | N40: 2013
B41: Profit from operations | E41: 1394 | F41: 1543 | G41: 1462 | H41: 1678 | I41: 1868 | J41: 1981 | K41: 2048 | L41: 2287 | M41: 2143 | N41: 2406
B42: Receivables | E42: -142 | F42: -14 | G42: 115 | H42: -60 | I42: -130 | J42: 14 | K42: 248 | L42: -78 | M42: -191 | N42: -55
B43: Inventory | E43: -1 | F43: -123 | G43: -10 | H43: -149 | I43: -44 | J43: -79 | K43: -355 | L43: -177 | M43: -96 | N43: 77
B44: Payables | E44: 26 | F44: 62 | G44: -16 | H44: 86 | I44: 45 | J44: 26 | K44: 434 | L44: 108 | M44: 141 | N44: 217
B45: Other WC items | E45: 0 | F45: 0 | G45: -1 | H45: -138 | I45: 111 | J45: -19 | K45: 62 | L45: 51 | M45: -15 | N45: -137
B46: Working capital changes | E46: -117 | F46: -75 | G46: 87 | H46: -262 | I46: -18 | J46: -58 | K46: 388 | L46: -97 | M46: -160 | N46: 101
B47: Direct taxes | E47: -230 | F47: -281 | G47: -322 | H47: -325 | I47: -351 | J47: -309 | K47: -321 | L47: -388 | M47: -494 | N47: -494
B49: Cash from Investing Activity - | E49: =SUM(E50:E56) -> -876 | F49: =SUM(F50:F56) -> -730 | G49: =SUM(G50:G56) -> -807 | H49: =SUM(H50:H56) -> -540 | I49: =SUM(I50:I56) -> 337 | J49: =SUM(J50:J56) -> -517 | K49: =SUM(K50:K56) -> -1403 | L49: =SUM(L50:L56) -> -1273 | ... N49: =SUM(N50:N56) -> -971
B50: Fixed assets purchased | E50: -267 | F50: -200 | G50: -490 | H50: -207 | I50: -234 | J50: -417 | K50: -311 | L50: -374 | M50: -509 | N50: -564
B51: Fixed assets sold | E51: 16 | F51: 11 | G51: 4 | H51: 7 | I51: 9 | J51: 17 | K51: 5 | L51: 5 | M51: 23 | N51: 3
B52: Investments purchased | E52: -6317 | F52: -7341 | G52: -9111 | H52: -9001 | I52: -5393 | J52: -8479 | K52: -7635 | L52: -7507 | M52: -4177 | N52: -5142
B53: Investments sold | E53: 5596 | F53: 6653 | G53: 8600 | H53: 8418 | I53: 5710 | J53: 8114 | K53: 6274 | L53: 6234 | M53: 4164 | N53: 4344
B54: Interest received | E54: 96 | F54: 148 | G54: 190 | H54: 244 | I54: 244 | J54: 248 | K54: 262 | L54: 367 | M54: 394 | N54: 387
B55: Invest in subsidiaries | E55: 0 | F55: 0 | G55: 0 | H55: 0 | I55: 0 | J55: 0 | K55: 0 | L55: 0 | M55: -481 | N55: 0
B56: Other investing items | E56: 0 | F56: -1 | G56: 0 | H56: -1 | I56: 1 | J56: 0 | K56: 2 | L56: 2 | M56: 4 | N56: 1
B58: Cash from Financing Activity - | E58: =SUM(E59:E65) -> -417 | F58: =SUM(F59:F65) -> -376 | G58: =SUM(G59:G65) -> -339 | H58: =SUM(H59:H65) -> -578 | I58: =SUM(I59:I65) -> -1889 | J58: =SUM(J59:J65) -> -1042 | K58: =SUM(K59:K65) -> -614 | L58: =SUM(L59:L65) -> -490 | ... N58: =SUM(N59:N65) -> -1161
B59: Proceeds from shares | E59: 46 | F59: 17 | G59: 15 | H59: 0 | I59: 0 | J59: 0 | K59: 0 | L59: 0 | M59: 0 | N59: 0
B60: Proceeds from borrowings | E60: 75 | F60: 131 | G60: 168 | H60: 4 | I60: 32 | J60: 0 | K60: 65 | L60: 541 | M60: 935 | N60: 631
B61: Repayment of borrowings | E61: -50 | F61: -60 | G61: 0 | H61: -62 | I61: -272 | J61: -358 | K61: -28 | L61: 0 | M61: -886 | N61: -678
B62: Interest paid fin | E62: -26 | F62: -40 | G62: -45 | H62: -43 | I62: -52 | J62: -42 | K62: -31 | L62: -33 | M62: -89 | N62: -119
B63: Dividends paid | E63: -395 | F63: -352 | G63: -396 | H63: -396 | I63: -1325 | J63: -512 | K63: -592 | L63: -972 | M63: -921 | N63: -966
B64: Financial liabilities | E64: 0 | F64: 0 | G64: 0 | H64: 0 | I64: 0 | J64: -25 | K64: -28 | L64: -26 | M64: -25 | N64: -29
B65: Other financing items | E65: -67 | F65: -72 | G65: -81 | H65: -81 | I65: -272 | J65: -105 | K65: 0 | L65: 0 | M65: -49 | N65: 0
B67: Net Cash Flow | E67: -245 | F67: 82 | G67: 81 | H67: -27 | I67: -51 | J67: 54 | K67: 97 | L67: 38 | M67: -130 | N67: -119
B70: Comps Data
B72: S.No. | C72: Name | D72: CMP Rs. | E72: No. Eq. Shares Cr. | F72: Debt Rs.Cr. | G72: Cash End Rs.Cr. | H72: EV Rs.Cr. | I72: Sales Rs.Cr. | J72: EBITDA Cr. | K72: NP 12M Rs.Cr. | L72: Mar Cap Rs.Cr. | M72: Net Debt
B73: 1 | C73: Hind. Unilever | D73: 2966.25 | E73: 234.96 | F73: 1484 | G73: 7559 | H73: 690872.51 | I73: 62107 | J73: 23528 | K73: 10338 | L73: 696947.51 | M73: =F73-G73 -> -6075
B74: 2 | C74: Nestle India | D74: 2745.7 | E74: 96.42 | F74: 344.53 | G74: 778.85 | H74: 264294.31 | I74: 19718.78 | J74: 6592.39 | K74: 3244.46 | L74: 264728.63 | M74: =F74-G74 -> -434.32
B75: 3 | C75: Varun Beverages | D75: 608.55 | E75: 324.87 | F75: 6760.92 | G75: 459.86 | H75: 204051.43 | I75: 18052.38 | J75: 3820.07 | K75: 2467.63 | L75: 197698.26 | M75: =F75-G75 -> 6301.06
B76: 4 | C76: Britannia Inds. | D76: 6268.8 | E76: 24.09 | F76: 2064.96 | G76: 446.35 | H76: 152614.13 | I76: 17008.86 | J76: 4874.5 | K76: 2183.65 | L76: 150995.52 | M76: =F76-G76 -> 1618.61
B77: 5 | C77: Godrej Consumer | D77: 1388.65 | E77: 102.29 | F77: 3222.2 | G77: 546.94 | H77: 144719.57 | I77: 13978.78 | J77: 3087.87 | K77: -428.69 | L77: 142044.31 | M77: =F77-G77 -> 2675.26
B78: 6 | C78: Dabur India | D78: 633 | E78: 177.23 | F78: 1365.09 | G78: 666.36 | H78: 112886.04 | I78: 12622.65 | J78: 3461.7 | K78: 1849.05 | L78: 112187.31 | M78: =F78-G78 -> 698.73
B79: 7 | C79: Colgate-Palmoliv | D79: 3764.05 | E79: 27.2 | F79: 71.75 | G79: 1373.78 | H79: 101074.72 | I79: 5853.46 | J79: 2967.52 | K79: 1413.96 | L79: 102376.75 | M79: =F79-G79 -> -1302.03
B80: 8 | C80: P & G Hygiene | D80: 16413.15 | E80: 3.25 | F80: 3.08 | G80: 588.2 | H80: 52693.17 | I80: 4205.7 | J80: 1566.49 | K80: 675.02 | L80: 53278.29 | M80: =F80-G80 -> -585.12
B81: 9 | C81: Emami | D81: 751.65 | E81: 43.65 | F81: 93.95 | G81: 201.38 | H81: 32702.09 | I81: 3658.5 | J81: 1188.32 | K81: 737.99 | L81: 32809.52 | M81: =F81-G81 -> -107.43
B82: 10 | C82: Gillette India | D82: 8490.55 | E82: 3.26 | F82: 0.05 | G82: 475.63 | H82: 27195.12 | I82: 2633.08 | J82: 847.9 | K82: 411.7 | L82: 27670.7 | M82: =F82-G82 -> -475.58

Sheet Data Sheet
A1: COMPANY NAME | B1: DABUR INDIA LTD | E1: =IF(B2<>B3, "A NEW VERSION OF THE WORKSHEET IS AVAILABLE", "")
A2: LATEST VERSION | B2: 2.1 | E2: PLEASE DO NOT MAKE ANY CHANGES TO THIS SHEET
A3: CURRENT VERSION | B3: 2.1
A5: META
A6: Number of shares | B6: =IF(B9>0, B9/B8, 0) -> 177.23104
A7: Face Value | B7: 1
A8: Current Price | B8: 625.7
A9: Market Capitalization | B9: 110893.46
A15: PROFIT & LOSS
A16: Report Date | B16: 42094 | C16: 42460 | D16: 42825 | E16: 43190 | F16: 43555 | G16: 43921 | H16: 44286 | I16: 44651 | J16: 45016 | K16: 45382
A17: Sales | B17: 7795.49 | C17: 7779.66 | D17: 7613.59 | E17: 7721.85 | F17: 8514.99 | G17: 8684.64 | H17: 9561.65 | I17: 10888.68 | J17: 11529.89 | K17: 12404.01
A18: Raw Material Cost | B18: 2633.97 | C18: 2739.77 | D18: 2659.55 | E18: 2775.35 | F18: 3067.95 | G18: 3138.49 | H18: 3764.3 | I18: 4136.7 | J18: 4762.03 | K18: 4714.88
A19: Change in Inventory | B19: 25.91 | C19: 70.53 | D19: 23.02 | E19: 65.93 | F19: -12.64 | G19: 65.04 | H19: 207.2 | I19: 8.55 | J19: 90.79 | K19: -48.95
A20: Power and Fuel | B20: 90.35 | C20: 84 | D20: 87.48 | E20: 93.91 | F20: 105.26 | G20: 107.12 | H20: 104.01 | I20: 128.66 | J20: 150.59 | K20: 153.44
A21: Other Mfr. Exp | B21: 1208.32 | C21: 1180.31 | D21: 1247.42 | E21: 1219 | F21: 1327.63 | G21: 1387.98 | H21: 1347.34 | I21: 1656.53 | J21: 1779.91 | K21: 1856.5
A22: Employee Cost | B22: 690.17 | C22: 794.1 | D22: 790.3 | E22: 793.36 | F22: 938.55 | G22: 949.16 | H22: 1034.9 | I22: 1081.39 | J22: 1138.43 | K22: 1241.06
A23: Selling and admin | B23: 1640.96 | C23: 1217.44 | D23: 1161.4 | E23: 1135.38 | F23: 1183.56 | G23: 1224.59 | H23: 1388.27 | I23: 1480.71 | J23: 1426.95 | K23: 1779.99
A24: Other Expenses | B24: 237.41 | C24: 316.29 | D24: 178.85 | E24: 153.34 | F24: 139.84 | G24: 150 | H24: 128.36 | I24: 161.23 | J24: 200.28 | K24: 209.47
A25: Other Income | B25: 154.24 | C25: 217.19 | D25: 295.93 | E25: 290.88 | F25: 221.79 | G25: 205.29 | H25: 325.29 | I25: 308.16 | J25: 445.39 | K25: 482.41
A26: Depreciation | B26: 114.98 | C26: 133.19 | D26: 142.86 | E26: 162.18 | F26: 176.9 | G26: 220.45 | H26: 240.13 | I26: 252.89 | J26: 310.96 | K26: 399.21
A27: Interest | B27: 40.12 | C27: 48.48 | D27: 54.03 | E27: 53.05 | F27: 59.58 | G27: 49.54 | H27: 30.81 | I27: 38.6 | J27: 78.24 | K27: 124.18
... A31: Dividend Amount | B31: 351.3 | C31: 395.8 | D31: 396.34 | E31: 1100.94 | F31: 485.73 | G31: 530.13 | H31: 839.52 | I31: 919.31 | J31: 921.34 | K31: 974.6
A40: Quarters
A41: Report Date | B41: 44651 | C41: 44742 | D41: 44834 | E41: 44926 | F41: 45016 | G41: 45107 | H41: 45199 | I41: 45291 | J41: 45382 | K41: 45473
A42: Sales | B42: 2517.81 | C42: 2822.43 | D42: 2986.49 | E42: 3043.17 | F42: 2677.8 | G42: 3130.47 | H42: 3203.84 | I42: 3255.06 | J42: 2814.64 | K42: 3349.11
A43: Expenses | B43: 2065.44 | C43: 2279.11 | D43: 2386.09 | E43: 2434.05 | F43: 2268.15 | G43: 2525.94 | H43: 2542.97 | I43: 2587.64 | J43: 2348.23 | K43: 2694.28
A44: Other Income | B44: 14.14 | C44: 100.55 | D44: 123.28 | E44: 100.84 | F44: 120.72 | G44: 109.78 | H44: 116.9 | I44: 127.37 | J44: 128.85 | K44: 129.4
A45: Depreciation | B45: 65.05 | C45: 67.6 | D45: 70.47 | E45: 70.89 | F45: 102 | G45: 96.64 | H45: 98.32 | I45: 96.89 | J45: 107.36 | K45: 109.12
A46: Interest | B46: 11.75 | C46: 12.15 | D46: 15.06 | E46: 18.91 | F46: 32.12 | G46: 24.31 | H46: 28.14 | I46: 36.49 | J46: 35.24 | K46: 32.66
A47: Profit before tax | B47: 389.71 | C47: 564.12 | D47: 638.15 | E47: 620.16 | F47: 396.25 | G47: 593.36 | H47: 651.31 | I47: 661.41 | J47: 452.66 | K47: 642.45
A48: Tax | B48: 95.37 | C48: 123.06 | D48: 147.29 | E48: 143.51 | F48: 103.49 | G48: 136.75 | H48: 144.27 | I48: 154.97 | J48: 111.44 | K48: 148.1
A49: Net profit | B49: 294.22 | C49: 440.32 | D49: 490.06 | E49: 475.94 | F49: 300.83 | G49: 463.88 | H49: 515.05 | I49: 514.22 | J49: 349.53 | K49: 500.12
A50: Operating Profit | B50: 452.37 | C50: 543.32 | D50: 600.4 | E50: 609.12 | F50: 409.65 | G50: 604.53 | H50: 660.87 | I50: 667.42 | J50: 466.41 | K50: 654.83
A55: BALANCE SHEET
A56: Report Date | B56: 42094 | C56: 42460 | D56: 42825 | E56: 43190 | F56: 43555 | G56: 43921 | H56: 44286 | I56: 44651 | J56: 45016 | K56: 45382
A57: Equity Share Capital | B57: 175.65 | C57: 175.91 | D57: 176.15 | E57: 176.15 | F57: 176.63 | G57: 176.71 | H57: 176.74 | I57: 176.79 | J57: 177.18 | K57: 177.2
A58: Reserves | B58: 3178.49 | C58: 3994.7 | D58: 4671.24 | E58: 5530.37 | F58: 5455.05 | G58: 6429.04 | H58: 7486.79 | I58: 8204.51 | J58: 8796.08 | K58: 9689.1
A59: Borrowings | B59: 733.56 | C59: 805.22 | D59: 975 | E59: 937.59 | F59: 699.37 | G59: 521.99 | H59: 509.06 | I59: 1030.1 | J59: 1173.79 | K59: 1365.09
A60: Other Liabilities | B60: 2018.58 | C60: 1956.47 | D60: 1909.85 | E60: 2057.52 | F60: 2105.59 | G60: 2208.84 | H60: 2660.63 | I60: 2872.46 | J60: 3505.23 | K60: 3884.97
A61: Total | B61: 6106.28 | C61: 6932.3 | D61: 7732.24 | E61: 8701.63 | F61: 8436.64 | G61: 9336.58 | H61: 10833.22 | I61: 12283.86 | J61: 13652.28 | K61: 15116.36
A62: Net Block | B62: 1877.13 | C62: 1667.4 | D62: 1958.4 | E62: 2028.11 | F62: 1969.06 | G62: 2252.68 | H62: 2242.92 | I62: 2307.9 | J62: 3578.65 | K62: 3815
A63: Capital Work in Progress | B63: 50.3 | C63: 44.8 | D63: 42.1 | E63: 41.51 | F63: 63.76 | G63: 146.57 | H63: 147.3 | I63: 167.5 | J63: 175.13 | K63: 232.23
A64: Investments | B64: 1813.37 | C64: 2690.74 | D64: 3240.16 | E64: 3805.17 | F64: 3358.76 | G64: 2800.26 | H64: 4159.63 | I64: 6219.62 | J64: 6265.26 | K64: 6932.69
A65: Other Assets | B65: 2365.48 | C65: 2529.36 | D65: 2491.58 | E65: 2826.84 | F65: 3045.06 | G65: 4137.07 | H65: 4283.37 | I65: 3588.84 | J65: 3633.24 | K65: 4136.44
A66: Total | B66: 6106.28 | C66: 6932.3 | D66: 7732.24 | E66: 8701.63 | F66: 8436.64 | G66: 9336.58 | H66: 10833.22 | I66: 12283.86 | J66: 13652.28 | K66: 15116.36
A67: Receivables | B67: 710.84 | C67: 809.2 | D67: 650.42 | E67: 706.08 | F67: 833.56 | G67: 813.89 | H67: 561.58 | I67: 646.15 | J67: 848.75 | K67: 898.72
... A70: No. of Equity Shares | B70: 1756511990 | C70: 1759141170 | D70: 1761520510 | E70: 1761520510 | F70: 1766291141 | G70: 1767063892 | H70: 1767425349 | I70: 1767856483 | J70: 1767856483 | K70: 1772039162
A71: New Bonus Shares
A72: Face value | B72: 1 | C72: 1 | D72: 1 | E72: 1 | F72: 1 | G72: 1 | H72: 1 | I72: 1 | J72: 1 | K72: 1
A75: Other Assets | B75: =B65-SUM(B67:B69) -> 405.33 | C75: =C65-SUM(C67:C69) -> 403.84 | D75: =D65-SUM(D67:D69) -> 429.64 | E75: =E65-SUM(E67:E69) -> 558.52 | F75: =F65-SUM(F67:F69) -> 582.81 | G75: =G65-SUM(G67:G69) -> 1132.24 | H75: =H65-SUM(H67:H69) -> 658.48 | I75: =I65-SUM(I67:I69) -> 461.18 | ... K75: =K65-SUM(K67:K69) -> 624.39
A77: book Value | B77: =B58+B57 -> 3354.14 | C77: =C58+C57 -> 4170.61 | D77: =D58+D57 -> 4847.39 | E77: =E58+E57 -> 5706.52 | F77: =F58+F57 -> 5631.68 | G77: =G58+G57 -> 6605.75 | H77: =H58+H57 -> 7663.53 | I77: =I58+I57 -> 8381.3 | ... K77: =K58+K57 -> 9866.3
A80: CASH FLOW:
A81: Report Date | B81: 42094 | C81: 42460 | D81: 42825 | E81: 43190 | F81: 43555 | G81: 43921 | H81: 44286 | I81: 44651 | J81: 45016 | K81: 45382
A82: Cash from Operating Activity | B82: 1047.21 | C82: 1186.99 | D82: 1226.94 | E82: 1091.5 | F82: 1499.13 | G82: 1613.62 | H82: 2114.67 | I82: 1802.33 | J82: 1488.43 | K82: 2013.47
A83: Cash from Investing Activity | B83: -875.9 | C83: -730.33 | D83: -807.07 | E83: -540.93 | F83: 337.58 | G83: -516.63 | H83: -1404.22 | I83: -1273.45 | J83: -582.79 | K83: -971.04
A84: Cash from Financing Activity | B84: -416.77 | C84: -374.31 | D84: -338.97 | E84: -577.11 | F84: -1888.2 | G84: -1042.97 | H84: -613.41 | I84: -490.49 | J84: -1035.24 | K84: -1161.18
A85: Net Cash Flow | B85: -245.46 | C85: 82.35 | D85: 80.9 | E85: -26.54 | F85: -51.49 | G85: 54.02 | H85: 97.04 | I85: 38.39 | J85: -129.6 | K85: -118.75
A90: PRICE: | B90: 265.55 | C90: 249.9 | D90: 277.35 | E90: 328.4 | F90: 408.8 | G90: 450.05 | H90: 540.5 | I90: 536.2 | J90: 544.9 | K90: 523.15
A92: DERIVED:
A93: Adjusted Equity Shares in Cr | B93: 175.65 | C93: 175.91 | D93: 176.15 | E93: 176.15 | F93: 176.63 | G93: 176.71 | H93: 176.74 | I93: 176.79 | J93: 177.18 | K93: 177.2
A97: Enterprise Value | B97: =B93*B90 -> 46643.858 | C97: =C93*C90 -> 43959.909 | D97: =D93*D90 -> 48855.203 | E97: =E93*E90 -> 57847.66 | F97: =F93*F90 -> 72206.344 | G97: =G93*G90 -> 79528.336 | H97: =H93*H90 -> 95527.97 | I97: =I93*I90 -> 94794.798 | ... K97: =K93*K90 -> 92702.18

Sheet Financials>

Sheet Historical FS
B2: DABUR INDIA LTD
B4: BSE : 500096 | NSE : DABUR
B6: ="Financial Statement Analysis - " & 'Data Sheet'!B1 -> Financial Statement Analysis - DABUR INDIA LTD
B7: Years | C7: ='Data Sheet'!B16 -> 42094 | D7: ='Data Sheet'!C16 -> 42460 | E7: ='Data Sheet'!D16 -> 42825 | F7: ='Data Sheet'!E16 -> 43190 | G7: ='Data Sheet'!F16 -> 43555 | H7: ='Data Sheet'!G16 -> 43921 | I7: ='Data Sheet'!H16 -> 44286 | J7: ='Data Sheet'!I16 -> 44651 | ... L7: ='Data Sheet'!K16 -> 45382 | M7: LTM
A9: # | B9: Income Statement
B10: Sales | C10: =IFERROR('Data Sheet'!B17,0) -> 7795.49 | D10: =IFERROR('Data Sheet'!C17,0) -> 7779.66 | E10: =IFERROR('Data Sheet'!D17,0) -> 7613.59 | F10: =IFERROR('Data Sheet'!E17,0) -> 7721.85 | G10: =IFERROR('Data Sheet'!F17,0) -> 8514.99 | H10: =IFERROR('Data Sheet'!G17,0) -> 8684.64 | I10: =IFERROR('Data Sheet'!H17,0) -> 9561.65 | J10: =IFERROR('Data Sheet'!I17,0) -> 10888.68 | ... L10: =IFERROR('Data Sheet'!K17,0) -> 12404.01
B11: Sales Growth | C11: - | D11: =D10/C10-1 -> -0.0020306613 | E11: =E10/D10-1 -> -0.021346691 | F11: =F10/E10-1 -> 0.01421931 | G11: =G10/F10-1 -> 0.10271373 | H11: =H10/G10-1 -> 0.019923688 | I11: =I10/H10-1 -> 0.10098404 | J11: =J10/I10-1 -> 0.13878672 | K11: =K10/J10-1 -> 0.058887762 | L11: =L10/K10-1 -> 0.075813386
B13: COGS | C13: =IFERROR(SUM('Data Sheet'!B18,'Data Sheet'!B20:B22)-1*'Data Sheet'!B19,0) -> 4596.9 | D13: =IFERROR(SUM('Data Sheet'!C18,'Data Sheet'!C20:C22)-1*'Data Sheet'!C19,0) -> 4727.65 | E13: =IFERROR(SUM('Data Sheet'!D18,'Data Sheet'!D20:D22)-1*'Data Sheet'!D19,0) -> 4761.73 | F13: =IFERROR(SUM('Data Sheet'!E18,'Data Sheet'!E20:E22)-1*'Data Sheet'!E19,0) -> 4815.69 | G13: =IFERROR(SUM('Data Sheet'!F18,'Data Sheet'!F20:F22)-1*'Data Sheet'!F19,0) -> 5452.03 | H13: =IFERROR(SUM('Data Sheet'!G18,'Data Sheet'!G20:G22)-1*'Data Sheet'!G19,0) -> 5517.71 | I13: =IFERROR(SUM('Data Sheet'!H18,'Data Sheet'!H20:H22)-1*'Data Sheet'!H19,0) -> 6043.35 | J13: =IFERROR(SUM('Data Sheet'!I18,'Data Sheet'!I20:I22)-1*'Data Sheet'!I19,0) -> 6994.73 | ... L13: =IFERROR(SUM('Data Sheet'!K18,'Data Sheet'!K20:K22)-1*'Data Sheet'!K19,0) -> 8014.83
B14: COGS % Sales | C14: =C13/C10 -> 0.58968711 | D14: =D13/D10 -> 0.60769365 | E14: =E13/E10 -> 0.62542506 | F14: =F13/F10 -> 0.62364459 | G14: =G13/G10 -> 0.64028613 | H14: =H13/H10 -> 0.63534125 | I14: =I13/I10 -> 0.6320405 | J14: =J13/J10 -> 0.64238549 | ... L14: =L13/L10 -> 0.6461483
B16: Gross Profit | C16: =C10-C13 -> 3198.59 | D16: =D10-D13 -> 3052.01 | E16: =E10-E13 -> 2851.86 | F16: =F10-F13 -> 2906.16 | G16: =G10-G13 -> 3062.96 | H16: =H10-H13 -> 3166.93 | I16: =I10-I13 -> 3518.3 | J16: =J10-J13 -> 3893.95 | ... L16: =L10-L13 -> 4389.18
B17: Gross Profit % Sales | C17: =C16/C10 -> 0.41031289 | D17: =D16/D10 -> 0.39230635 | E17: =E16/E10 -> 0.37457494 | F17: =F16/F10 -> 0.37635541 | G17: =G16/G10 -> 0.35971387 | H17: =H16/H10 -> 0.36465875 | I17: =I16/I10 -> 0.3679595 | J17: =J16/J10 -> 0.35761451 | ... L17: =L16/L10 -> 0.3538517
B19: Selling & General Expenses | C19: =IFERROR(SUM('Data Sheet'!B23:B24),0) -> 1878.37 | D19: =IFERROR(SUM('Data Sheet'!C23:C24),0) -> 1533.73 | E19: =IFERROR(SUM('Data Sheet'!D23:D24),0) -> 1340.25 | F19: =IFERROR(SUM('Data Sheet'!E23:E24),0) -> 1288.72 | G19: =IFERROR(SUM('Data Sheet'!F23:F24),0) -> 1323.4 | H19: =IFERROR(SUM('Data Sheet'!G23:G24),0) -> 1374.59 | I19: =IFERROR(SUM('Data Sheet'!H23:H24),0) -> 1516.63 | J19: =IFERROR(SUM('Data Sheet'!I23:I24),0) -> 1641.94 | ... L19: =IFERROR(SUM('Data Sheet'!K23:K24),0) -> 1989.46
B20: S&G Expenses % Sales | C20: =C19/C10 -> 0.24095599 | D20: =D19/D10 -> 0.19714615 | E20: =E19/E10 -> 0.17603391 | F20: =F19/F10 -> 0.16689265 | G20: =G19/G10 -> 0.15542003 | H20: =H19/H10 -> 0.15827829 | I20: =I19/I10 -> 0.15861593 | J20: =J19/J10 -> 0.1507933 | ... L20: =L19/L10 -> 0.16038846
B22: EBITDA | C22: =C16-C19 -> 1320.22 | D22: =D16-D19 -> 1518.28 | E22: =E16-E19 -> 1511.61 | F22: =F16-F19 -> 1617.44 | G22: =G16-G19 -> 1739.56 | H22: =H16-H19 -> 1792.34 | I22: =I16-I19 -> 2001.67 | J22: =J16-J19 -> 2252.01 | ... L22: =L16-L19 -> 2399.72
B23: EBITDA Margins | C23: =C22/C10 -> 0.1693569 | D23: =D22/D10 -> 0.1951602 | E23: =E22/E10 -> 0.19854103 | F23: =F22/F10 -> 0.20946276 | G23: =G22/G10 -> 0.20429384 | H23: =H22/H10 -> 0.20638046 | I23: =I22/I10 -> 0.20934358 | J23: =J22/J10 -> 0.20682121 | ... L23: =L22/L10 -> 0.19346324
B25: Interest | C25: =IFERROR('Data Sheet'!B27,0) -> 40.12 | D25: =IFERROR('Data Sheet'!C27,0) -> 48.48 | E25: =IFERROR('Data Sheet'!D27,0) -> 54.03 | F25: =IFERROR('Data Sheet'!E27,0) -> 53.05 | G25: =IFERROR('Data Sheet'!F27,0) -> 59.58 | H25: =IFERROR('Data Sheet'!G27,0) -> 49.54 | I25: =IFERROR('Data Sheet'!H27,0) -> 30.81 | J25: =IFERROR('Data Sheet'!I27,0) -> 38.6 | ... L25: =IFERROR('Data Sheet'!K27,0) -> 124.18
B26: Interest % Sales | C26: =C25/C10 -> 0.0051465655 | D26: =D25/D10 -> 0.0062316348 | E26: =E25/E10 -> 0.0070965208 | F26: =F25/F10 -> 0.0068701153 | G26: =G25/G10 -> 0.0069970722 | H26: =H25/H10 -> 0.005704324 | I26: =I25/I10 -> 0.0032222472 | J26: =J25/J10 -> 0.003544966 | ... L26: =L25/L10 -> 0.010011279
B28: Depreciation | C28: =IFERROR('Data Sheet'!B26,0) -> 114.98 | D28: =IFERROR('Data Sheet'!C26,0) -> 133.19 | E28: =IFERROR('Data Sheet'!D26,0) -> 142.86 | F28: =IFERROR('Data Sheet'!E26,0) -> 162.18 | G28: =IFERROR('Data Sheet'!F26,0) -> 176.9 | H28: =IFERROR('Data Sheet'!G26,0) -> 220.45 | I28: =IFERROR('Data Sheet'!H26,0) -> 240.13 | J28: =IFERROR('Data Sheet'!I26,0) -> 252.89 | ... L28: =IFERROR('Data Sheet'!K26,0) -> 399.21
B29: Depreciation % Sales | C29: =C28/C10 -> 0.014749554 | D29: =D28/D10 -> 0.017120285 | E29: =E28/E10 -> 0.018763816 | F29: =F28/F10 -> 0.021002739 | G29: =G28/G10 -> 0.020775127 | H29: =H28/H10 -> 0.025383896 | I29: =I28/I10 -> 0.025113866 | J29: =J28/J10 -> 0.023225037 | ... L29: =L28/L10 -> 0.032183947
B31: Earning Before Tax | C31: =IFERROR(C22-SUM(C28,C25),0) -> 1165.12 | D31: =IFERROR(D22-SUM(D28,D25),0) -> 1336.61 | E31: =IFERROR(E22-SUM(E28,E25),0) -> 1314.72 | F31: =IFERROR(F22-SUM(F28,F25),0) -> 1402.21 | G31: =IFERROR(G22-SUM(G28,G25),0) -> 1503.08 | H31: =IFERROR(H22-SUM(H28,H25),0) -> 1522.35 | I31: =IFERROR(I22-SUM(I28,I25),0) -> 1730.73 | J31: =IFERROR(J22-SUM(J28,J25),0) -> 1960.52 | ... L31: =IFERROR(L22-SUM(L28,L25),0) -> 1876.33
B32: EBT % Sales | C32: =C31/C10 -> 0.14946078 | D32: =D31/D10 -> 0.17180828 | E32: =E31/E10 -> 0.17268069 | F32: =F31/F10 -> 0.1815899 | G32: =G31/G10 -> 0.17652164 | H32: =H31/H10 -> 0.17529224 | I32: =I31/I10 -> 0.18100746 | J32: =J31/J10 -> 0.18005121 | ... L32: =L31/L10 -> 0.15126802
B34: Tax | C34: =IFERROR('Data Sheet'!B29,0) -> 250.89 | D34: =IFERROR('Data Sheet'!C29,0) -> 299.9 | E34: =IFERROR('Data Sheet'!D29,0) -> 330.34 | F34: =IFERROR('Data Sheet'!E29,0) -> 335.35 | G34: =IFERROR('Data Sheet'!F29,0) -> 278.62 | H34: =IFERROR('Data Sheet'!G29,0) -> 279.72 | I34: =IFERROR('Data Sheet'!H29,0) -> 361.07 | J34: =IFERROR('Data Sheet'!I29,0) -> 526.38 | ... L34: =IFERROR('Data Sheet'!K29,0) -> 547.43
B35: Effective Tax Rate | C35: =C34/C31 -> 0.21533404 | D35: =D34/D31 -> 0.2243736 | E35: =E34/E31 -> 0.25126263 | F35: =F34/F31 -> 0.23915819 | G35: =G34/G31 -> 0.18536605 | H35: =H34/H31 -> 0.18374224 | I35: =I34/I31 -> 0.20862295 | J35: =J34/J31 -> 0.26848999 | ... L35: =L34/L31 -> 0.29175571
B37: Net Profit | C37: =IFERROR(C31-C34,0) -> 914.23 | D37: =IFERROR(D31-D34,0) -> 1036.71 | E37: =IFERROR(E31-E34,0) -> 984.38 | F37: =IFERROR(F31-F34,0) -> 1066.86 | G37: =IFERROR(G31-G34,0) -> 1224.46 | H37: =IFERROR(H31-H34,0) -> 1242.63 | I37: =IFERROR(I31-I34,0) -> 1369.66 | J37: =IFERROR(J31-J34,0) -> 1434.14 | ... L37: =IFERROR(L31-L34,0) -> 1328.9
B38: Net Margins | C38: =C37/C10 -> 0.11727678 | D38: =D37/D10 -> 0.13325904 | E38: =E37/E10 -> 0.12929249 | F38: =F37/F10 -> 0.13816119 | G38: =G37/G10 -> 0.14380052 | H38: =H37/H10 -> 0.14308365 | I38: =I37/I10 -> 0.14324515 | J38: =J37/J10 -> 0.13170926 | ... L38: =L37/L10 -> 0.10713471
B40: No. of Equity Shares | C40: =IFERROR('Data Sheet'!B93,0) -> 175.65 | D40: =IFERROR('Data Sheet'!C93,0) -> 175.91 | E40: =IFERROR('Data Sheet'!D93,0) -> 176.15 | F40: =IFERROR('Data Sheet'!E93,0) -> 176.15 | G40: =IFERROR('Data Sheet'!F93,0) -> 176.63 | H40: =IFERROR('Data Sheet'!G93,0) -> 176.71 | I40: =IFERROR('Data Sheet'!H93,0) -> 176.74 | J40: =IFERROR('Data Sheet'!I93,0) -> 176.79 | ... L40: =IFERROR('Data Sheet'!K93,0) -> 177.2
B42: Earning Per Share | C42: =IFERROR(C37/C40,0) -> 5.2048392 | D42: =IFERROR(D37/D40,0) -> 5.8934114 | E42: =IFERROR(E37/E40,0) -> 5.5883054 | F42: =IFERROR(F37/F40,0) -> 6.0565427 | G42: =IFERROR(G37/G40,0) -> 6.9323444 | H42: =IFERROR(H37/H40,0) -> 7.0320299 | I42: =IFERROR(I37/I40,0) -> 7.7495756 | J42: =IFERROR(J37/J40,0) -> 8.1121104 | ... L42: =IFERROR(L37/L40,0) -> 7.4994357
B43: EPS Growth | C43: - | D43: =IFERROR(D42/C42-1,0) -> 0.13229462 | E43: =IFERROR(E42/D42-1,0) -> -0.051770691 | F43: =IFERROR(F42/E42-1,0) -> 0.083788781 | G43: =IFERROR(G42/F42-1,0) -> 0.14460424 | H43: =IFERROR(H42/G42-1,0) -> 0.014379757 | I43: =IFERROR(I42/H42-1,0) -> 0.10203964 | J43: =IFERROR(J42/I42-1,0) -> 0.046781241 | K43: =IFERROR(K42/J42-1,0) -> -0.1261833 | L43: =IFERROR(L42/K42-1,0) -> 0.057972524
B45: Dividend Per Share | C45: =IFERROR('Data Sheet'!B31/'Data Sheet'!B93,0) -> 2 | D45: =IFERROR('Data Sheet'!C31/'Data Sheet'!C93,0) -> 2.2500142 | E45: =IFERROR('Data Sheet'!D31/'Data Sheet'!D93,0) -> 2.2500142 | F45: =IFERROR('Data Sheet'!E31/'Data Sheet'!E93,0) -> 6.2500142 | G45: =IFERROR('Data Sheet'!F31/'Data Sheet'!F93,0) -> 2.7499858 | H45: =IFERROR('Data Sheet'!G31/'Data Sheet'!G93,0) -> 3 | I45: =IFERROR('Data Sheet'!H31/'Data Sheet'!H93,0) -> 4.7500283 | J45: =IFERROR('Data Sheet'!I31/'Data Sheet'!I93,0) -> 5.2000113 | ... L45: =IFERROR('Data Sheet'!K31/'Data Sheet'!K93,0) -> 5.5
B46: Dividend Payout Ratio | C46: =C45/C42 -> 0.38425779 | D46: =D45/D42 -> 0.38178468 | E46: =E45/E42 -> 0.40262907 | F46: =F45/F42 -> 1.0319442 | G46: =G45/G42 -> 0.39668915 | H46: =H45/H42 -> 0.42661935 | I46: =I45/I42 -> 0.61294044 | J46: =J45/J42 -> 0.64101831 | ... L46: =L45/L42 -> 0.73338852
B48: Retained Earning | C48: =IFERROR(IF(C42>C45,1-C46,0),0) -> 0.61574221 | D48: =IFERROR(IF(D42>D45,1-D46,0),0) -> 0.61821532 | E48: =IFERROR(IF(E42>E45,1-E46,0),0) -> 0.59737093 | F48: =IFERROR(IF(F42>F45,1-F46,0),0) -> 0 | G48: =IFERROR(IF(G42>G45,1-G46,0),0) -> 0.60331085 | H48: =IFERROR(IF(H42>H45,1-H46,0),0) -> 0.57338065 | I48: =IFERROR(IF(I42>I45,1-I46,0),0) -> 0.38705956 | J48: =IFERROR(IF(J42>J45,1-J46,0),0) -> 0.35898169 | ... L48: =IFERROR(IF(L42>L45,1-L46,0),0) -> 0.26661148
A50: # | B50: Balance Sheet
B51: Equity Share Capital | C51: =IFERROR('Data Sheet'!B57,0) -> 175.65 | D51: =IFERROR('Data Sheet'!C57,0) -> 175.91 | E51: =IFERROR('Data Sheet'!D57,0) -> 176.15 | F51: =IFERROR('Data Sheet'!E57,0) -> 176.15 | G51: =IFERROR('Data Sheet'!F57,0) -> 176.63 | H51: =IFERROR('Data Sheet'!G57,0) -> 176.71 | I51: =IFERROR('Data Sheet'!H57,0) -> 176.74 | J51: =IFERROR('Data Sheet'!I57,0) -> 176.79 | ... L51: =IFERROR('Data Sheet'!K57,0) -> 177.2
B52: Reserves | C52: =IFERROR('Data Sheet'!B58,0) -> 3178.49 | D52: =IFERROR('Data Sheet'!C58,0) -> 3994.7 | E52: =IFERROR('Data Sheet'!D58,0) -> 4671.24 | F52: =IFERROR('Data Sheet'!E58,0) -> 5530.37 | G52: =IFERROR('Data Sheet'!F58,0) -> 5455.05 | H52: =IFERROR('Data Sheet'!G58,0) -> 6429.04 | I52: =IFERROR('Data Sheet'!H58,0) -> 7486.79 | J52: =IFERROR('Data Sheet'!I58,0) -> 8204.51 | ... L52: =IFERROR('Data Sheet'!K58,0) -> 9689.1
B53: Borrowings | C53: =IFERROR('Data Sheet'!B59,0) -> 733.56 | D53: =IFERROR('Data Sheet'!C59,0) -> 805.22 | E53: =IFERROR('Data Sheet'!D59,0) -> 975 | F53: =IFERROR('Data Sheet'!E59,0) -> 937.59 | G53: =IFERROR('Data Sheet'!F59,0) -> 699.37 | H53: =IFERROR('Data Sheet'!G59,0) -> 521.99 | I53: =IFERROR('Data Sheet'!H59,0) -> 509.06 | J53: =IFERROR('Data Sheet'!I59,0) -> 1030.1 | ... L53: =IFERROR('Data Sheet'!K59,0) -> 1365.09
B54: Other Liabilities | C54: =IFERROR('Data Sheet'!B60,0) -> 2018.58 | D54: =IFERROR('Data Sheet'!C60,0) -> 1956.47 | E54: =IFERROR('Data Sheet'!D60,0) -> 1909.85 | F54: =IFERROR('Data Sheet'!E60,0) -> 2057.52 | G54: =IFERROR('Data Sheet'!F60,0) -> 2105.59 | H54: =IFERROR('Data Sheet'!G60,0) -> 2208.84 | I54: =IFERROR('Data Sheet'!H60,0) -> 2660.63 | J54: =IFERROR('Data Sheet'!I60,0) -> 2872.46 | ... L54: =IFERROR('Data Sheet'!K60,0) -> 3884.97
B55: Total Liabilities | C55: =IFERROR('Data Sheet'!B61,0) -> 6106.28 | D55: =IFERROR('Data Sheet'!C61,0) -> 6932.3 | E55: =IFERROR('Data Sheet'!D61,0) -> 7732.24 | F55: =IFERROR('Data Sheet'!E61,0) -> 8701.63 | G55: =IFERROR('Data Sheet'!F61,0) -> 8436.64 | H55: =IFERROR('Data Sheet'!G61,0) -> 9336.58 | I55: =IFERROR('Data Sheet'!H61,0) -> 10833.22 | J55: =IFERROR('Data Sheet'!I61,0) -> 12283.86 | ... L55: =IFERROR('Data Sheet'!K61,0) -> 15116.36
B57: Net Block | C57: =IFERROR('Data Sheet'!B62,0) -> 1877.13 | D57: =IFERROR('Data Sheet'!C62,0) -> 1667.4 | E57: =IFERROR('Data Sheet'!D62,0) -> 1958.4 | F57: =IFERROR('Data Sheet'!E62,0) -> 2028.11 | G57: =IFERROR('Data Sheet'!F62,0) -> 1969.06 | H57: =IFERROR('Data Sheet'!G62,0) -> 2252.68 | I57: =IFERROR('Data Sheet'!H62,0) -> 2242.92 | J57: =IFERROR('Data Sheet'!I62,0) -> 2307.9 | ... L57: =IFERROR('Data Sheet'!K62,0) -> 3815
B58: Capital Work in Progress | C58: =IFERROR('Data Sheet'!B63,0) -> 50.3 | D58: =IFERROR('Data Sheet'!C63,0) -> 44.8 | E58: =IFERROR('Data Sheet'!D63,0) -> 42.1 | F58: =IFERROR('Data Sheet'!E63,0) -> 41.51 | G58: =IFERROR('Data Sheet'!F63,0) -> 63.76 | H58: =IFERROR('Data Sheet'!G63,0) -> 146.57 | I58: =IFERROR('Data Sheet'!H63,0) -> 147.3 | J58: =IFERROR('Data Sheet'!I63,0) -> 167.5 | ... L58: =IFERROR('Data Sheet'!K63,0) -> 232.23
B59: Investments | C59: =IFERROR('Data Sheet'!B64,0) -> 1813.37 | D59: =IFERROR('Data Sheet'!C64,0) -> 2690.74 | E59: =IFERROR('Data Sheet'!D64,0) -> 3240.16 | F59: =IFERROR('Data Sheet'!E64,0) -> 3805.17 | G59: =IFERROR('Data Sheet'!F64,0) -> 3358.76 | H59: =IFERROR('Data Sheet'!G64,0) -> 2800.26 | I59: =IFERROR('Data Sheet'!H64,0) -> 4159.63 | J59: =IFERROR('Data Sheet'!I64,0) -> 6219.62 | ... L59: =IFERROR('Data Sheet'!K64,0) -> 6932.69
B60: Other Assets | C60: =IFERROR('Data Sheet'!B65-SUM('Data Sheet'!B67:B69),0) -> 405.33 | D60: =IFERROR('Data Sheet'!C65-SUM('Data Sheet'!C67:C69),0) -> 403.84 | E60: =IFERROR('Data Sheet'!D65-SUM('Data Sheet'!D67:D69),0) -> 429.64 | F60: =IFERROR('Data Sheet'!E65-SUM('Data Sheet'!E67:E69),0) -> 558.52 | G60: =IFERROR('Data Sheet'!F65-SUM('Data Sheet'!F67:F69),0) -> 582.81 | H60: =IFERROR('Data Sheet'!G65-SUM('Data Sheet'!G67:G69),0) -> 1132.24 | I60: =IFERROR('Data Sheet'!H65-SUM('Data Sheet'!H67:H69),0) -> 658.48 | J60: =IFERROR('Data Sheet'!I65-SUM('Data Sheet'!I67:I69),0) -> 461.18 | ... L60: =IFERROR('Data Sheet'!K65-SUM('Data Sheet'!K67:K69),0) -> 624.39
B61: Total Non-Current Assets | C61: =SUM(C57:C60) -> 4146.13 | D61: =SUM(D57:D60) -> 4806.78 | E61: =SUM(E57:E60) -> 5670.3 | F61: =SUM(F57:F60) -> 6433.31 | G61: =SUM(G57:G60) -> 5974.39 | H61: =SUM(H57:H60) -> 6331.75 | I61: =SUM(I57:I60) -> 7208.33 | J61: =SUM(J57:J60) -> 9156.2 | ... L61: =SUM(L57:L60) -> 11604.31
B63: Receivables | C63: =IFERROR('Data Sheet'!B67,0) -> 710.84 | D63: =IFERROR('Data Sheet'!C67,0) -> 809.2 | E63: =IFERROR('Data Sheet'!D67,0) -> 650.42 | F63: =IFERROR('Data Sheet'!E67,0) -> 706.08 | G63: =IFERROR('Data Sheet'!F67,0) -> 833.56 | H63: =IFERROR('Data Sheet'!G67,0) -> 813.89 | I63: =IFERROR('Data Sheet'!H67,0) -> 561.58 | J63: =IFERROR('Data Sheet'!I67,0) -> 646.15 | ... L63: =IFERROR('Data Sheet'!K67,0) -> 898.72
B64: Inventory | C64: =IFERROR('Data Sheet'!B68,0) -> 973.27 | D64: =IFERROR('Data Sheet'!C68,0) -> 1096.5 | E64: =IFERROR('Data Sheet'!D68,0) -> 1106.71 | F64: =IFERROR('Data Sheet'!E68,0) -> 1256.18 | G64: =IFERROR('Data Sheet'!F68,0) -> 1300.53 | H64: =IFERROR('Data Sheet'!G68,0) -> 1379.57 | I64: =IFERROR('Data Sheet'!H68,0) -> 1734.28 | J64: =IFERROR('Data Sheet'!I68,0) -> 1911.37 | ... L64: =IFERROR('Data Sheet'!K68,0) -> 1946.97
B65: Cash & Bank | C65: =IFERROR('Data Sheet'!B69,0) -> 276.04 | D65: =IFERROR('Data Sheet'!C69,0) -> 219.82 | E65: =IFERROR('Data Sheet'!D69,0) -> 304.81 | F65: =IFERROR('Data Sheet'!E69,0) -> 306.06 | G65: =IFERROR('Data Sheet'!F69,0) -> 328.16 | H65: =IFERROR('Data Sheet'!G69,0) -> 811.37 | I65: =IFERROR('Data Sheet'!H69,0) -> 1329.03 | J65: =IFERROR('Data Sheet'!I69,0) -> 570.14 | ... L65: =IFERROR('Data Sheet'!K69,0) -> 666.36
B66: Total Current Assets | C66: =SUM(C63:C65) -> 1960.15 | D66: =SUM(D63:D65) -> 2125.52 | E66: =SUM(E63:E65) -> 2061.94 | F66: =SUM(F63:F65) -> 2268.32 | G66: =SUM(G63:G65) -> 2462.25 | H66: =SUM(H63:H65) -> 3004.83 | I66: =SUM(I63:I65) -> 3624.89 | J66: =SUM(J63:J65) -> 3127.66 | ... L66: =SUM(L63:L65) -> 3512.05
B68: Total Assets | C68: =SUM(C61,C66) -> 6106.28 | D68: =SUM(D61,D66) -> 6932.3 | E68: =SUM(E61,E66) -> 7732.24 | F68: =SUM(F61,F66) -> 8701.63 | G68: =SUM(G61,G66) -> 8436.64 | H68: =SUM(H61,H66) -> 9336.58 | I68: =SUM(I61,I66) -> 10833.22 | J68: =SUM(J61,J66) -> 12283.86 | ... L68: =SUM(L61,L66) -> 15116.36
B70: Check | C70: =C55=C68 -> TRUE | D70: =D55=D68 -> TRUE | E70: =E55=E68 -> TRUE | F70: =F55=F68 -> TRUE | G70: =G55=G68 -> TRUE | H70: =H55=H68 -> TRUE | I70: =I55=I68 -> TRUE | J70: =J55=J68 -> TRUE | ... L70: =L55=L68 -> TRUE
A72: # | B72: Cash Flow Statement
B74: Cash Flow from Operating Activities | C74: =IFERROR('Data Sheet'!B82,0) -> 1047.21 | D74: =IFERROR('Data Sheet'!C82,0) -> 1186.99 | E74: =IFERROR('Data Sheet'!D82,0) -> 1226.94 | F74: =IFERROR('Data Sheet'!E82,0) -> 1091.5 | G74: =IFERROR('Data Sheet'!F82,0) -> 1499.13 | H74: =IFERROR('Data Sheet'!G82,0) -> 1613.62 | I74: =IFERROR('Data Sheet'!H82,0) -> 2114.67 | J74: =IFERROR('Data Sheet'!I82,0) -> 1802.33 | ... L74: =IFERROR('Data Sheet'!K82,0) -> 2013.47
B75: Cash Flow from Investing Activities | C75: =IFERROR('Data Sheet'!B83,0) -> -875.9 | D75: =IFERROR('Data Sheet'!C83,0) -> -730.33 | E75: =IFERROR('Data Sheet'!D83,0) -> -807.07 | F75: =IFERROR('Data Sheet'!E83,0) -> -540.93 | G75: =IFERROR('Data Sheet'!F83,0) -> 337.58 | H75: =IFERROR('Data Sheet'!G83,0) -> -516.63 | I75: =IFERROR('Data Sheet'!H83,0) -> -1404.22 | J75: =IFERROR('Data Sheet'!I83,0) -> -1273.45 | ... L75: =IFERROR('Data Sheet'!K83,0) -> -971.04
B76: Cash Flow from Financing Activities | C76: =IFERROR('Data Sheet'!B84,0) -> -416.77 | D76: =IFERROR('Data Sheet'!C84,0) -> -374.31 | E76: =IFERROR('Data Sheet'!D84,0) -> -338.97 | F76: =IFERROR('Data Sheet'!E84,0) -> -577.11 | G76: =IFERROR('Data Sheet'!F84,0) -> -1888.2 | H76: =IFERROR('Data Sheet'!G84,0) -> -1042.97 | I76: =IFERROR('Data Sheet'!H84,0) -> -613.41 | J76: =IFERROR('Data Sheet'!I84,0) -> -490.49 | ... L76: =IFERROR('Data Sheet'!K84,0) -> -1161.18
B78: Net Cash Flow | C78: =SUM(C76,C75,C74) -> -245.46 | D78: =SUM(D76,D75,D74) -> 82.35 | E78: =SUM(E76,E75,E74) -> 80.9 | F78: =SUM(F76,F75,F74) -> -26.54 | G78: =SUM(G76,G75,G74) -> -51.49 | H78: =SUM(H76,H75,H74) -> 54.02 | I78: =SUM(I76,I75,I74) -> 97.04 | J78: =SUM(J76,J75,J74) -> 38.39 | ... L78: =SUM(L76,L75,L74) -> -118.75

Sheet Ratios
B2: DABUR INDIA LTD
B4: BSE : 500096 | NSE : DABUR
B6: ="Financial Statement Analysis - " & 'Data Sheet'!B1 -> Financial Statement Analysis - DABUR INDIA LTD
B7: Years | C7: ='Data Sheet'!B16 -> 42094 | D7: ='Data Sheet'!C16 -> 42460 | E7: ='Data Sheet'!D16 -> 42825 | F7: ='Data Sheet'!E16 -> 43190 | G7: ='Data Sheet'!F16 -> 43555 | H7: ='Data Sheet'!G16 -> 43921 | I7: ='Data Sheet'!H16 -> 44286 | J7: ='Data Sheet'!I16 -> 44651 | ... L7: ='Data Sheet'!K16 -> 45382 | M7: Trend | N7: Mean | O7: Median
B9: Sales Growth | C9: - | D9: =IFERROR('Historical FS'!D11,0) -> -0.0020306613 | E9: =IFERROR('Historical FS'!E11,0) -> -0.021346691 | F9: =IFERROR('Historical FS'!F11,0) -> 0.01421931 | G9: =IFERROR('Historical FS'!G11,0) -> 0.10271373 | H9: =IFERROR('Historical FS'!H11,0) -> 0.019923688 | I9: =IFERROR('Historical FS'!I11,0) -> 0.10098404 | J9: =IFERROR('Historical FS'!J11,0) -> 0.13878672 | K9: =IFERROR('Historical FS'!K11,0) -> 0.058887762 | L9: =IFERROR('Historical FS'!L11,0) -> 0.075813386 | N9: =IFERROR(AVERAGE(D9:L9),0) -> 0.054216808 | O9: =IFERROR(MEDIAN(D9:L9),0) -> 0.058887762
B10: EBITDA Growth | C10: - | D10: =IFERROR('Historical FS'!D22/'Historical FS'!C22-1,0) -> 0.15002045 | E10: =IFERROR('Historical FS'!E22/'Historical FS'!D22-1,0) -> -0.0043931291 | F10: =IFERROR('Historical FS'!F22/'Historical FS'!E22-1,0) -> 0.070011445 | G10: =IFERROR('Historical FS'!G22/'Historical FS'!F22-1,0) -> 0.075502028 | H10: =IFERROR('Historical FS'!H22/'Historical FS'!G22-1,0) -> 0.030341006 | I10: =IFERROR('Historical FS'!I22/'Historical FS'!H22-1,0) -> 0.11679146 | J10: =IFERROR('Historical FS'!J22/'Historical FS'!I22-1,0) -> 0.12506557 | K10: =IFERROR('Historical FS'!K22/'Historical FS'!J22-1,0) -> -0.039751156 | L10: =IFERROR('Historical FS'!L22/'Historical FS'!K22-1,0) -> 0.10970224 | N10: =IFERROR(AVERAGE(D10:L10),0) -> 0.070365546 | O10: =IFERROR(MEDIAN(D10:L10),0) -> 0.075502028
B11: EBIT Growth | C11: - | D11: =IFERROR('Historical FS'!D31/'Historical FS'!C31-1,0) -> 0.14718656 | E11: =IFERROR('Historical FS'!E31/'Historical FS'!D31-1,0) -> -0.016377253 | F11: =IFERROR('Historical FS'!F31/'Historical FS'!E31-1,0) -> 0.066546489 | G11: =IFERROR('Historical FS'!G31/'Historical FS'!F31-1,0) -> 0.071936443 | H11: =IFERROR('Historical FS'!H31/'Historical FS'!G31-1,0) -> 0.012820342 | I11: =IFERROR('Historical FS'!I31/'Historical FS'!H31-1,0) -> 0.13688048 | J11: =IFERROR('Historical FS'!J31/'Historical FS'!I31-1,0) -> 0.13277057 | K11: =IFERROR('Historical FS'!K31/'Historical FS'!J31-1,0) -> -0.095500173 | L11: =IFERROR('Historical FS'!L31/'Historical FS'!K31-1,0) -> 0.058106683 | N11: =IFERROR(AVERAGE(D11:L11),0) -> 0.057152237 | O11: =IFERROR(MEDIAN(D11:L11),0) -> 0.066546489
B12: Net Profit Growth | C12: - | D12: =IFERROR('Historical FS'!D37/'Historical FS'!C37-1,0) -> 0.13397066 | E12: =IFERROR('Historical FS'!E37/'Historical FS'!D37-1,0) -> -0.05047699 | F12: =IFERROR('Historical FS'!F37/'Historical FS'!E37-1,0) -> 0.083788781 | G12: =IFERROR('Historical FS'!G37/'Historical FS'!F37-1,0) -> 0.14772323 | H12: =IFERROR('Historical FS'!H37/'Historical FS'!G37-1,0) -> 0.014839194 | I12: =IFERROR('Historical FS'!I37/'Historical FS'!H37-1,0) -> 0.10222673 | J12: =IFERROR('Historical FS'!J37/'Historical FS'!I37-1,0) -> 0.047077377 | K12: =IFERROR('Historical FS'!K37/'Historical FS'!J37-1,0) -> -0.12425565 | L12: =IFERROR('Historical FS'!L37/'Historical FS'!K37-1,0) -> 0.058091947 | N12: =IFERROR(AVERAGE(D12:L12),0) -> 0.045887253 | O12: =IFERROR(MEDIAN(D12:L12),0) -> 0.058091947
B13: Dividend Growth | C13: - | D13: =IFERROR('Historical FS'!D45/'Historical FS'!C45-1,0) -> 0.12500711 | E13: =IFERROR('Historical FS'!E45/'Historical FS'!D45-1,0) -> -8.6058313e-09 | F13: =IFERROR('Historical FS'!F45/'Historical FS'!E45-1,0) -> 1.7777666 | G13: =IFERROR('Historical FS'!G45/'Historical FS'!F45-1,0) -> -0.56000326 | H13: =IFERROR('Historical FS'!H45/'Historical FS'!G45-1,0) -> 0.090914706 | I13: =IFERROR('Historical FS'!I45/'Historical FS'!H45-1,0) -> 0.58334276 | J13: =IFERROR('Historical FS'!J45/'Historical FS'!I45-1,0) -> 0.094732704 | K13: =IFERROR('Historical FS'!K45/'Historical FS'!J45-1,0) -> 2.1659673e-06 | L13: =IFERROR('Historical FS'!L45/'Historical FS'!K45-1,0) -> 0.057687716 | N13: =IFERROR(AVERAGE(D13:L13),0) -> 0.24105005 | O13: =IFERROR(MEDIAN(D13:L13),0) -> 0.090914706
B15: Gross Margin | C15: =IFERROR('Historical FS'!C17,0) -> 0.41031289 | D15: =IFERROR('Historical FS'!D17,0) -> 0.39230635 | E15: =IFERROR('Historical FS'!E17,0) -> 0.37457494 | F15: =IFERROR('Historical FS'!F17,0) -> 0.37635541 | G15: =IFERROR('Historical FS'!G17,0) -> 0.35971387 | H15: =IFERROR('Historical FS'!H17,0) -> 0.36465875 | I15: =IFERROR('Historical FS'!I17,0) -> 0.3679595 | J15: =IFERROR('Historical FS'!J17,0) -> 0.35761451 | ... L15: =IFERROR('Historical FS'!L17,0) -> 0.3538517 | N15: =IFERROR(AVERAGE(C15:L15),0) -> 0.36860345 | O15: =IFERROR(MEDIAN(C15:L15),0) -> 0.36630913
B16: EBITDA Margin | C16: =IFERROR('Historical FS'!C23,0) -> 0.1693569 | D16: =IFERROR('Historical FS'!D23,0) -> 0.1951602 | E16: =IFERROR('Historical FS'!E23,0) -> 0.19854103 | F16: =IFERROR('Historical FS'!F23,0) -> 0.20946276 | G16: =IFERROR('Historical FS'!G23,0) -> 0.20429384 | H16: =IFERROR('Historical FS'!H23,0) -> 0.20638046 | I16: =IFERROR('Historical FS'!I23,0) -> 0.20934358 | J16: =IFERROR('Historical FS'!J23,0) -> 0.20682121 | ... L16: =IFERROR('Historical FS'!L23,0) -> 0.19346324 | N16: =IFERROR(AVERAGE(C16:L16),0) -> 0.19803783 | O16: =IFERROR(MEDIAN(C16:L16),0) -> 0.20141743
B17: EBIT Margin | C17: =IFERROR(('Historical FS'!C22-'Historical FS'!C28)/'Historical FS'!C10,0) -> 0.15460734 | D17: =IFERROR(('Historical FS'!D22-'Historical FS'!D28)/'Historical FS'!D10,0) -> 0.17803991 | E17: =IFERROR(('Historical FS'!E22-'Historical FS'!E28)/'Historical FS'!E10,0) -> 0.17977721 | F17: =IFERROR(('Historical FS'!F22-'Historical FS'!F28)/'Historical FS'!F10,0) -> 0.18846002 | G17: =IFERROR(('Historical FS'!G22-'Historical FS'!G28)/'Historical FS'!G10,0) -> 0.18351871 | H17: =IFERROR(('Historical FS'!H22-'Historical FS'!H28)/'Historical FS'!H10,0) -> 0.18099656 | I17: =IFERROR(('Historical FS'!I22-'Historical FS'!I28)/'Historical FS'!I10,0) -> 0.18422971 | J17: =IFERROR(('Historical FS'!J22-'Historical FS'!J28)/'Historical FS'!J10,0) -> 0.18359618 | ... L17: =IFERROR(('Historical FS'!L22-'Historical FS'!L28)/'Historical FS'!L10,0) -> 0.1612793 | N17: =IFERROR(AVERAGE(C17:L17),0) -> 0.17550902 | O17: =IFERROR(MEDIAN(C17:L17),0) -> 0.18038689
B18: EBT Margin | C18: =IFERROR('Historical FS'!C32,0) -> 0.14946078 | D18: =IFERROR('Historical FS'!D32,0) -> 0.17180828 | E18: =IFERROR('Historical FS'!E32,0) -> 0.17268069 | F18: =IFERROR('Historical FS'!F32,0) -> 0.1815899 | G18: =IFERROR('Historical FS'!G32,0) -> 0.17652164 | H18: =IFERROR('Historical FS'!H32,0) -> 0.17529224 | I18: =IFERROR('Historical FS'!I32,0) -> 0.18100746 | J18: =IFERROR('Historical FS'!J32,0) -> 0.18005121 | ... L18: =IFERROR('Historical FS'!L32,0) -> 0.15126802 | N18: =IFERROR(AVERAGE(C18:L18),0) -> 0.16934796 | O18: =IFERROR(MEDIAN(C18:L18),0) -> 0.17398647
B19: Net Profit Margin | C19: =IFERROR('Historical FS'!C38,0) -> 0.11727678 | D19: =IFERROR('Historical FS'!D38,0) -> 0.13325904 | E19: =IFERROR('Historical FS'!E38,0) -> 0.12929249 | F19: =IFERROR('Historical FS'!F38,0) -> 0.13816119 | G19: =IFERROR('Historical FS'!G38,0) -> 0.14380052 | H19: =IFERROR('Historical FS'!H38,0) -> 0.14308365 | I19: =IFERROR('Historical FS'!I38,0) -> 0.14324515 | J19: =IFERROR('Historical FS'!J38,0) -> 0.13170926 | ... L19: =IFERROR('Historical FS'!L38,0) -> 0.10713471 | N19: =IFERROR(AVERAGE(C19:L19),0) -> 0.12958918 | O19: =IFERROR(MEDIAN(C19:L19),0) -> 0.13248415
B21: SalesExpenses%Sales | C21: =IFERROR('Historical FS'!C20,0) -> 0.24095599 | D21: =IFERROR('Historical FS'!D20,0) -> 0.19714615 | E21: =IFERROR('Historical FS'!E20,0) -> 0.17603391 | F21: =IFERROR('Historical FS'!F20,0) -> 0.16689265 | G21: =IFERROR('Historical FS'!G20,0) -> 0.15542003 | H21: =IFERROR('Historical FS'!H20,0) -> 0.15827829 | I21: =IFERROR('Historical FS'!I20,0) -> 0.15861593 | J21: =IFERROR('Historical FS'!J20,0) -> 0.1507933 | ... L21: =IFERROR('Historical FS'!L20,0) -> 0.16038846 | N21: =IFERROR(AVERAGE(C21:L21),0) -> 0.17056561 | O21: =IFERROR(MEDIAN(C21:L21),0) -> 0.15950219
B22: Depreciation%Sales | C22: =IFERROR('Historical FS'!C29,0) -> 0.014749554 | D22: =IFERROR('Historical FS'!D29,0) -> 0.017120285 | E22: =IFERROR('Historical FS'!E29,0) -> 0.018763816 | F22: =IFERROR('Historical FS'!F29,0) -> 0.021002739 | G22: =IFERROR('Historical FS'!G29,0) -> 0.020775127 | H22: =IFERROR('Historical FS'!H29,0) -> 0.025383896 | I22: =IFERROR('Historical FS'!I29,0) -> 0.025113866 | J22: =IFERROR('Historical FS'!J29,0) -> 0.023225037 | ... L22: =IFERROR('Historical FS'!L29,0) -> 0.032183947 | N22: =IFERROR(AVERAGE(C22:L22),0) -> 0.022528817 | O22: =IFERROR(MEDIAN(C22:L22),0) -> 0.022113888
B23: OperatingIncome%Sales | C23: =C17 -> 0.15460734 | D23: =D17 -> 0.17803991 | E23: =E17 -> 0.17977721 | F23: =F17 -> 0.18846002 | G23: =G17 -> 0.18351871 | H23: =H17 -> 0.18099656 | I23: =I17 -> 0.18422971 | J23: =J17 -> 0.18359618 | ... L23: =L17 -> 0.1612793 | N23: =IFERROR(AVERAGE(C23:L23),0) -> 0.17550902 | O23: =IFERROR(MEDIAN(C23:L23),0) -> 0.18038689
B25: Return on Capital Employed | C25: =IFERROR(('Historical FS'!C22-'Historical FS'!C28)/SUM('Historical FS'!C51:C53),0) -> 0.29484551 | D25: =IFERROR(('Historical FS'!D22-'Historical FS'!D28)/SUM('Historical FS'!D51:D53),0) -> 0.27836361 | E25: =IFERROR(('Historical FS'!E22-'Historical FS'!E28)/SUM('Historical FS'!E51:E53),0) -> 0.23508387 | F25: =IFERROR(('Historical FS'!F22-'Historical FS'!F28)/SUM('Historical FS'!F51:F53),0) -> 0.21903009 | G25: =IFERROR(('Historical FS'!G22-'Historical FS'!G28)/SUM('Historical FS'!G51:G53),0) -> 0.24682478 | H25: =IFERROR(('Historical FS'!H22-'Historical FS'!H28)/SUM('Historical FS'!H51:H53),0) -> 0.22053133 | I25: =IFERROR(('Historical FS'!I22-'Historical FS'!I28)/SUM('Historical FS'!I51:I53),0) -> 0.21554244 | J25: =IFERROR(('Historical FS'!J22-'Historical FS'!J28)/SUM('Historical FS'!J51:J53),0) -> 0.21241473 | ... L25: =IFERROR(('Historical FS'!L22-'Historical FS'!L28)/SUM('Historical FS'!L51:L53),0) -> 0.17811776 | N25: =IFERROR(AVERAGE(C25:L25),0) -> 0.22832239 | O25: =IFERROR(MEDIAN(C25:L25),0) -> 0.21978071
B26: Retained Earnings | C26: =IFERROR('Historical FS'!C48,0) -> 0.61574221 | D26: =IFERROR('Historical FS'!D48,0) -> 0.61821532 | E26: =IFERROR('Historical FS'!E48,0) -> 0.59737093 | F26: =IFERROR('Historical FS'!F48,0) -> 0 | G26: =IFERROR('Historical FS'!G48,0) -> 0.60331085 | H26: =IFERROR('Historical FS'!H48,0) -> 0.57338065 | I26: =IFERROR('Historical FS'!I48,0) -> 0.38705956 | J26: =IFERROR('Historical FS'!J48,0) -> 0.35898169 | ... L26: =IFERROR('Historical FS'!L48,0) -> 0.26661148 | N26: =IFERROR(AVERAGE(C26:L26),0) -> 0.42870867 | O26: =IFERROR(MEDIAN(C26:L26),0) -> 0.48022011
B27: Return on Equity | C27: =IFERROR('Historical FS'!C37/SUM('Historical FS'!C51:C52),0) -> 0.27256763 | D27: =IFERROR('Historical FS'!D37/SUM('Historical FS'!D51:D52),0) -> 0.24857515 | E27: =IFERROR('Historical FS'!E37/SUM('Historical FS'!E51:E52),0) -> 0.20307423 | F27: =IFERROR('Historical FS'!F37/SUM('Historical FS'!F51:F52),0) -> 0.18695457 | G27: =IFERROR('Historical FS'!G37/SUM('Historical FS'!G51:G52),0) -> 0.21742358 | H27: =IFERROR('Historical FS'!H37/SUM('Historical FS'!H51:H52),0) -> 0.18811339 | I27: =IFERROR('Historical FS'!I37/SUM('Historical FS'!I51:I52),0) -> 0.17872443 | J27: =IFERROR('Historical FS'!J37/SUM('Historical FS'!J51:J52),0) -> 0.17111188 | ... L27: =IFERROR('Historical FS'!L37/SUM('Historical FS'!L51:L52),0) -> 0.13469082 | N27: =IFERROR(AVERAGE(C27:L27),0) -> 0.19412004 | O27: =IFERROR(MEDIAN(C27:L27),0) -> 0.18753398
B28: Self Sustained Growth Rate | C28: =IFERROR(C26*C27,0) -> 0.1678314 | D28: =IFERROR(D26*D27,0) -> 0.15367296 | E28: =IFERROR(E26*E27,0) -> 0.12131064 | F28: =IFERROR(F26*F27,0) -> 0 | G28: =IFERROR(G26*G27,0) -> 0.131174 | H28: =IFERROR(H26*H27,0) -> 0.10786058 | I28: =IFERROR(I26*I27,0) -> 0.069176998 | J28: =IFERROR(J26*J27,0) -> 0.061426032 | ... L28: =IFERROR(L26*L27,0) -> 0.035910118 | N28: =IFERROR(AVERAGE(C28:L28),0) -> 0.08856513 | O28: =IFERROR(MEDIAN(C28:L28),0) -> 0.088518787
B29: Interest Coverage Ratio | C29: =IFERROR(('Historical FS'!C22-'Historical FS'!C28)/'Historical FS'!C25,0) -> 30.040877 | D29: =IFERROR(('Historical FS'!D22-'Historical FS'!D28)/'Historical FS'!D25,0) -> 28.570338 | E29: =IFERROR(('Historical FS'!E22-'Historical FS'!E28)/'Historical FS'!E25,0) -> 25.333148 | F29: =IFERROR(('Historical FS'!F22-'Historical FS'!F28)/'Historical FS'!F25,0) -> 27.431857 | G29: =IFERROR(('Historical FS'!G22-'Historical FS'!G28)/'Historical FS'!G25,0) -> 26.227929 | H29: =IFERROR(('Historical FS'!H22-'Historical FS'!H28)/'Historical FS'!H25,0) -> 31.729713 | I29: =IFERROR(('Historical FS'!I22-'Historical FS'!I28)/'Historical FS'!I25,0) -> 57.174294 | J29: =IFERROR(('Historical FS'!J22-'Historical FS'!J28)/'Historical FS'!J25,0) -> 51.790674 | ... L29: =IFERROR(('Historical FS'!L22-'Historical FS'!L28)/'Historical FS'!L25,0) -> 16.10976 | N29: =IFERROR(AVERAGE(C29:L29),0) -> 31.807334 | O29: =IFERROR(MEDIAN(C29:L29),0) -> 28.001098
B31: Debtor Turnover Ratio | C31: =IFERROR('Historical FS'!C10/'Historical FS'!C63,0) -> 10.966589 | D31: =IFERROR('Historical FS'!D10/'Historical FS'!D63,0) -> 9.6140138 | E31: =IFERROR('Historical FS'!E10/'Historical FS'!E63,0) -> 11.705652 | F31: =IFERROR('Historical FS'!F10/'Historical FS'!F63,0) -> 10.936225 | G31: =IFERROR('Historical FS'!G10/'Historical FS'!G63,0) -> 10.215209 | H31: =IFERROR('Historical FS'!H10/'Historical FS'!H63,0) -> 10.670533 | I31: =IFERROR('Historical FS'!I10/'Historical FS'!I63,0) -> 17.026336 | J31: =IFERROR('Historical FS'!J10/'Historical FS'!J63,0) -> 16.851629 | ... L31: =IFERROR('Historical FS'!L10/'Historical FS'!L63,0) -> 13.801863 | N31: =IFERROR(AVERAGE(C31:L31),0) -> 12.53726 | O31: =IFERROR(MEDIAN(C31:L31),0) -> 11.33612
B32: Credit Turnover Ratio | C32: =IFERROR('Historical FS'!C10/'Historical FS'!C54,0) -> 3.8618682 | D32: =IFERROR('Historical FS'!D10/'Historical FS'!D54,0) -> 3.9763758 | E32: =IFERROR('Historical FS'!E10/'Historical FS'!E54,0) -> 3.9864858 | F32: =IFERROR('Historical FS'!F10/'Historical FS'!F54,0) -> 3.752989 | G32: =IFERROR('Historical FS'!G10/'Historical FS'!G54,0) -> 4.0439924 | H32: =IFERROR('Historical FS'!H10/'Historical FS'!H54,0) -> 3.9317651 | I32: =IFERROR('Historical FS'!I10/'Historical FS'!I54,0) -> 3.5937541 | J32: =IFERROR('Historical FS'!J10/'Historical FS'!J54,0) -> 3.790716 | ... L32: =IFERROR('Historical FS'!L10/'Historical FS'!L54,0) -> 3.19282 | N32: =IFERROR(AVERAGE(C32:L32),0) -> 3.7420106 | O32: =IFERROR(MEDIAN(C32:L32),0) -> 3.8262921
B33: Inventory Turnover Ratio | C33: =IFERROR('Historical FS'!C10/'Historical FS'!C64,0) -> 8.0095862 | D33: =IFERROR('Historical FS'!D10/'Historical FS'!D64,0) -> 7.0949932 | E33: =IFERROR('Historical FS'!E10/'Historical FS'!E64,0) -> 6.8794806 | F33: =IFERROR('Historical FS'!F10/'Historical FS'!F64,0) -> 6.1470888 | G33: =IFERROR('Historical FS'!G10/'Historical FS'!G64,0) -> 6.547323 | H33: =IFERROR('Historical FS'!H10/'Historical FS'!H64,0) -> 6.2951789 | I33: =IFERROR('Historical FS'!I10/'Historical FS'!I64,0) -> 5.5133254 | J33: =IFERROR('Historical FS'!J10/'Historical FS'!J64,0) -> 5.6967934 | ... L33: =IFERROR('Historical FS'!L10/'Historical FS'!L64,0) -> 6.3709302 | N33: =IFERROR(AVERAGE(C33:L33),0) -> 6.4250723 | O33: =IFERROR(MEDIAN(C33:L33),0) -> 6.3330546
B34: Fixed Assets Turnover Ratio | C34: =IFERROR('Historical FS'!C10/'Historical FS'!C57,0) -> 4.152877 | D34: =IFERROR('Historical FS'!D10/'Historical FS'!D57,0) -> 4.6657431 | E34: =IFERROR('Historical FS'!E10/'Historical FS'!E57,0) -> 3.8876583 | F34: =IFERROR('Historical FS'!F10/'Historical FS'!F57,0) -> 3.8074118 | G34: =IFERROR('Historical FS'!G10/'Historical FS'!G57,0) -> 4.3243934 | H34: =IFERROR('Historical FS'!H10/'Historical FS'!H57,0) -> 3.855248 | I34: =IFERROR('Historical FS'!I10/'Historical FS'!I57,0) -> 4.2630366 | J34: =IFERROR('Historical FS'!J10/'Historical FS'!J57,0) -> 4.7180034 | ... L34: =IFERROR('Historical FS'!L10/'Historical FS'!L57,0) -> 3.2513788 | N34: =IFERROR(AVERAGE(C34:L34),0) -> 4.0147605 | O34: =IFERROR(MEDIAN(C34:L34),0) -> 4.0202676
B35: Capital Turnover Ratio | C35: =IFERROR('Historical FS'!C10/SUM('Historical FS'!C51:C52),0) -> 2.3241397 | D35: =IFERROR('Historical FS'!D10/SUM('Historical FS'!D51:D52),0) -> 1.865353 | E35: =IFERROR('Historical FS'!E10/SUM('Historical FS'!E51:E52),0) -> 1.5706576 | F35: =IFERROR('Historical FS'!F10/SUM('Historical FS'!F51:F52),0) -> 1.3531627 | G35: =IFERROR('Historical FS'!G10/SUM('Historical FS'!G51:G52),0) -> 1.5119804 | H35: =IFERROR('Historical FS'!H10/SUM('Historical FS'!H51:H52),0) -> 1.3147092 | I35: =IFERROR('Historical FS'!I10/SUM('Historical FS'!I51:I52),0) -> 1.2476822 | J35: =IFERROR('Historical FS'!J10/SUM('Historical FS'!J51:J52),0) -> 1.2991636 | ... L35: =IFERROR('Historical FS'!L10/SUM('Historical FS'!L51:L52),0) -> 1.2572099 | N35: =IFERROR(AVERAGE(C35:L35),0) -> 1.5028975 | O35: =IFERROR(MEDIAN(C35:L35),0) -> 1.3339359
B37: Debtors days | C37: =IFERROR(365/C31,0) -> 33.282911 | D37: =IFERROR(365/D31,0) -> 37.965412 | E37: =IFERROR(365/E31,0) -> 31.181519 | F37: =IFERROR(365/F31,0) -> 33.375318 | G37: =IFERROR(365/G31,0) -> 35.731034 | H37: =IFERROR(365/H31,0) -> 34.206352 | I37: =IFERROR(365/I31,0) -> 21.437377 | J37: =IFERROR(365/J31,0) -> 21.659627 | ... L37: =IFERROR(365/L31,0) -> 26.445706 | N37: =IFERROR(AVERAGE(C37:L37),0) -> 30.215401 | O37: =IFERROR(MEDIAN(C37:L37),0) -> 32.232215
B38: Creditors days | C38: =IFERROR(365/C32,0) -> 94.513841 | D38: =IFERROR(365/D32,0) -> 91.792128 | E38: =IFERROR(365/E32,0) -> 91.559337 | F38: =IFERROR(365/F32,0) -> 97.255813 | G38: =IFERROR(365/G32,0) -> 90.25734 | H38: =IFERROR(365/H32,0) -> 92.833624 | I38: =IFERROR(365/I32,0) -> 101.5651 | J38: =IFERROR(365/J32,0) -> 96.287879 | ... L38: =IFERROR(365/L32,0) -> 114.319 | N38: =IFERROR(AVERAGE(C38:L38),0) -> 98.134861 | O38: =IFERROR(MEDIAN(C38:L38),0) -> 95.40086
B39: Inventory days | C39: =IFERROR(365/C33,0) -> 45.570394 | D39: =IFERROR(365/D33,0) -> 51.444729 | E39: =IFERROR(365/E33,0) -> 53.056331 | F39: =IFERROR(365/F33,0) -> 59.377701 | G39: =IFERROR(365/G33,0) -> 55.747975 | H39: =IFERROR(365/H33,0) -> 57.980878 | I39: =IFERROR(365/I33,0) -> 66.203239 | J39: =IFERROR(365/J33,0) -> 64.071132 | ... L39: =IFERROR(365/L33,0) -> 57.291477 | N39: =IFERROR(AVERAGE(C39:L39),0) -> 57.482365 | O39: =IFERROR(MEDIAN(C39:L39),0) -> 57.636177
B40: Cash Conversion Cycle | C40: =SUM(C37,C39)-C38 -> -15.660536 | D40: =SUM(D37,D39)-D38 -> -2.3819871 | E40: =SUM(E37,E39)-E38 -> -7.321487 | F40: =SUM(F37,F39)-F38 -> -4.502794 | G40: =SUM(G37,G39)-G38 -> 1.2216691 | H40: =SUM(H37,H39)-H38 -> -0.64639409 | I40: =SUM(I37,I39)-I38 -> -13.924485 | J40: =SUM(J37,J39)-J38 -> -10.55712 | ... L40: =SUM(L37,L39)-L38 -> -30.58182 | N40: =IFERROR(AVERAGE(C40:L40),0) -> -10.437095 | O40: =IFERROR(MEDIAN(C40:L40),0) -> -8.9393034
B42: CFO/Sales | C42: =IFERROR('Historical FS'!C74/'Historical FS'!C10,0) -> 0.13433537 | D42: =IFERROR('Historical FS'!D74/'Historical FS'!D10,0) -> 0.15257608 | E42: =IFERROR('Historical FS'!E74/'Historical FS'!E10,0) -> 0.16115131 | F42: =IFERROR('Historical FS'!F74/'Historical FS'!F10,0) -> 0.14135214 | G42: =IFERROR('Historical FS'!G74/'Historical FS'!G10,0) -> 0.17605775 | H42: =IFERROR('Historical FS'!H74/'Historical FS'!H10,0) -> 0.1858016 | I42: =IFERROR('Historical FS'!I74/'Historical FS'!I10,0) -> 0.22116162 | J42: =IFERROR('Historical FS'!J74/'Historical FS'!J10,0) -> 0.16552328 | ... L42: =IFERROR('Historical FS'!L74/'Historical FS'!L10,0) -> 0.16232412 | N42: =IFERROR(AVERAGE(C42:L42),0) -> 0.16293764 | O42: =IFERROR(MEDIAN(C42:L42),0) -> 0.16173771
B43: CFO/Total Assets | C43: =IFERROR('Historical FS'!C74/'Historical FS'!C68,0) -> 0.17149721 | D43: =IFERROR('Historical FS'!D74/'Historical FS'!D68,0) -> 0.171226 | E43: =IFERROR('Historical FS'!E74/'Historical FS'!E68,0) -> 0.15867847 | F43: =IFERROR('Historical FS'!F74/'Historical FS'!F68,0) -> 0.12543627 | G43: =IFERROR('Historical FS'!G74/'Historical FS'!G68,0) -> 0.17769278 | H43: =IFERROR('Historical FS'!H74/'Historical FS'!H68,0) -> 0.17282774 | I43: =IFERROR('Historical FS'!I74/'Historical FS'!I68,0) -> 0.19520235 | J43: =IFERROR('Historical FS'!J74/'Historical FS'!J68,0) -> 0.14672342 | ... L43: =IFERROR('Historical FS'!L74/'Historical FS'!L68,0) -> 0.13319807 | N43: =IFERROR(AVERAGE(C43:L43),0) -> 0.15615066 | O43: =IFERROR(MEDIAN(C43:L43),0) -> 0.16495223
B44: CFO/Total Debt | C44: =IFERROR('Historical FS'!C74/'Historical FS'!C53,0) -> 1.4275724 | D44: =IFERROR('Historical FS'!D74/'Historical FS'!D53,0) -> 1.4741189 | E44: =IFERROR('Historical FS'!E74/'Historical FS'!E53,0) -> 1.2584 | F44: =IFERROR('Historical FS'!F74/'Historical FS'!F53,0) -> 1.1641549 | G44: =IFERROR('Historical FS'!G74/'Historical FS'!G53,0) -> 2.1435435 | H44: =IFERROR('Historical FS'!H74/'Historical FS'!H53,0) -> 3.0912853 | I44: =IFERROR('Historical FS'!I74/'Historical FS'!I53,0) -> 4.1540683 | J44: =IFERROR('Historical FS'!J74/'Historical FS'!J53,0) -> 1.7496651 | ... L44: =IFERROR('Historical FS'!L74/'Historical FS'!L53,0) -> 1.4749723 | N44: =IFERROR(AVERAGE(C44:L44),0) -> 1.9205835 | O44: =IFERROR(MEDIAN(C44:L44),0) -> 1.4745456

Sheet Common Size Statement
B2: DABUR INDIA LTD
B4: BSE : 500096 | NSE : DABUR
B6: ="Common Size Income Statements - " & 'Data Sheet'!B1 -> Common Size Income Statements - DABUR INDIA LTD
B7: Particulars | C7: ='Data Sheet'!B16 -> 42094 | D7: ='Data Sheet'!C16 -> 42460 | E7: ='Data Sheet'!D16 -> 42825 | F7: ='Data Sheet'!E16 -> 43190 | G7: ='Data Sheet'!F16 -> 43555 | H7: ='Data Sheet'!G16 -> 43921 | I7: ='Data Sheet'!H16 -> 44286 | J7: ='Data Sheet'!I16 -> 44651 | ... L7: ='Data Sheet'!K16 -> 45382
B9: ='Data Sheet'!A17 -> Sales | C9: ='Data Sheet'!B17/'Data Sheet'!B$17 -> 1 | D9: ='Data Sheet'!C17/'Data Sheet'!C$17 -> 1 | E9: ='Data Sheet'!D17/'Data Sheet'!D$17 -> 1 | F9: ='Data Sheet'!E17/'Data Sheet'!E$17 -> 1 | G9: ='Data Sheet'!F17/'Data Sheet'!F$17 -> 1 | H9: ='Data Sheet'!G17/'Data Sheet'!G$17 -> 1 | I9: ='Data Sheet'!H17/'Data Sheet'!H$17 -> 1 | J9: ='Data Sheet'!I17/'Data Sheet'!I$17 -> 1 | ... L9: ='Data Sheet'!K17/'Data Sheet'!K$17 -> 1
B10: ='Data Sheet'!A18 -> Raw Material Cost | C10: ='Data Sheet'!B18/'Data Sheet'!B$17 -> 0.33788383 | D10: ='Data Sheet'!C18/'Data Sheet'!C$17 -> 0.35217092 | E10: ='Data Sheet'!D18/'Data Sheet'!D$17 -> 0.34931616 | F10: ='Data Sheet'!E18/'Data Sheet'!E$17 -> 0.35941517 | G10: ='Data Sheet'!F18/'Data Sheet'!F$17 -> 0.36029989 | H10: ='Data Sheet'!G18/'Data Sheet'!G$17 -> 0.36138401 | I10: ='Data Sheet'!H18/'Data Sheet'!H$17 -> 0.39368728 | J10: ='Data Sheet'!I18/'Data Sheet'!I$17 -> 0.37990831 | ... L10: ='Data Sheet'!K18/'Data Sheet'!K$17 -> 0.38010934
B11: ='Data Sheet'!A19 -> Change in Inventory | C11: ='Data Sheet'!B19/'Data Sheet'!B$17 -> 0.0033237167 | D11: ='Data Sheet'!C19/'Data Sheet'!C$17 -> 0.0090659489 | E11: ='Data Sheet'!D19/'Data Sheet'!D$17 -> 0.0030235408 | F11: ='Data Sheet'!E19/'Data Sheet'!E$17 -> 0.0085381094 | G11: ='Data Sheet'!F19/'Data Sheet'!F$17 -> -0.001484441 | H11: ='Data Sheet'!G19/'Data Sheet'!G$17 -> 0.0074890842 | I11: ='Data Sheet'!H19/'Data Sheet'!H$17 -> 0.0216699 | J11: ='Data Sheet'!I19/'Data Sheet'!I$17 -> 0.00078521915 | ... L11: ='Data Sheet'!K19/'Data Sheet'!K$17 -> -0.0039463045
B12: ='Data Sheet'!A20 -> Power and Fuel | C12: ='Data Sheet'!B20/'Data Sheet'!B$17 -> 0.011590035 | D12: ='Data Sheet'!C20/'Data Sheet'!C$17 -> 0.010797387 | E12: ='Data Sheet'!D20/'Data Sheet'!D$17 -> 0.01148998 | F12: ='Data Sheet'!E20/'Data Sheet'!E$17 -> 0.012161593 | G12: ='Data Sheet'!F20/'Data Sheet'!F$17 -> 0.012361729 | H12: ='Data Sheet'!G20/'Data Sheet'!G$17 -> 0.01233442 | I12: ='Data Sheet'!H20/'Data Sheet'!H$17 -> 0.01087783 | J12: ='Data Sheet'!I20/'Data Sheet'!I$17 -> 0.011815941 | ... L12: ='Data Sheet'!K20/'Data Sheet'!K$17 -> 0.012370193
B13: ='Data Sheet'!A21 -> Other Mfr. Exp | C13: ='Data Sheet'!B21/'Data Sheet'!B$17 -> 0.15500244 | D13: ='Data Sheet'!C21/'Data Sheet'!C$17 -> 0.15171743 | E13: ='Data Sheet'!D21/'Data Sheet'!D$17 -> 0.16384124 | F13: ='Data Sheet'!E21/'Data Sheet'!E$17 -> 0.15786372 | G13: ='Data Sheet'!F21/'Data Sheet'!F$17 -> 0.1559168 | H13: ='Data Sheet'!G21/'Data Sheet'!G$17 -> 0.1598201 | I13: ='Data Sheet'!H21/'Data Sheet'!H$17 -> 0.14091083 | J13: ='Data Sheet'!I21/'Data Sheet'!I$17 -> 0.15213322 | ... L13: ='Data Sheet'!K21/'Data Sheet'!K$17 -> 0.14966934
B14: ='Data Sheet'!A22 -> Employee Cost | C14: ='Data Sheet'!B22/'Data Sheet'!B$17 -> 0.088534524 | D14: ='Data Sheet'!C22/'Data Sheet'!C$17 -> 0.10207387 | E14: ='Data Sheet'!D22/'Data Sheet'!D$17 -> 0.10380123 | F14: ='Data Sheet'!E22/'Data Sheet'!E$17 -> 0.10274222 | G14: ='Data Sheet'!F22/'Data Sheet'!F$17 -> 0.11022327 | H14: ='Data Sheet'!G22/'Data Sheet'!G$17 -> 0.10929181 | I14: ='Data Sheet'!H22/'Data Sheet'!H$17 -> 0.10823446 | J14: ='Data Sheet'!I22/'Data Sheet'!I$17 -> 0.099313232 | ... L14: ='Data Sheet'!K22/'Data Sheet'!K$17 -> 0.10005313
B15: ='Data Sheet'!A23 -> Selling and admin | C15: ='Data Sheet'!B23/'Data Sheet'!B$17 -> 0.2105012 | D15: ='Data Sheet'!C23/'Data Sheet'!C$17 -> 0.15649013 | E15: ='Data Sheet'!D23/'Data Sheet'!D$17 -> 0.15254302 | F15: ='Data Sheet'!E23/'Data Sheet'!E$17 -> 0.14703471 | G15: ='Data Sheet'!F23/'Data Sheet'!F$17 -> 0.13899723 | H15: ='Data Sheet'!G23/'Data Sheet'!G$17 -> 0.14100642 | I15: ='Data Sheet'!H23/'Data Sheet'!H$17 -> 0.14519147 | J15: ='Data Sheet'!I23/'Data Sheet'!I$17 -> 0.13598618 | ... L15: ='Data Sheet'!K23/'Data Sheet'!K$17 -> 0.14350117
B16: ='Data Sheet'!A24 -> Other Expenses | C16: ='Data Sheet'!B24/'Data Sheet'!B$17 -> 0.030454789 | D16: ='Data Sheet'!C24/'Data Sheet'!C$17 -> 0.040656018 | E16: ='Data Sheet'!D24/'Data Sheet'!D$17 -> 0.023490889 | F16: ='Data Sheet'!E24/'Data Sheet'!E$17 -> 0.019857936 | G16: ='Data Sheet'!F24/'Data Sheet'!F$17 -> 0.016422803 | H16: ='Data Sheet'!G24/'Data Sheet'!G$17 -> 0.017271873 | I16: ='Data Sheet'!H24/'Data Sheet'!H$17 -> 0.013424461 | J16: ='Data Sheet'!I24/'Data Sheet'!I$17 -> 0.014807121 | ... L16: ='Data Sheet'!K24/'Data Sheet'!K$17 -> 0.016887281
B17: ='Data Sheet'!A25 -> Other Income | C17: ='Data Sheet'!B25/'Data Sheet'!B$17 -> 0.019785799 | D17: ='Data Sheet'!C25/'Data Sheet'!C$17 -> 0.027917672 | E17: ='Data Sheet'!D25/'Data Sheet'!D$17 -> 0.038868655 | F17: ='Data Sheet'!E25/'Data Sheet'!E$17 -> 0.037669729 | G17: ='Data Sheet'!F25/'Data Sheet'!F$17 -> 0.026047007 | H17: ='Data Sheet'!G25/'Data Sheet'!G$17 -> 0.023638286 | I17: ='Data Sheet'!H25/'Data Sheet'!H$17 -> 0.034020279 | J17: ='Data Sheet'!I25/'Data Sheet'!I$17 -> 0.028300951 | ... L17: ='Data Sheet'!K25/'Data Sheet'!K$17 -> 0.038891455
B18: ='Data Sheet'!A26 -> Depreciation | C18: ='Data Sheet'!B26/'Data Sheet'!B$17 -> 0.014749554 | D18: ='Data Sheet'!C26/'Data Sheet'!C$17 -> 0.017120285 | E18: ='Data Sheet'!D26/'Data Sheet'!D$17 -> 0.018763816 | F18: ='Data Sheet'!E26/'Data Sheet'!E$17 -> 0.021002739 | G18: ='Data Sheet'!F26/'Data Sheet'!F$17 -> 0.020775127 | H18: ='Data Sheet'!G26/'Data Sheet'!G$17 -> 0.025383896 | I18: ='Data Sheet'!H26/'Data Sheet'!H$17 -> 0.025113866 | J18: ='Data Sheet'!I26/'Data Sheet'!I$17 -> 0.023225037 | ... L18: ='Data Sheet'!K26/'Data Sheet'!K$17 -> 0.032183947
B19: ='Data Sheet'!A27 -> Interest | C19: ='Data Sheet'!B27/'Data Sheet'!B$17 -> 0.0051465655 | D19: ='Data Sheet'!C27/'Data Sheet'!C$17 -> 0.0062316348 | E19: ='Data Sheet'!D27/'Data Sheet'!D$17 -> 0.0070965208 | F19: ='Data Sheet'!E27/'Data Sheet'!E$17 -> 0.0068701153 | G19: ='Data Sheet'!F27/'Data Sheet'!F$17 -> 0.0069970722 | H19: ='Data Sheet'!G27/'Data Sheet'!G$17 -> 0.005704324 | I19: ='Data Sheet'!H27/'Data Sheet'!H$17 -> 0.0032222472 | J19: ='Data Sheet'!I27/'Data Sheet'!I$17 -> 0.003544966 | ... L19: ='Data Sheet'!K27/'Data Sheet'!K$17 -> 0.010011279
B20: ='Data Sheet'!A28 -> Profit before tax | C20: ='Data Sheet'!B28/'Data Sheet'!B$17 -> 0.16924658 | D20: ='Data Sheet'!C28/'Data Sheet'!C$17 -> 0.19972595 | E20: ='Data Sheet'!D28/'Data Sheet'!D$17 -> 0.21154935 | F20: ='Data Sheet'!E28/'Data Sheet'!E$17 -> 0.21925963 | G20: ='Data Sheet'!F28/'Data Sheet'!F$17 -> 0.20256865 | H20: ='Data Sheet'!G28/'Data Sheet'!G$17 -> 0.19893053 | I20: ='Data Sheet'!H28/'Data Sheet'!H$17 -> 0.21502774 | J20: ='Data Sheet'!I28/'Data Sheet'!I$17 -> 0.20835216 | ... L20: ='Data Sheet'!K28/'Data Sheet'!K$17 -> 0.19015947
B22: ="Common Size Balance Sheet - " & 'Data Sheet'!B1 -> Common Size Balance Sheet - DABUR INDIA LTD
B23: Particulars | C23: =C7 -> 42094 | D23: =D7 -> 42460 | E23: =E7 -> 42825 | F23: =F7 -> 43190 | G23: =G7 -> 43555 | H23: =H7 -> 43921 | I23: =I7 -> 44286 | J23: =J7 -> 44651 | ... L23: =L7 -> 45382
B25: Total Assets | C25: ='Data Sheet'!B61/'Data Sheet'!B$61 -> 1 | D25: ='Data Sheet'!C61/'Data Sheet'!C$61 -> 1 | E25: ='Data Sheet'!D61/'Data Sheet'!D$61 -> 1 | F25: ='Data Sheet'!E61/'Data Sheet'!E$61 -> 1 | G25: ='Data Sheet'!F61/'Data Sheet'!F$61 -> 1 | H25: ='Data Sheet'!G61/'Data Sheet'!G$61 -> 1 | I25: ='Data Sheet'!H61/'Data Sheet'!H$61 -> 1 | J25: ='Data Sheet'!I61/'Data Sheet'!I$61 -> 1 | ... L25: ='Data Sheet'!K61/'Data Sheet'!K$61 -> 1
B26: Net Block | C26: ='Data Sheet'!B62/'Data Sheet'!B$61 -> 0.30740975 | D26: ='Data Sheet'!C62/'Data Sheet'!C$61 -> 0.24052623 | E26: ='Data Sheet'!D62/'Data Sheet'!D$61 -> 0.25327719 | F26: ='Data Sheet'!E62/'Data Sheet'!E$61 -> 0.23307242 | G26: ='Data Sheet'!F62/'Data Sheet'!F$61 -> 0.23339386 | H26: ='Data Sheet'!G62/'Data Sheet'!G$61 -> 0.24127464 | I26: ='Data Sheet'!H62/'Data Sheet'!H$61 -> 0.20704094 | J26: ='Data Sheet'!I62/'Data Sheet'!I$61 -> 0.18788068 | ... L26: ='Data Sheet'!K62/'Data Sheet'!K$61 -> 0.25237557
B27: Capital Work in Progress | C27: ='Data Sheet'!B63/'Data Sheet'!B$61 -> 0.0082374211 | D27: ='Data Sheet'!C63/'Data Sheet'!C$61 -> 0.0064625016 | E27: ='Data Sheet'!D63/'Data Sheet'!D$61 -> 0.0054447353 | F27: ='Data Sheet'!E63/'Data Sheet'!E$61 -> 0.0047703706 | G27: ='Data Sheet'!F63/'Data Sheet'!F$61 -> 0.007557511 | H27: ='Data Sheet'!G63/'Data Sheet'!G$61 -> 0.015698468 | I27: ='Data Sheet'!H63/'Data Sheet'!H$61 -> 0.013597065 | J27: ='Data Sheet'!I63/'Data Sheet'!I$61 -> 0.013635779 | ... L27: ='Data Sheet'!K63/'Data Sheet'!K$61 -> 0.015362825
B28: Investments | C28: ='Data Sheet'!B64/'Data Sheet'!B$61 -> 0.29696804 | D28: ='Data Sheet'!C64/'Data Sheet'!C$61 -> 0.38814535 | E28: ='Data Sheet'!D64/'Data Sheet'!D$61 -> 0.41904545 | F28: ='Data Sheet'!E64/'Data Sheet'!E$61 -> 0.43729393 | G28: ='Data Sheet'!F64/'Data Sheet'!F$61 -> 0.39811584 | H28: ='Data Sheet'!G64/'Data Sheet'!G$61 -> 0.29992353 | I28: ='Data Sheet'!H64/'Data Sheet'!H$61 -> 0.38396986 | J28: ='Data Sheet'!I64/'Data Sheet'!I$61 -> 0.50632456 | ... L28: ='Data Sheet'!K64/'Data Sheet'!K$61 -> 0.45862165
B29: Other Assets | C29: ='Data Sheet'!B75/'Data Sheet'!B$61 -> 0.066379203 | D29: ='Data Sheet'!C75/'Data Sheet'!C$61 -> 0.058254836 | E29: ='Data Sheet'!D75/'Data Sheet'!D$61 -> 0.055564752 | F29: ='Data Sheet'!E75/'Data Sheet'!E$61 -> 0.064185676 | G29: ='Data Sheet'!F75/'Data Sheet'!F$61 -> 0.069080819 | H29: ='Data Sheet'!G75/'Data Sheet'!G$61 -> 0.12126924 | I29: ='Data Sheet'!H75/'Data Sheet'!H$61 -> 0.060783405 | J29: ='Data Sheet'!I75/'Data Sheet'!I$61 -> 0.037543573 | ... L29: ='Data Sheet'!K75/'Data Sheet'!K$61 -> 0.041305579
B30: Receivables | C30: ='Data Sheet'!B67/'Data Sheet'!B$61 -> 0.1164113 | D30: ='Data Sheet'!C67/'Data Sheet'!C$61 -> 0.11672894 | E30: ='Data Sheet'!D67/'Data Sheet'!D$61 -> 0.084117927 | F30: ='Data Sheet'!E67/'Data Sheet'!E$61 -> 0.081143418 | G30: ='Data Sheet'!F67/'Data Sheet'!F$61 -> 0.098802367 | H30: ='Data Sheet'!G67/'Data Sheet'!G$61 -> 0.087172177 | I30: ='Data Sheet'!H67/'Data Sheet'!H$61 -> 0.051838696 | J30: ='Data Sheet'!I67/'Data Sheet'!I$61 -> 0.052601544 | ... L30: ='Data Sheet'!K67/'Data Sheet'!K$61 -> 0.059453466
B31: Inventory | C31: ='Data Sheet'!B68/'Data Sheet'!B$61 -> 0.15938837 | D31: ='Data Sheet'!C68/'Data Sheet'!C$61 -> 0.15817261 | E31: ='Data Sheet'!D68/'Data Sheet'!D$61 -> 0.14312929 | F31: ='Data Sheet'!E68/'Data Sheet'!E$61 -> 0.14436146 | G31: ='Data Sheet'!F68/'Data Sheet'!F$61 -> 0.1541526 | H31: ='Data Sheet'!G68/'Data Sheet'!G$61 -> 0.14775967 | I31: ='Data Sheet'!H68/'Data Sheet'!H$61 -> 0.16008906 | J31: ='Data Sheet'!I68/'Data Sheet'!I$61 -> 0.15560011 | ... L31: ='Data Sheet'!K68/'Data Sheet'!K$61 -> 0.12879886
B32: Cash & Bank | C32: ='Data Sheet'!B69/'Data Sheet'!B$61 -> 0.045205919 | D32: ='Data Sheet'!C69/'Data Sheet'!C$61 -> 0.031709534 | E32: ='Data Sheet'!D69/'Data Sheet'!D$61 -> 0.039420659 | F32: ='Data Sheet'!E69/'Data Sheet'!E$61 -> 0.035172721 | G32: ='Data Sheet'!F69/'Data Sheet'!F$61 -> 0.038897002 | H32: ='Data Sheet'!G69/'Data Sheet'!G$61 -> 0.08690227 | I32: ='Data Sheet'!H69/'Data Sheet'!H$61 -> 0.12268098 | J32: ='Data Sheet'!I69/'Data Sheet'!I$61 -> 0.046413749 | ... L32: ='Data Sheet'!K69/'Data Sheet'!K$61 -> 0.044082041
B34: Total Liabilities | C34: ='Data Sheet'!B61/'Data Sheet'!B$61 -> 1 | D34: ='Data Sheet'!C61/'Data Sheet'!C$61 -> 1 | E34: ='Data Sheet'!D61/'Data Sheet'!D$61 -> 1 | F34: ='Data Sheet'!E61/'Data Sheet'!E$61 -> 1 | G34: ='Data Sheet'!F61/'Data Sheet'!F$61 -> 1 | H34: ='Data Sheet'!G61/'Data Sheet'!G$61 -> 1 | I34: ='Data Sheet'!H61/'Data Sheet'!H$61 -> 1 | J34: ='Data Sheet'!I61/'Data Sheet'!I$61 -> 1 | ... L34: ='Data Sheet'!K61/'Data Sheet'!K$61 -> 1
B35: Equity Share Capital | C35: ='Data Sheet'!B57/'Data Sheet'!B$61 -> 0.028765468 | D35: ='Data Sheet'!C57/'Data Sheet'!C$61 -> 0.025375417 | E35: ='Data Sheet'!D57/'Data Sheet'!D$61 -> 0.022781238 | F35: ='Data Sheet'!E57/'Data Sheet'!E$61 -> 0.020243334 | G35: ='Data Sheet'!F57/'Data Sheet'!F$61 -> 0.02093606 | H35: ='Data Sheet'!G57/'Data Sheet'!G$61 -> 0.018926631 | I35: ='Data Sheet'!H57/'Data Sheet'!H$61 -> 0.016314632 | J35: ='Data Sheet'!I57/'Data Sheet'!I$61 -> 0.014392056 | ... L35: ='Data Sheet'!K57/'Data Sheet'!K$61 -> 0.011722399
B36: Reserves | C36: ='Data Sheet'!B58/'Data Sheet'!B$61 -> 0.52052805 | D36: ='Data Sheet'!C58/'Data Sheet'!C$61 -> 0.57624454 | E36: ='Data Sheet'!D58/'Data Sheet'!D$61 -> 0.60412507 | F36: ='Data Sheet'!E58/'Data Sheet'!E$61 -> 0.63555564 | G36: ='Data Sheet'!F58/'Data Sheet'!F$61 -> 0.64659035 | H36: ='Data Sheet'!G58/'Data Sheet'!G$61 -> 0.68858618 | I36: ='Data Sheet'!H58/'Data Sheet'!H$61 -> 0.69109554 | J36: ='Data Sheet'!I58/'Data Sheet'!I$61 -> 0.66790976 | ... L36: ='Data Sheet'!K58/'Data Sheet'!K$61 -> 0.6409678
B37: Borrowings | C37: ='Data Sheet'!B59/'Data Sheet'!B$61 -> 0.12013206 | D37: ='Data Sheet'!C59/'Data Sheet'!C$61 -> 0.11615481 | E37: ='Data Sheet'!D59/'Data Sheet'!D$61 -> 0.12609541 | F37: ='Data Sheet'!E59/'Data Sheet'!E$61 -> 0.10774878 | G37: ='Data Sheet'!F59/'Data Sheet'!F$61 -> 0.082896746 | H37: ='Data Sheet'!G59/'Data Sheet'!G$61 -> 0.055908052 | I37: ='Data Sheet'!H59/'Data Sheet'!H$61 -> 0.046990645 | J37: ='Data Sheet'!I59/'Data Sheet'!I$61 -> 0.083858006 | ... L37: ='Data Sheet'!K59/'Data Sheet'!K$61 -> 0.09030547
B38: Other Liabilities | C38: ='Data Sheet'!B60/'Data Sheet'!B$61 -> 0.33057443 | D38: ='Data Sheet'!C60/'Data Sheet'!C$61 -> 0.28222524 | E38: ='Data Sheet'!D60/'Data Sheet'!D$61 -> 0.24699828 | F38: ='Data Sheet'!E60/'Data Sheet'!E$61 -> 0.23645225 | G38: ='Data Sheet'!F60/'Data Sheet'!F$61 -> 0.24957685 | H38: ='Data Sheet'!G60/'Data Sheet'!G$61 -> 0.23657913 | I38: ='Data Sheet'!H60/'Data Sheet'!H$61 -> 0.24559918 | J38: ='Data Sheet'!I60/'Data Sheet'!I$61 -> 0.23384018 | ... L38: ='Data Sheet'!K60/'Data Sheet'!K$61 -> 0.25700433

Sheet Forecasting
B2: DABUR INDIA LTD
B4: BSE : 500096 | NSE : DABUR
B6: ='Data Sheet'!$B$1&" - "&"Sales Forecasting" -> DABUR INDIA LTD - Sales Forecasting | G6: ='Data Sheet'!$B$1&" - "&"EBITDA Forecasting" -> DABUR INDIA LTD - EBITDA Forecasting | L6: ='Data Sheet'!$B$1&" - "&"EPS Forecasting" -> DABUR INDIA LTD - EPS Forecasting
B7: Year Weight | C7: Year | D7: Sales | E7: Sales Growth | G7: Year Weight | H7: Year | I7: EBITDA | J7: EBITDA Growth | L7: Year Weight | M7: Year | N7: EPS | O7: EPS Growth
B8: 1 | C8: ='Data Sheet'!B16 -> 42094 | D8: {=TRANSPOSE('Data Sheet'!B17:K17)} -> 7795.49 | G8: 1 | H8: ='Data Sheet'!B16 -> 42094 | I8: {=TRANSPOSE('Historical FS'!C22:L22)} -> 1320.22 | L8: 1 | M8: ='Data Sheet'!B16 -> 42094 | N8: {=TRANSPOSE('Historical FS'!C42:L42)} -> 5.2048392
B9: =B8+1 -> 2 | C9: =C8+365 -> 42459 | D9: 7779.66 | E9: =D9/D8-1 -> -0.0020306613 | G9: =G8+1 -> 2 | H9: =H8+365 -> 42459 | I9: 1518.28 | J9: =I9/I8-1 -> 0.15002045 | L9: =L8+1 -> 2 | M9: =M8+365 -> 42459 | N9: 5.8934114 | O9: =N9/N8-1 -> 0.13229462
B10: =B9+1 -> 3 | C10: =C9+365 -> 42824 | D10: 7613.59 | E10: =D10/D9-1 -> -0.021346691 | G10: =G9+1 -> 3 | H10: =H9+365 -> 42824 | I10: 1511.61 | J10: =I10/I9-1 -> -0.0043931291 | L10: =L9+1 -> 3 | M10: =M9+365 -> 42824 | N10: 5.5883054 | O10: =N10/N9-1 -> -0.051770691
B11: =B10+1 -> 4 | C11: =C10+365 -> 43189 | D11: 7721.85 | E11: =D11/D10-1 -> 0.01421931 | G11: =G10+1 -> 4 | H11: =H10+365 -> 43189 | I11: 1617.44 | J11: =I11/I10-1 -> 0.070011445 | L11: =L10+1 -> 4 | M11: =M10+365 -> 43189 | N11: 6.0565427 | O11: =N11/N10-1 -> 0.083788781
B12: =B11+1 -> 5 | C12: =C11+365 -> 43554 | D12: 8514.99 | E12: =D12/D11-1 -> 0.10271373 | G12: =G11+1 -> 5 | H12: =H11+365 -> 43554 | I12: 1739.56 | J12: =I12/I11-1 -> 0.075502028 | L12: =L11+1 -> 5 | M12: =M11+365 -> 43554 | N12: 6.9323444 | O12: =N12/N11-1 -> 0.14460424
B13: =B12+1 -> 6 | C13: =C12+365 -> 43919 | D13: 8684.64 | E13: =D13/D12-1 -> 0.019923688 | G13: =G12+1 -> 6 | H13: =H12+365 -> 43919 | I13: 1792.34 | J13: =I13/I12-1 -> 0.030341006 | L13: =L12+1 -> 6 | M13: =M12+365 -> 43919 | N13: 7.0320299 | O13: =N13/N12-1 -> 0.014379757
B14: =B13+1 -> 7 | C14: =C13+365 -> 44284 | D14: 9561.65 | E14: =D14/D13-1 -> 0.10098404 | G14: =G13+1 -> 7 | H14: =H13+365 -> 44284 | I14: 2001.67 | J14: =I14/I13-1 -> 0.11679146 | L14: =L13+1 -> 7 | M14: =M13+365 -> 44284 | N14: 7.7495756 | O14: =N14/N13-1 -> 0.10203964
B15: =B14+1 -> 8 | C15: =C14+365 -> 44649 | D15: 10888.68 | E15: =D15/D14-1 -> 0.13878672 | G15: =G14+1 -> 8 | H15: =H14+365 -> 44649 | I15: 2252.01 | J15: =I15/I14-1 -> 0.12506557 | L15: =L14+1 -> 8 | M15: =M14+365 -> 44649 | N15: 8.1121104 | O15: =N15/N14-1 -> 0.046781241
B16: =B15+1 -> 9 | C16: =C15+365 -> 45014 | D16: 11529.89 | E16: =D16/D15-1 -> 0.058887762 | G16: =G15+1 -> 9 | H16: =H15+365 -> 45014 | I16: 2162.49 | J16: =I16/I15-1 -> -0.039751156 | L16: =L15+1 -> 9 | M16: =M15+365 -> 45014 | N16: 7.0884976 | O16: =N16/N15-1 -> -0.1261833
B17: =B16+1 -> 10 | C17: =C16+365 -> 45379 | D17: 12404.01 | E17: =D17/D16-1 -> 0.075813386 | G17: =G16+1 -> 10 | H17: =H16+365 -> 45379 | I17: 2399.72 | J17: =I17/I16-1 -> 0.10970224 | L17: =L16+1 -> 10 | M17: =M16+365 -> 45379 | N17: 7.4994357 | O17: =N17/N16-1 -> 0.057972524
B18: =B17+1 -> 11 | C18: =C17+365 -> 45744 | D18: =FORECAST(B18,$D$8:$D$17,$B$8:$B$17) -> 12242.538 | E18: =D18/D17-1 -> -0.013017726 | G18: =G17+1 -> 11 | H18: =H17+365 -> 45744 | I18: =FORECAST(G18,$I$8:$I$17,$G$8:$G$17) -> 2469.282 | J18: =I18/I17-1 -> 0.028987549 | L18: =L17+1 -> 11 | M18: =M17+365 -> 45744 | N18: =FORECAST(L18,$N$8:$N$17,$L$8:$L$17) -> 8.2762019 | O18: =N18/N17-1 -> 0.10357663
B19: =B18+1 -> 12 | C19: =C18+365 -> 46109 | D19: =FORECAST(B19,$D$8:$D$17,$B$8:$B$17) -> 12786.737 | E19: =D19/D18-1 -> 0.044451463 | G19: =G18+1 -> 12 | H19: =H18+365 -> 46109 | I19: =FORECAST(G19,$I$8:$I$17,$G$8:$G$17) -> 2585.2362 | J19: =I19/I18-1 -> 0.046958663 | L19: =L18+1 -> 12 | M19: =M18+365 -> 46109 | N19: =FORECAST(L19,$N$8:$N$17,$L$8:$L$17) -> 8.5599279 | O19: =N19/N18-1 -> 0.034282144
B20: =B19+1 -> 13 | C20: =C19+365 -> 46474 | D20: =FORECAST(B20,$D$8:$D$17,$B$8:$B$17) -> 13330.935 | E20: =D20/D19-1 -> 0.042559626 | G20: =G19+1 -> 13 | H20: =H19+365 -> 46474 | I20: =FORECAST(G20,$I$8:$I$17,$G$8:$G$17) -> 2701.1904 | J20: =I20/I19-1 -> 0.044852452 | L20: =L19+1 -> 13 | M20: =M19+365 -> 46474 | N20: =FORECAST(L20,$N$8:$N$17,$L$8:$L$17) -> 8.8436538 | O20: =N20/N19-1 -> 0.033145834
B21: =B20+1 -> 14 | C21: =C20+365 -> 46839 | D21: =FORECAST(B21,$D$8:$D$17,$B$8:$B$17) -> 13875.134 | E21: =D21/D20-1 -> 0.040822246 | G21: =G20+1 -> 14 | H21: =H20+365 -> 46839 | I21: =FORECAST(G21,$I$8:$I$17,$G$8:$G$17) -> 2817.1445 | J21: =I21/I20-1 -> 0.042927068 | L21: =L20+1 -> 14 | M21: =M20+365 -> 46839 | N21: =FORECAST(L21,$N$8:$N$17,$L$8:$L$17) -> 9.1273798 | O21: =N21/N20-1 -> 0.032082435

Sheet Market Return
B2: DABUR INDIA LTD
B4: BSE : 500096 | NSE : DABUR
B6: Return on Market using Annual Return of 24 Years
B8: Year | C8: Return | E8: Year | F8: Return
B9: 2023 | C9: 0.1942 | E9: 2009 | F9: 0.7576 | H9: Average Return | I9: =AVERAGE(C9:C35) -> 0.15609167
B10: 2022 | C10: 0.0432 | E10: 2008 | F10: -0.5179 | H10: Dividend Yield | I10: 0.0087
B11: 2021 | C11: 0.2412 | E11: 2007 | F11: 0.5477 | H11: Total Market Return | I11: =+I9+I10 -> 0.16479167
B12: 2020 | C12: 0.149 | E12: 2006 | F12: 0.3983
B13: 2019 | C13: 0.1202 | E13: 2005 | F13: 0.3634
B14: 2018 | C14: 0.0315 | E14: 2004 | F14: 0.1068
B15: 2017 | C15: 0.2865 | E15: 2003 | F15: 0.719
B16: 2016 | C16: 0.0301 | E16: 2002 | F16: 0.0325
B17: 2015 | C17: -0.0406 | E17: 2001 | F17: -0.1618
B18: 2014 | C18: 0.3139 | E18: 2000 | F18: -0.1465
B19: 2013 | C19: 0.0676
B20: 2012 | C20: 0.277
B21: 2011 | C21: -0.2462
B22: 2010 | C22: 0.1795
B26: 2009 | C26: 0.7576
B27: 2008 | C27: -0.5179
B28: 2007 | C28: 0.5477
B29: 2006 | C29: 0.3983
B30: 2005 | C30: 0.3634
B31: 2004 | C31: 0.1068
B32: 2003 | C32: 0.719
B33: 2002 | C33: 0.0325
... B35: 2000 | C35: -0.1465

Sheet WACC
B2: DABUR INDIA LTD
B4: BSE : 500096 | NSE : DABUR
B6: Weighted Average Cost of Capital
B7: All figures are in INR unless stated otherwise
B9: Peer Companies
I10: Debt / | J10: Debt / | K10: Levered | L10: Unlevered
B11: Name of the Company | E11: Country | F11: Total Debt | G11: Total Equity | H11: Tax Rate 1 | I11: Equity | J11: Capital | K11: Beta 2 | L11: Beta 3
L12: `
B13: Hind. Unilever | E13: India | F13: 1139 | G13: 611503.89 | H13: 0.3 | I13: =F13/G13 -> 0.001862621 | J13: =F13/(F13+G13) -> 0.0018591581 | K13: 0.31 | L13: =K13/(1+(1-H13)*I13) -> 0.30959634
B14: Nestle India | E14: India | F14: 279.93 | G14: 182975.03 | H14: 0.3 | I14: =F14/G14 -> 0.0015298809 | J14: =F14/(F14+G14) -> 0.0015275439 | K14: 0.36 | L14: =K14/(1+(1-H14)*I14) -> 0.35961488
B15: Britannia Inds. | E15: India | F15: 3037.7 | G15: 110689.96 | H15: 0.3 | I15: =F15/G15 -> 0.02744332 | J15: =F15/(F15+G15) -> 0.026710301 | K15: 0.46 | L15: =K15/(1+(1-H15)*I15) -> 0.45132981
B16: Godrej Consumer | E16: India | F16: 1164.46 | G16: 96256.38 | H16: 0.3 | I16: =F16/G16 -> 0.012097484 | J16: =F16/(F16+G16) -> 0.011952884 | K16: 0.46 | L16: =K16/(1+(1-H16)*I16) -> 0.45613732
B17: Dabur India | E17: India | F17: 1068.11 | G17: 94940.38 | H17: 0.3 | I17: =F17/G17 -> 0.011250324 | J17: =F17/(F17+G17) -> 0.011125162 | K17: 0.62 | L17: =K17/(1+(1-H17)*I17) -> 0.61515551
G19: Average | H19: =AVERAGE(H13:H17) -> 0.3 | I19: =AVERAGE(I13:I17) -> 0.010836726 | J19: =AVERAGE(J13:J17) -> 0.01063501 | K19: =AVERAGE(K13:K17) -> 0.442 | L19: =AVERAGE(L13:L17) -> 0.43836677
G20: Median | H20: =MEDIAN(H13:H17) -> 0.3 | I20: =MEDIAN(I13:I17) -> 0.011250324 | J20: =MEDIAN(J13:J17) -> 0.011125162 | K20: =MEDIAN(K13:K17) -> 0.46 | L20: =MEDIAN(L13:L17) -> 0.45132981
B23: Cost of Debt | H23: Cost of Equity
B25: Pre-Tax Cost of Debt | F25: 0.0765 | H25: Risk Free Rate | L25: 0.0697
B26: Tax Rate | F26: 0.3 | H26: Equity Risk Return | L26: ='Market Return'!I11-WACC!L25 -> 0.095091667
B27: Post-Tax Cost of Debt | F27: =F25*(1-F26) -> 0.05355 | H27: Levered Beta | L27: =L36 -> 0.45488413
H28: Cost of Equity | L28: =L25+(L26*L27) -> 0.11295569
B31: Capital Structure | H31: Levered Beta
E33: Current | F33: Target | H33: Comps Median Unlevered Beta | L33: =L20 -> 0.45132981
B34: Total Debt | D34: =F17 -> 1068.11 | E34: =D34/D36 -> 0.011125162 | F34: =J20 -> 0.011125162 | H34: Target Debt / Equity | L34: =F38 -> 0.011250324
B35: Market Capitalization | D35: =G17 -> 94940.38 | E35: =D35/$D$36 -> 0.98887484 | F35: =F36-F34 -> 0.98887484 | H35: Tax Rate | L35: =F26 -> 0.3
B36: Total Capital | D36: =SUM(D34:D35) -> 96008.49 | E36: =D36/$D$36 -> 1 | F36: 1 | H36: Levered Beta | L36: =L33*(1+(1-L35)*L34) -> 0.45488413
B38: Debt / Equity | E38: =E34/E35 -> 0.011250324 | F38: =F34/F35 -> 0.011250324 | H38: Wieghted Average Cost of Capital
B40: 1. Tax Rate considered as Marginal Tax Rate for the country | K40: Total Cost | L40: Total Weight
B41: 2. Levered Beta is based on 5 years monthly data | H41: Debt | K41: =F27 -> 0.05355 | L41: =F34 -> 0.011125162
B42: 3. Unlevered Beta = Levered Beta/(1+(1-Tax Rate)*Debt/Equity) | H42: Equity | K42: =L28 -> 0.11295569 | L42: =F35 -> 0.98887484
B43: 4. Levered Beta = Unlevered Beta*(1+(1-Tax Rate)*Debt/Equity) | H43: Weighted Average Cost of Capital | L43: =SUMPRODUCT(K41:K42,L41:L42) -> 0.11229479

Sheet Intrinsic Growth
B2: DABUR INDIA LTD
B4: BSE : 500096 | NSE : DABUR
B6: ="Intrinsic Growth - " & 'Data Sheet'!B1 -> Intrinsic Growth - DABUR INDIA LTD
B7: Calculation of ROIC | F7: ='Data Sheet'!G16 -> 43921 | G7: ='Data Sheet'!H16 -> 44286 | H7: ='Data Sheet'!I16 -> 44651 | I7: ='Data Sheet'!J16 -> 45016 | J7: ='Data Sheet'!K16 -> 45382
B9: Current Assets
B10: Inventories | F10: ='Raw FS'!H31 -> 1380 | G10: ='Raw FS'!I31 -> 1734 | H10: ='Raw FS'!J31 -> 1911 | I10: ='Raw FS'!K31 -> 2024 | J10: ='Raw FS'!L31 -> 1947
B11: Trade receivables | F11: ='Raw FS'!H32 -> 814 | G11: ='Raw FS'!I32 -> 562 | H11: ='Raw FS'!J32 -> 646 | I11: ='Raw FS'!K32 -> 849 | J11: ='Raw FS'!L32 -> 899
B12: Short term loans | F12: ='Raw FS'!H34 -> 23 | G12: ='Raw FS'!I34 -> 20 | H12: ='Raw FS'!J34 -> 24 | I12: ='Raw FS'!K34 -> 33 | J12: ='Raw FS'!L34 -> 45
B13: Other asset items | F13: ='Raw FS'!H35 -> 1109 | G13: ='Raw FS'!I35 -> 639 | H13: ='Raw FS'!J35 -> 437 | I13: ='Raw FS'!K35 -> 401 | J13: ='Raw FS'!L35 -> 579
B14: Total Current Assets | F14: =SUM(F10:F13) -> 3326 | G14: =SUM(G10:G13) -> 2955 | H14: =SUM(H10:H13) -> 3018 | I14: =SUM(I10:I13) -> 3307 | J14: =SUM(J10:J13) -> 3470
B16: Current Liabilities
B17: ='Raw FS'!B12 -> Trade Payables | F17: ='Raw FS'!H12 -> 1482 | G17: ='Raw FS'!I12 -> 1915 | H17: ='Raw FS'!J12 -> 2018 | I17: ='Raw FS'!K12 -> 2187 | J17: ='Raw FS'!L12 -> 2422
B18: Advance from Customers | F18: ='Raw FS'!H13 -> 30 | G18: ='Raw FS'!I13 -> 43 | H18: ='Raw FS'!J13 -> 37 | I18: ='Raw FS'!K13 -> 9 | J18: ='Raw FS'!L13 -> 33
B19: ='Raw FS'!B14 -> Other liability items | F19: ='Raw FS'!H14 -> 660 | G19: ='Raw FS'!I14 -> 666 | H19: ='Raw FS'!J14 -> 777 | I19: ='Raw FS'!K14 -> 842 | J19: ='Raw FS'!L14 -> 994
B20: Total Current Liabilities | F20: =SUM(F17:F19) -> 2172 | G20: =SUM(G17:G19) -> 2624 | H20: =SUM(H17:H19) -> 2832 | I20: =SUM(I17:I19) -> 3038 | J20: =SUM(J17:J19) -> 3449
A22: # | B22: Net Working Capital | F22: =F14-F20 -> 1154 | G22: =G14-G20 -> 331 | H22: =H14-H20 -> 186 | I22: =I14-I20 -> 269 | J22: =J14-J20 -> 21
B24: Non-Current Assets
B25: Land | F25: ='Raw FS'!H18 -> 103 | G25: ='Raw FS'!I18 -> 93 | H25: ='Raw FS'!J18 -> 123 | I25: ='Raw FS'!K18 -> 141 | J25: ='Raw FS'!L18 -> 145
B26: Building | F26: ='Raw FS'!H19 -> 1054 | G26: ='Raw FS'!I19 -> 1057 | H26: ='Raw FS'!J19 -> 1144 | I26: ='Raw FS'!K19 -> 1279 | J26: ='Raw FS'!L19 -> 1513
B27: Plant Machinery | F27: ='Raw FS'!H20 -> 1719 | G27: ='Raw FS'!I20 -> 1862 | H27: ='Raw FS'!J20 -> 2074 | I27: ='Raw FS'!K20 -> 2408 | J27: ='Raw FS'!L20 -> 2775
B28: Equipments | F28: ='Raw FS'!H21 -> 69 | G28: ='Raw FS'!I21 -> 73 | H28: ='Raw FS'!J21 -> 78 | I28: ='Raw FS'!K21 -> 88 | J28: ='Raw FS'!L21 -> 93
B29: Furniture n fittings | F29: ='Raw FS'!H22 -> 126 | G29: ='Raw FS'!I22 -> 129 | H29: ='Raw FS'!J22 -> 134 | I29: ='Raw FS'!K22 -> 148 | J29: ='Raw FS'!L22 -> 159
B30: Vehicles | F30: ='Raw FS'!H23 -> 45 | G30: ='Raw FS'!I23 -> 45 | H30: ='Raw FS'!J23 -> 47 | I30: ='Raw FS'!K23 -> 43 | J30: ='Raw FS'!L23 -> 44
B31: Intangible Assets | F31: ='Raw FS'!H24 -> 374 | G31: ='Raw FS'!I24 -> 375 | H31: ='Raw FS'!J24 -> 291 | I31: ='Raw FS'!K24 -> 1322 | J31: ='Raw FS'!L24 -> 1321
B32: Other fixed assets | F32: ='Raw FS'!H25 -> 139 | G32: ='Raw FS'!I25 -> 146 | H32: ='Raw FS'!J25 -> 149 | I32: ='Raw FS'!K25 -> 154 | J32: ='Raw FS'!L25 -> 164
B33: Gross Block | F33: =SUM(F25:F32) -> 3629 | G33: =SUM(G25:G32) -> 3780 | H33: =SUM(H25:H32) -> 4040 | I33: =SUM(I25:I32) -> 5583 | J33: =SUM(J25:J32) -> 6214
B34: Accumulated Depreciation | F34: =-'Raw FS'!H27 -> -1377 | G34: =-'Raw FS'!I27 -> -1536 | H34: =-'Raw FS'!J27 -> -1733 | I34: =-'Raw FS'!K27 -> -2004 | J34: =-'Raw FS'!L27 -> -2400
B35: Net Non-Current Assets | F35: =SUM(F33:F34) -> 2252 | G35: =SUM(G33:G34) -> 2244 | H35: =SUM(H33:H34) -> 2307 | I35: =SUM(I33:I34) -> 3579 | J35: =SUM(J33:J34) -> 3814
A37: # | B37: Invested Capital | F37: =F35+F22 -> 3406 | G37: =G35+G22 -> 2575 | H37: =H35+H22 -> 2493 | I37: =I35+I22 -> 3848 | J37: =J35+J22 -> 3835
B38: EBIT | F38: ='Historical FS'!H31+'Historical FS'!H25 -> 1571.89 | G38: ='Historical FS'!I31+'Historical FS'!I25 -> 1761.54 | H38: ='Historical FS'!J31+'Historical FS'!J25 -> 1999.12 | I38: ='Historical FS'!K31+'Historical FS'!K25 -> 1851.53 | J38: ='Historical FS'!L31+'Historical FS'!L25 -> 2000.51
A40: # | B40: ROIC | F40: =F38/F37 -> 0.46150617 | G40: =G38/G37 -> 0.6840932 | H40: =H38/H37 -> 0.8018933 | I40: =I38/I37 -> 0.48116684 | J40: =J38/J37 -> 0.52164537
B42: Calculation of Reinvestment Rate | F42: ='Historical FS'!H7 -> 43921 | G42: ='Historical FS'!I7 -> 44286 | H42: ='Historical FS'!J7 -> 44651 | I42: ='Historical FS'!K7 -> 45016 | J42: ='Historical FS'!L7 -> 45382
B44: Net Capex | F44: =-('Raw FS'!J50-'Raw FS'!J51) -> 434 | G44: =-('Raw FS'!K50-'Raw FS'!K51) -> 316 | H44: =-('Raw FS'!L50-'Raw FS'!L51) -> 379 | I44: =-('Raw FS'!M50-'Raw FS'!M51) -> 532 | J44: =-('Raw FS'!N50-'Raw FS'!N51) -> 567
B45: Change in Working Capital | G45: =G22-F22 -> -823 | H45: =H22-G22 -> -145 | I45: =I22-H22 -> 83 | J45: =J22-I22 -> -248
B46: Depreciation | F46: =-('Data Sheet'!G26) -> -220.45 | G46: =-('Data Sheet'!H26) -> -240.13 | H46: =-('Data Sheet'!I26) -> -252.89 | I46: =-('Data Sheet'!J26) -> -310.96 | J46: =-('Data Sheet'!K26) -> -399.21
B48: EBIT | F48: =F38 -> 1571.89 | G48: =G38 -> 1761.54 | H48: =H38 -> 1999.12 | I48: =I38 -> 1851.53 | J48: =J38 -> 2000.51
B49: Marginal Tax Rate | F49: 0.25 | G49: 0.25 | H49: 0.25 | I49: 0.25 | J49: 0.25
B50: EBT | F50: =F48*(1-F49) -> 1178.9175 | G50: =G48*(1-G49) -> 1321.155 | H50: =H48*(1-H49) -> 1499.34 | I50: =I48*(1-I49) -> 1388.6475 | J50: =J48*(1-J49) -> 1500.3825
B52: Reinvestment | G52: =SUM(G44:G46) -> -747.13 | H52: =SUM(H44:H46) -> -18.89 | I52: =SUM(I44:I46) -> 304.04 | J52: =SUM(J44:J46) -> -80.21
B53: Reinvestment Rate | G53: =G52/G50 -> -0.56551275 | H53: =H52/H50 -> -0.012598877 | I53: =I52/I50 -> 0.21894685 | J53: =J52/J50 -> -0.053459701
I55: 4 Years Average | J55: =AVERAGE(G53:J53) -> -0.10315612
I56: 4 Years Median | J56: =MEDIAN(G53:J53) -> -0.033029289
B58: Calculation of Growth Rate | F58: =F42 -> 43921 | G58: =G42 -> 44286 | H58: =H42 -> 44651 | I58: =I42 -> 45016 | J58: =J42 -> 45382
B60: Reinvestment Rate | G60: =G53 -> -0.56551275 | H60: =H53 -> -0.012598877 | I60: =I53 -> 0.21894685 | J60: =J53 -> -0.053459701
B61: ROIC | G61: =G40 -> 0.6840932 | H61: =H40 -> 0.8018933 | I61: =I40 -> 0.48116684 | J61: =J40 -> 0.52164537
B63: Intrinsic Growth Rate | G63: =G60*G61 -> -0.38686343 | H63: =H60*H61 -> -0.010102955 | I63: =I60*I61 -> 0.10534997 | J63: =J60*J61 -> -0.027887006
I65: 4 Years Average | J65: =AVERAGE(G63:J63) -> -0.079875856
I66: 4 Years Median | J66: =MEDIAN(G63:J63) -> -0.01899498

Sheet DCF
B2: DABUR INDIA LTD
B4: BSE : 500096 | NSE : DABUR
B6: Calculation of PV of FCFF | F6: ='Intrinsic Growth'!J7 -> 45382 | G6: =F6+365 -> 45747 | H6: =G6+365 -> 46112 | I6: =H6+365 -> 46477 | J6: =I6+365 -> 46842 | K6: =J6+365 -> 47207
B8: EBIT | F8: =SUM('Data Sheet'!K29:K30,'Data Sheet'!K27) -> 2514.29 | G8: =F8*(1+$E$17) -> 2652.0731 | H8: =G8*(1+$E$17) -> 2797.4067 | I8: =H8*(1+$E$17) -> 2950.7046 | J8: =I8*(1+$E$17) -> 3112.4032 | K8: =J8*(1+$E$17) -> 3282.9629
B9: Tax Rate | F9: 0.25 | G9: =F9 -> 0.25 | H9: =G9 -> 0.25 | I9: =H9 -> 0.25 | J9: =I9 -> 0.25 | K9: =J9 -> 0.25
B10: EBIT(1-T) | F10: =F8*(1-F9) -> 1885.7175 | G10: =F10*(1+$E$17) -> 1989.0548 | H10: =G10*(1+$E$17) -> 2098.055 | I10: =H10*(1+$E$17) -> 2213.0284 | J10: =I10*(1+$E$17) -> 2334.3024 | K10: =J10*(1+$E$17) -> 2462.2222
B11: less: Reinvestment Rate | F11: ='Intrinsic Growth'!J56 -> -0.033029289 | G11: =F11-(($F$11-$K$11)/4) -> 0.079453033 | H11: =G11-(($F$11-$K$11)/4) -> 0.19193536 | I11: =H11-(($F$11-$K$11)/4) -> 0.30441768 | J11: =I11-(($F$11-$K$11)/4) -> 0.4169 | K11: 0.4169
B12: Free Cash Flows to Firm | F12: =F10*(1-F11) -> 1948.0014 | G12: =G10*(1-G11) -> 1831.0184 | H12: =H10*(1-H11) -> 1695.3641 | I12: =I10*(1-I11) -> 1539.3435 | J12: =J10*(1-J11) -> 1361.1317 | K12: =K10*(1-K11) -> 1435.7217
B13: Mid Year Convention | G13: 0.5 | H13: =G13+1 -> 1.5 | I13: =H13+1 -> 2.5 | J13: =I13+1 -> 3.5 | K13: =J13+1 -> 4.5
B14: Discounting Factor | G14: =1/(1+$E$19)^G13 -> 0.94817838 | H14: =1/(1+$E$19)^H13 -> 0.85245241 | I14: =1/(1+$E$19)^I13 -> 0.76639073 | J14: =1/(1+$E$19)^J13 -> 0.68901763 | K14: =1/(1+$E$19)^K13 -> 0.61945596
B15: PV of FCFF | G15: =G12*G14 -> 1736.132 | H15: =H12*H14 -> 1445.2172 | I15: =I12*I14 -> 1179.7386 | J15: =J12*J14 -> 937.84376 | K15: =K12*K14 -> 889.36639
B17: Expected Growth | E17: 0.0548
B18: Terminal Growth | E18: 0.072
B19: WACC | E19: =WACC!L43 -> 0.11229479
B22: Calculation of Terminal Value | F22: Senstivity Analysis - Terminal Value
F23: =D28 -> 37583.003 | G23: 0.092 | H23: 0.1 | I23: =D25 -> 0.11229479 | J23: 0.12 | K23: 0.13
B24: FCFF (n+1) | D24: =K12*(1+E17) -> 1514.3993 | F24: 0.05 | G24: 36057.126 | H24: 30287.986 | I24: 30287.986 | J24: 21634.276 | K24: 18929.991
B25: WACC | D25: =E19 -> 0.11229479 | F25: 0.06 | G25: 47324.978 | H25: 37859.982 | I25: 37859.982 | J25: 25239.988 | K25: 21634.276
B26: Terminal Growth Rate | D26: =E18 -> 0.072 | F26: =D26 -> 0.072 | G26: 47324.978 | H26: 37859.982 | I26: 37859.982 | J26: 25239.988 | K26: 21634.276
F27: 0.08 | G27: 126199.94 | H27: 75719.965 | I27: 75719.965 | J27: 37859.982 | K27: 30287.986
B28: Terminal Value | D28: =D24/(D25-D26) -> 37583.003 | F28: 0.091 | G28: 1514399.3 | H28: 168266.59 | I28: 168266.59 | J28: 52220.665 | K28: 38830.751
B30: Calculation of Equity Value | F30: Senstivity Analysis - Equity Value per Share
B31: PV of FCFF | D31: =SUM(G15:K15) -> 6188.2979 | F31: =D39 -> 163.50225 | G31: 0.092 | H31: 0.1 | I31: =D25 -> 0.11229479 | J31: 0.12 | K31: 0.13
B32: PV of Terminal Value | D32: =D28*K14 -> 23281.015 | F32: 0.05 | G32: 158.16902 | H32: 138.00479 | I32: 138.00479 | J32: 107.75843 | K32: 98.306448
B33: Value of Operating Activities | D33: =SUM(D31:D32) -> 29469.313 | F33: 0.06 | G33: 197.55229 | H33: 164.47034 | I33: 164.47034 | J33: 120.36108 | K33: 107.75843
F34: =D26 -> 0.072 | G34: 197.55229 | H34: 164.47034 | I34: 164.47034 | J34: 120.36108 | K34: 107.75843
B35: Add : Cash | D35: ='Data Sheet'!K69 -> 666.36 | F35: 0.08 | G35: 473.23519 | H35: 296.79813 | I35: 296.79813 | J35: 164.47034 | K35: 138.00479
B36: Less : Debt | D36: =SUM('Raw FS'!L6:L7) -> 1158 | F36: 0.085 | G36: 788.30136 | H36: 385.01666 | I36: 385.01666 | J36: 183.37431 | K36: 149.76726
B37: Equity Value | D37: =D33+D35-D36 -> 28977.673
B38: No. of Shares | D38: ='Data Sheet'!B6 -> 177.23104
B39: Equity Value per Share | D39: =D37/D38 -> 163.50225
B41: Share Price | D41: ='Data Sheet'!B8 -> 625.7
B42: Discount/Premium | D42: =D41/D39 -> 3.8268587

Sheet Comps Val
B2: DABUR INDIA LTD
B4: BSE : 500096 | NSE : DABUR
B5: Amount in crores
B6: Comparable Company Valuation
D7: Market Data | J7: Financials | N7: Valuation
B8: Company | C8: Ticker | D8: Share Price | E8: Shares Outstanding | F8: Equity Value | G8: Net Debt | H8: Enterprise Value | J8: Revenue | K8: EBITDA | L8: Net Income | N8: EV/Revenue | O8: EV/EBITDA | P8: P/E
B10: ='Raw FS'!C78 -> Dabur India | D10: ='Raw FS'!D78 -> 633 | E10: ='Raw FS'!E78 -> 177.23 | F10: =D10*E10 -> 112186.59 | G10: ='Raw FS'!M78 -> 698.73 | H10: ='Raw FS'!H78 -> 112886.04 | J10: ='Raw FS'!I78 -> 12622.65 | K10: ='Raw FS'!J78 -> 3461.7 | L10: ='Raw FS'!K78 -> 1849.05 | N10: =H10/J10 -> 8.9431332 | O10: =H10/K10 -> 32.610001 | P10: =F10/L10 -> 60.672556
B11: Hind. Unilever | D11: ='Raw FS'!D73 -> 2966.25 | E11: ='Raw FS'!E73 -> 234.96 | F11: =D11*E11 -> 696950.1 | G11: ='Raw FS'!M73 -> -6075 | H11: ='Raw FS'!H73 -> 690872.51 | J11: ='Raw FS'!I73 -> 62107 | K11: ='Raw FS'!J73 -> 23528 | L11: ='Raw FS'!K73 -> 10338 | N11: =H11/J11 -> 11.123907 | O11: =H11/K11 -> 29.363844 | P11: =F11/L11 -> 67.416338
B12: Nestle India | D12: ='Raw FS'!D74 -> 2745.7 | E12: ='Raw FS'!E74 -> 96.42 | F12: =D12*E12 -> 264740.39 | G12: ='Raw FS'!M74 -> -434.32 | H12: ='Raw FS'!H74 -> 264294.31 | J12: ='Raw FS'!I74 -> 19718.78 | K12: ='Raw FS'!J74 -> 6592.39 | L12: ='Raw FS'!K74 -> 3244.46 | N12: =H12/J12 -> 13.403178 | O12: =H12/K12 -> 40.090818 | P12: =F12/L12 -> 81.597675
B13: Varun Beverages | D13: ='Raw FS'!D75 -> 608.55 | E13: ='Raw FS'!E75 -> 324.87 | F13: =D13*E13 -> 197699.64 | G13: ='Raw FS'!M75 -> 6301.06 | H13: ='Raw FS'!H75 -> 204051.43 | J13: ='Raw FS'!I75 -> 18052.38 | K13: ='Raw FS'!J75 -> 3820.07 | L13: ='Raw FS'!K75 -> 2467.63 | N13: =H13/J13 -> 11.303298 | O13: =H13/K13 -> 53.415626 | P13: =F13/L13 -> 80.117213
B14: Britannia Inds. | D14: ='Raw FS'!D76 -> 6268.8 | E14: ='Raw FS'!E76 -> 24.09 | F14: =D14*E14 -> 151015.39 | G14: ='Raw FS'!M76 -> 1618.61 | H14: ='Raw FS'!H76 -> 152614.13 | J14: ='Raw FS'!I76 -> 17008.86 | K14: ='Raw FS'!J76 -> 4874.5 | L14: ='Raw FS'!K76 -> 2183.65 | N14: =H14/J14 -> 8.9726254 | O14: =H14/K14 -> 31.308674 | P14: =F14/L14 -> 69.157325
B15: Godrej Consumer | D15: ='Raw FS'!D77 -> 1388.65 | E15: ='Raw FS'!E77 -> 102.29 | F15: =D15*E15 -> 142045.01 | G15: ='Raw FS'!M77 -> 2675.26 | H15: ='Raw FS'!H77 -> 144719.57 | J15: ='Raw FS'!I77 -> 13978.78 | K15: ='Raw FS'!J77 -> 3087.87 | L15: ='Raw FS'!K77 -> -428.69 | N15: =H15/J15 -> 10.352804 | O15: =H15/K15 -> 46.867119 | P15: =F15/L15 -> -331.34668
B16: Colgate-Palmoliv | D16: ='Raw FS'!D79 -> 3764.05 | E16: ='Raw FS'!E79 -> 27.2 | F16: =D16*E16 -> 102382.16 | G16: ='Raw FS'!M79 -> -1302.03 | H16: ='Raw FS'!H79 -> 101074.72 | J16: ='Raw FS'!I79 -> 5853.46 | K16: ='Raw FS'!J79 -> 2967.52 | L16: ='Raw FS'!K79 -> 1413.96 | N16: =H16/J16 -> 17.267517 | O16: =H16/K16 -> 34.060333 | P16: =F16/L16 -> 72.408102
B17: P & G Hygiene | D17: ='Raw FS'!D80 -> 16413.15 | E17: ='Raw FS'!E80 -> 3.25 | F17: =D17*E17 -> 53342.738 | G17: ='Raw FS'!M80 -> -585.12 | H17: ='Raw FS'!H80 -> 52693.17 | J17: ='Raw FS'!I80 -> 4205.7 | K17: ='Raw FS'!J80 -> 1566.49 | L17: ='Raw FS'!K80 -> 675.02 | N17: =H17/J17 -> 12.528989 | O17: =H17/K17 -> 33.637731 | P17: =F17/L17 -> 79.023936
B18: Emami | D18: ='Raw FS'!D81 -> 751.65 | E18: ='Raw FS'!E81 -> 43.65 | F18: =D18*E18 -> 32809.522 | G18: ='Raw FS'!M81 -> -107.43 | H18: ='Raw FS'!H81 -> 32702.09 | J18: ='Raw FS'!I81 -> 3658.5 | K18: ='Raw FS'!J81 -> 1188.32 | L18: ='Raw FS'!K81 -> 737.99 | N18: =H18/J18 -> 8.9386607 | O18: =H18/K18 -> 27.519599 | P18: =F18/L18 -> 44.45795
B19: Gillette India | D19: ='Raw FS'!D82 -> 8490.55 | E19: ='Raw FS'!E82 -> 3.26 | F19: =D19*E19 -> 27679.193 | G19: ='Raw FS'!M82 -> -475.58 | H19: ='Raw FS'!H82 -> 27195.12 | J19: ='Raw FS'!I82 -> 2633.08 | K19: ='Raw FS'!J82 -> 847.9 | L19: ='Raw FS'!K82 -> 411.7 | N19: =H19/J19 -> 10.328254 | O19: =H19/K19 -> 32.073499 | P19: =F19/L19 -> 67.231462
B21: High | N21: =MAX(N10:N19) -> 17.267517 | O21: =MAX(O10:O19) -> 53.415626 | P21: =MAX(P10:P19) -> 81.597675
B22: 75th Percentile | N22: =QUARTILE(N10:N19,3) -> 12.222566 | O22: =QUARTILE(O10:O19,3) -> 38.583197 | P22: =QUARTILE(P10:P19,3) -> 77.369978
B23: Average | N23: =AVERAGE(N10:N19) -> 11.316237 | O23: =AVERAGE(O10:O19) -> 36.094724 | P23: =AVERAGE(P10:P19) -> 29.073588
B24: Median | N24: =MEDIAN(N10:N19) -> 10.738356 | O24: =MEDIAN(O10:O19) -> 33.123866 | P24: =MEDIAN(P10:P19) -> 68.286831
B25: 25th Percentile | N25: =QUARTILE(N10:N19,1) -> 9.3115327 | O25: =QUARTILE(O10:O19,1) -> 31.49988 | P25: =QUARTILE(P10:P19,1) -> 62.312283
B26: Low | N26: =MIN(N10:N19) -> 8.9386607 | O26: =MIN(O10:O19) -> 27.519599 | P26: =MIN(P10:P19) -> -331.34668
B28: Dabur Comparable Valuation | N28: EV/Revenue | O28: EV/EBITDA | P28: P/E
B30: Implied Enterprise Value | N30: =N24*H10 -> 1212210.4 | O30: =O24*H10 -> 3739222.1 | P30: =P31+P32 -> 126964.5
B31: Net Debt | N31: =$G$10 -> 698.73 | O31: =$G$10 -> 698.73 | P31: =$G$10 -> 698.73
B32: Implied Market Value | N32: =N30-N31 -> 1211511.7 | O32: =O30-O31 -> 3738523.4 | P32: =P24*L10 -> 126265.77
B33: Shares Outstanding | N33: =$E$10 -> 177.23 | O33: =$E$10 -> 177.23 | P33: =$E$10 -> 177.23
B34: Implied Value per Share | N34: =N32/N33 -> 6835.8163 | O34: =O32/O33 -> 21094.19 | P34: =P32/P33 -> 712.44014
N36: =IF(N34>$D$10,"UnderValued","OverValued") -> UnderValued | O36: =IF(O34>$D$10,"UnderValued","OverValued") -> UnderValued | P36: =IF(P34>$D$10,"UnderValued","OverValued") -> UnderValued

Sheet Football Field Analysis
B3: DABUR INDIA LTD
B5: BSE : 500096 | NSE : DABUR
J7: Football Field Analysis Data
L8: OpenLow | M8: Low | N8: OpenHigh | O8: High
J10: Comps | L10: 608 | M10: 608 | N10: 959 | O10: 959
J11: DCF Bear | L11: =DCF!$K$32 -> 98.306448 | M11: =DCF!$K$32 -> 98.306448 | N11: =DCF!$K$36 -> 149.76726 | O11: =DCF!$K$36 -> 149.76726
J12: DCF Base | L12: =DCF!$I$32 -> 138.00479 | M12: =DCF!$I$32 -> 138.00479 | N12: =DCF!$I$36 -> 385.01666 | O12: =DCF!$I$36 -> 385.01666
J13: DCF Bull | L13: =DCF!$G$32 -> 158.16902 | M13: =DCF!$G$32 -> 158.16902 | N13: =DCF!$G$36 -> 788.30136 | O13: =DCF!$G$36 -> 788.30136
J14: 52W H/L | L14: 489 | M14: 489 | N14: 672 | O14: 672

Sheet VAR
B2: DABUR INDIA LTD
B4: BSE : 500096 | NSE : DABUR
B6: Date | C6: Adj Close | D6: Returns | E6: Sorted Return | F6: Replication | G6: Simulated Return | I6: Calculation of Value at Risk
B7: Sep 27, 2024 | C7: 633 | D7: =(C7-C8)/C8 -> 0 | E7: 0.13453591 | F7: 1 | G7: =_xlfn.NORM.INV(RAND(),$M$9,$M$10) -> 0.053929875
B8: Sep 23, 2024 | C8: 633 | D8: =(C8-C9)/C9 -> -0.051756423 | E8: 0.12474667 | F8: 2 | G8: =_xlfn.NORM.INV(RAND(),$M$9,$M$10) -> 0.041075518 | I8: Historical Approach
B9: Sep 16, 2024 | C9: 667.55 | D9: =(C9-C10)/C10 -> 0.010062037 | E9: 0.089178578 | F9: 3 | G9: =_xlfn.NORM.INV(RAND(),$M$9,$M$10) -> 0.0067246245 | I9: Mean | M9: =AVERAGE(E7:E253) -> 0.0018408769
B10: Sep 9, 2024 | C10: 660.9 | D10: =(C10-C11)/C11 -> 0.025605214 | E10: 0.080488569 | F10: 4 | G10: =_xlfn.NORM.INV(RAND(),$M$9,$M$10) -> -0.010705745 | I10: STD | M10: =_xlfn.STDEV.S(E7:E253) -> 0.03015119
B11: Sep 2, 2024 | C11: 644.4 | D11: =(C11-C12)/C12 -> 0.011378796 | E11: 0.06564543 | F11: 5 | G11: =_xlfn.NORM.INV(RAND(),$M$9,$M$10) -> 0.032254158 | I11: Min | M11: =MIN(E7:E253) -> -0.099794303
B12: Aug 26, 2024 | C12: 637.15 | D12: =(C12-C13)/C13 -> -0.0094830937 | E12: 0.063854071 | F12: 6 | G12: =_xlfn.NORM.INV(RAND(),$M$9,$M$10) -> 0.0054158902 | I12: Max | M12: =MAX(E7:E253) -> 0.13453591
B13: Aug 19, 2024 | C13: 643.25 | D13: =(C13-C14)/C14 -> 0.041531736 | E13: 0.062177677 | F13: 7 | G13: =_xlfn.NORM.INV(RAND(),$M$9,$M$10) -> 0.0030620831 | I13: CMP | M13: ='Data Sheet'!B8 -> 625.7
B14: Aug 12, 2024 | C14: 617.6 | D14: =(C14-C15)/C15 -> -0.010177098 | E14: 0.056020013 | F14: 8 | G14: =_xlfn.NORM.INV(RAND(),$M$9,$M$10) -> 0.029704439
B15: Aug 5, 2024 | C15: 623.95 | D15: =(C15-C16)/C16 -> -0.0057365947 | E15: 0.053376336 | F15: 9 | G15: =_xlfn.NORM.INV(RAND(),$M$9,$M$10) -> 0.0417404
B16: Jul 29, 2024 | C16: 627.55 | D16: =(C16-C17)/C17 -> -0.007747648 | E16: 0.052709472 | F16: 10 | G16: =_xlfn.NORM.INV(RAND(),$M$9,$M$10) -> 0.020856095 | I16: Percentile | J16: Confidence | K16: VAR | L16: Stock Price | M16: VAR(INR)
B17: Jul 22, 2024 | C17: 632.45 | D17: =(C17-C18)/C18 -> 0.0035702951 | E17: 0.051881113 | F17: 11 | G17: =_xlfn.NORM.INV(RAND(),$M$9,$M$10) -> 0.0063954257 | I17: 0.05 | J17: =100%-I17 -> 0.95 | K17: =_xlfn.PERCENTILE.INC($E$7:$E$253,I17) -> -0.039581867 | L17: =$M$13*(1-K17) -> 650.46637 | M17: =$M$13-L17 -> -24.766374
B18: Jul 15, 2024 | C18: 630.2 | D18: =(C18-C19)/C19 -> 0.0046069726 | E18: 0.050965164 | F18: 12 | G18: =_xlfn.NORM.INV(RAND(),$M$9,$M$10) -> -0.063566847 | I18: 0.01 | J18: =100%-I18 -> 0.99 | K18: =_xlfn.PERCENTILE.INC($E$7:$E$253,I18) -> -0.077741786 | L18: =$M$13*(1-K18) -> 674.34304 | M18: =$M$13-L18 -> -48.643035
B19: Jul 8, 2024 | C19: 627.31 | D19: =(C19-C20)/C20 -> 0.038833504 | E19: 0.050528211 | F19: 13 | G19: =_xlfn.NORM.INV(RAND(),$M$9,$M$10) -> -0.01871503 | I19: 0.005 | J19: =100%-I19 -> 0.995 | K19: =_xlfn.PERCENTILE.INC($E$7:$E$253,I19) -> -0.08583834 | L19: =$M$13*(1-K19) -> 679.40905 | M19: =$M$13-L19 -> -53.70905
B20: Jul 1, 2024 | C20: 603.86 | D20: =(C20-C21)/C21 -> 0.0095629786 | E20: 0.048831562 | F20: 14 | G20: =_xlfn.NORM.INV(RAND(),$M$9,$M$10) -> 0.045098195
B21: Jun 24, 2024 | C21: 598.14 | D21: =(C21-C22)/C22 -> 0.01823196 | E21: 0.046053595 | F21: 15 | G21: =_xlfn.NORM.INV(RAND(),$M$9,$M$10) -> 0.044735376
B22: Jun 17, 2024 | C22: 587.43 | D22: =(C22-C23)/C23 -> -0.030723538 | E22: 0.045566999 | F22: 16 | G22: =_xlfn.NORM.INV(RAND(),$M$9,$M$10) -> -0.043662753 | I22: Monte Carlo Simulation
B23: Jun 10, 2024 | C23: 606.05 | D23: =(C23-C24)/C24 -> -0.0072728464 | E23: 0.044689541 | F23: 17 | G23: =_xlfn.NORM.INV(RAND(),$M$9,$M$10) -> 0.018308416 | I23: Mean | M23: =AVERAGE(G7:G5006) -> 0.0014593455
B24: Jun 3, 2024 | C24: 610.49 | D24: =(C24-C25)/C25 -> 0.12474667 | E24: 0.044311588 | F24: 18 | G24: =_xlfn.NORM.INV(RAND(),$M$9,$M$10) -> 0.035139394 | I24: STD | M24: =_xlfn.STDEV.S(G7:G5006) -> 0.030112486
B25: May 27, 2024 | C25: 542.78 | D25: =(C25-C26)/C26 -> -0.023285108 | E25: 0.043582724 | F25: 19 | G25: =_xlfn.NORM.INV(RAND(),$M$9,$M$10) -> -0.049302387 | I25: Min | M25: =MIN(G7:G5006) -> -0.11915096
B26: May 20, 2024 | C26: 555.72 | D26: =(C26-C27)/C27 -> 0.033513111 | E26: 0.043038135 | F26: 20 | G26: =_xlfn.NORM.INV(RAND(),$M$9,$M$10) -> -0.00046528754 | I26: Max | M26: =MAX(G7:G5006) -> 0.11136468
B27: May 13, 2024 | C27: 537.7 | D27: =(C27-C28)/C28 -> -0.019600693 | E27: 0.04234608 | F27: 21 | G27: =_xlfn.NORM.INV(RAND(),$M$9,$M$10) -> -0.00463782 | I27: CMP | M27: =M13 -> 625.7
B28: May 6, 2024 | C28: 548.45 | D28: =(C28-C29)/C29 -> 0.035827604 | E28: 0.041531736 | F28: 22 | G28: =_xlfn.NORM.INV(RAND(),$M$9,$M$10) -> -0.016701791
B29: Apr 29, 2024 | C29: 529.48 | D29: =(C29-C30)/C30 -> 0.044689541 | E29: 0.041019997 | F29: 23 | G29: =_xlfn.NORM.INV(RAND(),$M$9,$M$10) -> 0.016264428
B30: Apr 22, 2024 | C30: 506.83 | D30: =(C30-C31)/C31 -> 0.009520964 | E30: 0.040567757 | F30: 24 | G30: =_xlfn.NORM.INV(RAND(),$M$9,$M$10) -> 0.042101089 | I30: Percentile | J30: Confidence | K30: VAR | L30: Stock Price | M30: VAR(INR)
B31: Apr 15, 2024 | C31: 502.05 | D31: =(C31-C32)/C32 -> 0.0071819768 | E31: 0.040533234 | F31: 25 | G31: =_xlfn.NORM.INV(RAND(),$M$9,$M$10) -> 0.0059630189 | I31: 0.05 | J31: =100%-I31 -> 0.95 | K31: =_xlfn.PERCENTILE.INC($G$7:$G$5006,I31) -> -0.047508454 | L31: =$M$27*(1-K31) -> 655.42604 | M31: =$M$27-L31 -> -29.72604
B32: Apr 8, 2024 | C32: 498.47 | D32: =(C32-C33)/C33 -> -0.014355486 | E32: 0.03978613 | F32: 26 | G32: =_xlfn.NORM.INV(RAND(),$M$9,$M$10) -> 0.015324933 | I32: 0.01 | J32: =100%-I32 -> 0.99 | K32: =_xlfn.PERCENTILE.INC($G$7:$G$5006,I32) -> -0.066237037 | L32: =$M$27*(1-K32) -> 667.14451 | M32: =$M$27-L32 -> -41.444514
B33: Apr 1, 2024 | C33: 505.73 | D33: =(C33-C34)/C34 -> -0.029159948 | E33: 0.039061033 | F33: 27 | G33: =_xlfn.NORM.INV(RAND(),$M$9,$M$10) -> 0.013058017 | I33: 0.005 | J33: =100%-I33 -> 0.995 | K33: =_xlfn.PERCENTILE.INC($G$7:$G$5006,I33) -> -0.073591729 | L33: =$M$27*(1-K33) -> 671.74635 | M33: =$M$27-L33 -> -46.046345
B34: Mar 25, 2024 | C34: 520.92 | D34: =(C34-C35)/C35 -> 0.0045123221 | E34: 0.038873486 | F34: 28 | G34: =_xlfn.NORM.INV(RAND(),$M$9,$M$10) -> 0.0056836079
B35: Mar 18, 2024 | C35: 518.58 | D35: =(C35-C36)/C36 -> -0.010909784 | E35: 0.038833504 | F35: 29 | G35: =_xlfn.NORM.INV(RAND(),$M$9,$M$10) -> 0.027332458
B36: Mar 11, 2024 | C36: 524.3 | D36: =(C36-C37)/C37 -> -0.016267332 | E36: 0.038191237 | F36: 30 | G36: =_xlfn.NORM.INV(RAND(),$M$9,$M$10) -> 0.019625031
B37: Mar 4, 2024 | C37: 532.97 | D37: =(C37-C38)/C38 -> -0.010801982 | E37: 0.038082065 | F37: 31 | G37: =_xlfn.NORM.INV(RAND(),$M$9,$M$10) -> 0.020871604
B38: Feb 26, 2024 | C38: 538.79 | D38: =(C38-C39)/C39 -> 0.01082511 | E38: 0.035827604 | F38: 32 | G38: =_xlfn.NORM.INV(RAND(),$M$9,$M$10) -> -0.037664052
B39: Feb 19, 2024 | C39: 533.02 | D39: =(C39-C40)/C40 -> -0.016894758 | E39: 0.035006909 | F39: 33 | G39: =_xlfn.NORM.INV(RAND(),$M$9,$M$10) -> -0.0090308609
B40: Feb 12, 2024 | C40: 542.18 | D40: =(C40-C41)/C41 -> 0.0098342336 | E40: 0.034022394 | F40: 34 | G40: =_xlfn.NORM.INV(RAND(),$M$9,$M$10) -> 0.042241192
B41: Feb 5, 2024 | C41: 536.9 | D41: =(C41-C42)/C42 -> -0.010012354 | E41: 0.033513111 | F41: 35 | G41: =_xlfn.NORM.INV(RAND(),$M$9,$M$10) -> -0.031817955
B42: Jan 29, 2024 | C42: 542.33 | D42: =(C42-C43)/C43 -> 0.024559349 | E42: 0.0326628 | F42: 36 | G42: =_xlfn.NORM.INV(RAND(),$M$9,$M$10) -> 0.013428278
B43: Jan 22, 2024 | C43: 529.33 | D43: =(C43-C44)/C44 -> -0.019741106 | E43: 0.030790124 | F43: 37 | G43: =_xlfn.NORM.INV(RAND(),$M$9,$M$10) -> -0.0032946056
B44: Jan 15, 2024 | C44: 539.99 | D44: =(C44-C45)/C45 -> -0.01346463 | E44: 0.029001562 | F44: 38 | G44: =_xlfn.NORM.INV(RAND(),$M$9,$M$10) -> 0.047182433
B45: Jan 8, 2024 | C45: 547.36 | D45: =(C45-C46)/C46 -> -0.033991035 | E45: 0.027838581 | F45: 39 | G45: =_xlfn.NORM.INV(RAND(),$M$9,$M$10) -> 0.041420034
... B253: Jan 13, 2020 | C253: 470.81 | D253: =(C253-C254)/C254 -> 0.048831562 | E253: -0.099794303 | F253: 247 | G253: =_xlfn.NORM.INV(RAND(),$M$9,$M$10) -> 0.01962487
B254: Jan 6, 2020 | C254: 448.89 | F254: 248 | G254: =_xlfn.NORM.INV(RAND(),$M$9,$M$10) -> 0.018047385
F255: 249 | G255: =_xlfn.NORM.INV(RAND(),$M$9,$M$10) -> -0.006565821
F256: 250 | G256: =_xlfn.NORM.INV(RAND(),$M$9,$M$10) -> -0.058163948
F257: 251 | G257: =_xlfn.NORM.INV(RAND(),$M$9,$M$10) -> -0.015609681
F258: 252 | G258: =_xlfn.NORM.INV(RAND(),$M$9,$M$10) -> -0.0024233497 | N258: Dec 30, 2019 | O258: 459.5 | P258: 466.8 | Q258: 453.55 | R258: 455.6 | S258: 438.07 | T258: 4892062
F259: 253 | G259: =_xlfn.NORM.INV(RAND(),$M$9,$M$10) -> -0.027335694 | N259: Dec 23, 2019 | O259: 458 | P259: 462.9 | Q259: 454.65 | R259: 459.8 | S259: 442.11 | T259: 3913898
F260: 254 | G260: =_xlfn.NORM.INV(RAND(),$M$9,$M$10) -> -0.053157595 | N260: Dec 16, 2019 | O260: 461 | P260: 466 | Q260: 456 | R260: 459.8 | S260: 442.11 | T260: 6046089
F261: 255 | G261: =_xlfn.NORM.INV(RAND(),$M$9,$M$10) -> 0.041160504 | N261: Dec 9, 2019 | O261: 463.85 | P261: 468.5 | Q261: 448.4 | R261: 460 | S261: 442.3 | T261: 7562964
F262: 256 | G262: =_xlfn.NORM.INV(RAND(),$M$9,$M$10) -> -0.01850814 | N262: Dec 2, 2019 | O262: 458.9 | P262: 471.85 | Q262: 446.15 | R262: 463.8 | S262: 445.96 | T262: 12996355
F263: 257 | G263: =_xlfn.NORM.INV(RAND(),$M$9,$M$10) -> 0.0093084219 | N263: Nov 25, 2019 | O263: 463.7 | P263: 476.95 | Q263: 457.3 | R263: 459.1 | S263: 441.44 | T263: 13773739
F264: 258 | G264: =_xlfn.NORM.INV(RAND(),$M$9,$M$10) -> -0.026623496 | N264: Nov 18, 2019 | O264: 461.7 | P264: 473.9 | Q264: 448.6 | R264: 463.8 | S264: 445.96 | T264: 8806385
F265: 259 | G265: =_xlfn.NORM.INV(RAND(),$M$9,$M$10) -> 0.012478689 | N265: Nov 13, 2019 | O265: 1.40 Dividend
F266: 260 | G266: =_xlfn.NORM.INV(RAND(),$M$9,$M$10) -> -0.032507435 | N266: Nov 11, 2019 | O266: 474.4 | P266: 480.65 | Q266: 455 | R266: 461.7 | S266: 442.64 | T266: 5022111
F267: 261 | G267: =_xlfn.NORM.INV(RAND(),$M$9,$M$10) -> 0.0026713501 | N267: Nov 4, 2019 | O267: 464.2 | P267: 487.7 | Q267: 455.2 | R267: 473.65 | S267: 454.09 | T267: 17439501
F268: 262 | G268: =_xlfn.NORM.INV(RAND(),$M$9,$M$10) -> 0.00065356051 | N268: Oct 28, 2019 | O268: 465.55 | P268: 471.95 | Q268: 456.95 | R268: 463.85 | S268: 444.7 | T268: 6635292
F269: 263 | G269: =_xlfn.NORM.INV(RAND(),$M$9,$M$10) -> -0.020185511 | N269: Oct 21, 2019 | O269: 466.5 | P269: 480 | Q269: 463 | R269: 469.3 | S269: 449.92 | T269: 5645899
F270: 264 | G270: =_xlfn.NORM.INV(RAND(),$M$9,$M$10) -> 0.0013497494 | N270: Oct 14, 2019 | O270: 446.85 | P270: 467.7 | Q270: 444 | R270: 466.5 | S270: 447.24 | T270: 7746197
F271: 265 | G271: =_xlfn.NORM.INV(RAND(),$M$9,$M$10) -> 0.038417691 | N271: Oct 7, 2019 | O271: 425.15 | P271: 447 | Q271: 421.5 | R271: 445.6 | S271: 427.2 | T271: 4451998
F272: 266 | G272: =_xlfn.NORM.INV(RAND(),$M$9,$M$10) -> -0.016471951 | N272: Sep 30, 2019 | O272: 446 | P272: 451.5 | Q272: 424.25 | R272: 425.7 | S272: 408.12 | T272: 6146549
F273: 267 | G273: =_xlfn.NORM.INV(RAND(),$M$9,$M$10) -> -0.027354807 | N273: Sep 23, 2019 | O273: 443 | P273: 453.55 | Q273: 432.7 | R273: 447.1 | S273: 428.64 | T273: 11650982
F274: 268 | G274: =_xlfn.NORM.INV(RAND(),$M$9,$M$10) -> 0.011878642 | N274: Sep 16, 2019 | O274: 449.9 | P274: 469.2 | Q274: 441.1 | R274: 445.7 | S274: 427.3 | T274: 13695302
F275: 269 | G275: =_xlfn.NORM.INV(RAND(),$M$9,$M$10) -> 0.016945917 | N275: Sep 9, 2019 | O275: 441 | P275: 454.65 | Q275: 438 | R275: 452.2 | S275: 433.53 | T275: 8068104
F276: 270 | G276: =_xlfn.NORM.INV(RAND(),$M$9,$M$10) -> -0.010790576 | N276: Sep 2, 2019 | O276: 448.8 | P276: 452.3 | Q276: 433.95 | R276: 441.3 | S276: 423.08 | T276: 5724283
F277: 271 | G277: =_xlfn.NORM.INV(RAND(),$M$9,$M$10) -> 0.027589023 | N277: Aug 26, 2019 | O277: 426 | P277: 450.35 | Q277: 419.25 | R277: 448.8 | S277: 430.27 | T277: 11014843
... F279: 273 | G279: =_xlfn.NORM.INV(RAND(),$M$9,$M$10) -> 0.014659112 | N279: Aug 12, 2019 | O279: 439.05 | P279: 439.05 | Q279: 426 | R279: 428.05 | S279: 410.37 | T279: 3590613
F280: 274 | G280: =_xlfn.NORM.INV(RAND(),$M$9,$M$10) -> -0.0029146076 | N280: Aug 7, 2019 | O280: 1.50 Dividend
F281: 275 | G281: =_xlfn.NORM.INV(RAND(),$M$9,$M$10) -> -0.034814019 | N281: Aug 5, 2019 | O281: 424.3 | P281: 440.85 | Q281: 421 | R281: 439.05 | S281: 419.46 | T281: 8423895
F282: 276 | G282: =_xlfn.NORM.INV(RAND(),$M$9,$M$10) -> 0.025645834 | N282: Jul 29, 2019 | O282: 429 | P282: 433.85 | Q282: 415.7 | R282: 426.5 | S282: 407.47 | T282: 9320076
F283: 277 | G283: =_xlfn.NORM.INV(RAND(),$M$9,$M$10) -> -0.012889254 | N283: Jul 22, 2019 | O283: 423.6 | P283: 429.5 | Q283: 413.55 | R283: 428.15 | S283: 409.05 | T283: 11842614
F284: 278 | G284: =_xlfn.NORM.INV(RAND(),$M$9,$M$10) -> 0.055579431 | N284: Jul 15, 2019 | O284: 407 | P284: 435.4 | Q284: 406.15 | R284: 420.2 | S284: 401.45 | T284: 24593148
F285: 279 | G285: =_xlfn.NORM.INV(RAND(),$M$9,$M$10) -> 0.036155111 | N285: Jul 8, 2019 | O285: 405.2 | P285: 413 | Q285: 397.3 | R285: 407.7 | S285: 389.51 | T285: 8645973
F286: 280 | G286: =_xlfn.NORM.INV(RAND(),$M$9,$M$10) -> 0.026899059 | N286: Jul 1, 2019 | O286: 400.8 | P286: 411.5 | Q286: 397.8 | R286: 407.3 | S286: 389.13 | T286: 9786881
F287: 281 | G287: =_xlfn.NORM.INV(RAND(),$M$9,$M$10) -> 0.0096223554 | N287: Jun 24, 2019 | O287: 392.6 | P287: 403.1 | Q287: 388.05 | R287: 400.5 | S287: 382.63 | T287: 6926145
F288: 282 | G288: =_xlfn.NORM.INV(RAND(),$M$9,$M$10) -> 0.057487024 | N288: Jun 17, 2019 | O288: 398.35 | P288: 404.6 | Q288: 376.85 | R288: 392.6 | S288: 375.09 | T288: 13109293
F289: 283 | G289: =_xlfn.NORM.INV(RAND(),$M$9,$M$10) -> 0.026621924 | N289: Jun 10, 2019 | O289: 408 | P289: 414.35 | Q289: 400 | R289: 400.55 | S289: 382.68 | T289: 7385725
F290: 284 | G290: =_xlfn.NORM.INV(RAND(),$M$9,$M$10) -> 0.035013591 | N290: Jun 3, 2019 | O290: 400 | P290: 410.3 | Q290: 398.05 | R290: 404.15 | S290: 386.12 | T290: 7553850
F291: 285 | G291: =_xlfn.NORM.INV(RAND(),$M$9,$M$10) -> -0.0026742536 | N291: May 27, 2019 | O291: 400.2 | P291: 408.4 | Q291: 391 | R291: 395.95 | S291: 378.29 | T291: 12486209
F292: 286 | G292: =_xlfn.NORM.INV(RAND(),$M$9,$M$10) -> -0.011512659 | N292: May 20, 2019 | O292: 377.6 | P292: 405.95 | Q292: 374.25 | R292: 399.05 | S292: 381.25 | T292: 17200527
... F319: 313 | G319: =_xlfn.NORM.INV(RAND(),$M$9,$M$10) -> -0.033546784 | N319: Nov 12, 2018 | O319: 378 | P319: 397 | Q319: 366.2 | R319: 395.65 | S319: 378 | T319: 17309237
F320: 314 | G320: =_xlfn.NORM.INV(RAND(),$M$9,$M$10) -> -0.040496204 | N320: Nov 9, 2018 | O320: 1.25 Dividend
F321: 315 | G321: =_xlfn.NORM.INV(RAND(),$M$9,$M$10) -> -0.015611344 | N321: Nov 5, 2018 | O321: 369 | P321: 379.9 | Q321: 362.6 | R321: 377.2 | S321: 359.15 | T321: 11924686
F322: 316 | G322: =_xlfn.NORM.INV(RAND(),$M$9,$M$10) -> -0.00082427895 | N322: Oct 29, 2018 | O322: 400.7 | P322: 416.7 | Q322: 365.45 | R322: 369.45 | S322: 351.77 | T322: 31702055
F323: 317 | G323: =_xlfn.NORM.INV(RAND(),$M$9,$M$10) -> 0.02328251 | N323: Oct 22, 2018 | O323: 408 | P323: 414 | Q323: 394 | R323: 398.25 | S323: 379.2 | T323: 10627995
F324: 318 | G324: =_xlfn.NORM.INV(RAND(),$M$9,$M$10) -> -0.041415707 | N324: Oct 15, 2018 | O324: 411 | P324: 423 | Q324: 393.05 | R324: 404.45 | S324: 385.1 | T324: 10921078
F325: 319 | G325: =_xlfn.NORM.INV(RAND(),$M$9,$M$10) -> 0.008764401 | N325: Oct 8, 2018 | O325: 421 | P325: 423.3 | Q325: 383.8 | R325: 407.85 | S325: 388.34 | T325: 19549022
F326: 320 | G326: =_xlfn.NORM.INV(RAND(),$M$9,$M$10) -> 0.020782066 | N326: Oct 1, 2018 | O326: 425 | P326: 442.5 | Q326: 403.95 | R326: 420.05 | S326: 399.95 | T326: 9916615
F327: 321 | G327: =_xlfn.NORM.INV(RAND(),$M$9,$M$10) -> 0.04990115 | N327: Sep 24, 2018 | O327: 452.9 | P327: 457.5 | Q327: 416.55 | R327: 426.9 | S327: 406.48 | T327: 14779792
F328: 322 | G328: =_xlfn.NORM.INV(RAND(),$M$9,$M$10) -> 0.0067878386 | N328: Sep 17, 2018 | O328: 468 | P328: 475.15 | Q328: 430.15 | R328: 455.7 | S328: 433.9 | T328: 12838153
F329: 323 | G329: =_xlfn.NORM.INV(RAND(),$M$9,$M$10) -> -0.021147095 | N329: Sep 10, 2018 | O329: 468.2 | P329: 469.9 | Q329: 439.4 | R329: 468.25 | S329: 445.85 | T329: 15396357
F330: 324 | G330: =_xlfn.NORM.INV(RAND(),$M$9,$M$10) -> 0.0045395873 | N330: Sep 3, 2018 | O330: 481.05 | P330: 481.05 | Q330: 443.7 | R330: 468.3 | S330: 445.89 | T330: 17290239
F331: 325 | G331: =_xlfn.NORM.INV(RAND(),$M$9,$M$10) -> 0.064092246 | N331: Aug 27, 2018 | O331: 475.2 | P331: 490.65 | Q331: 475.05 | R331: 478.75 | S331: 455.84 | T331: 15243843
F332: 326 | G332: =_xlfn.NORM.INV(RAND(),$M$9,$M$10) -> 0.042505336 | N332: Aug 20, 2018 | O332: 456.9 | P332: 489.35 | Q332: 448.3 | R332: 475.1 | S332: 452.37 | T332: 20703616
... F338: 332 | G338: =_xlfn.NORM.INV(RAND(),$M$9,$M$10) -> -0.015875436 | N338: Jul 9, 2018 | O338: 371.2 | P338: 382.75 | Q338: 371.2 | R338: 376.1 | S338: 358.11 | T338: 12034970
F339: 333 | G339: =_xlfn.NORM.INV(RAND(),$M$9,$M$10) -> -0.016782543 | N339: Jul 5, 2018 | O339: 5.00 Dividend
F340: 334 | G340: =_xlfn.NORM.INV(RAND(),$M$9,$M$10) -> -0.013979816 | N340: Jul 2, 2018 | O340: 391.45 | P340: 391.45 | Q340: 369.4 | R340: 370 | S340: 343.14 | T340: 11747511
F341: 335 | G341: =_xlfn.NORM.INV(RAND(),$M$9,$M$10) -> -0.040145915 | N341: Jul 4, 2018 | O341: 5.00 Dividend
F342: 336 | G342: =_xlfn.NORM.INV(RAND(),$M$9,$M$10) -> 0.037294643 | N342: Jun 25, 2018 | O342: 385 | P342: 396.4 | Q342: 382.4 | R342: 391.45 | S342: 363.03 | T342: 7188790
...

Sheet Dupont Analysis
B3: ='Data Sheet'!B1 -> DABUR INDIA LTD
B4: ( DABUR | BSE Code : 500096 )
B5: =" INR "&'Data Sheet'!B8 -> INR 625.7
B6: 52 Weeks (High - 672.00 & Low - 489.20)
B9: About the Company
B10: Dabur Ltd is an Indian multinational consumer goods company, founded by S. K. Burman and headquartered in Ghaziabad. It manufactures Ayurvedic products and fast-moving consumer goods. Dabur derives around 60% of its revenue from the consumer care business, 11% from the food business and remaining from the international business unit.
B14: Financial Summary
B58: Return on Equity (ROE)
D59: ='Historical FS'!F7 -> 43190 | E59: ='Historical FS'!G7 -> 43555 | F59: ='Historical FS'!H7 -> 43921 | G59: ='Historical FS'!I7 -> 44286 | H59: ='Historical FS'!J7 -> 44651 | I59: ='Historical FS'!K7 -> 45016 | J59: ='Historical FS'!L7 -> 45382
B60: Net Profit | D60: ='Historical FS'!F37 -> 1066.86 | E60: ='Historical FS'!G37 -> 1224.46 | F60: ='Historical FS'!H37 -> 1242.63 | G60: ='Historical FS'!I37 -> 1369.66 | H60: ='Historical FS'!J37 -> 1434.14 | I60: ='Historical FS'!K37 -> 1255.94 | J60: ='Historical FS'!L37 -> 1328.9
B61: Average Shareholder's Equity | D61: =(('Historical FS'!F51+'Historical FS'!F52)+('Historical FS'!E51+'Historical FS'!E52))/2 -> 5276.955 | E61: =(('Historical FS'!G51+'Historical FS'!G52)+('Historical FS'!F51+'Historical FS'!F52))/2 -> 5669.1 | F61: =(('Historical FS'!H51+'Historical FS'!H52)+('Historical FS'!G51+'Historical FS'!G52))/2 -> 6118.715 | G61: =(('Historical FS'!I51+'Historical FS'!I52)+('Historical FS'!H51+'Historical FS'!H52))/2 -> 7134.64 | H61: =(('Historical FS'!J51+'Historical FS'!J52)+('Historical FS'!I51+'Historical FS'!I52))/2 -> 8022.415 | I61: =(('Historical FS'!K51+'Historical FS'!K52)+('Historical FS'!J51+'Historical FS'!J52))/2 -> 8677.28 | J61: =(('Historical FS'!L51+'Historical FS'!L52)+('Historical FS'!K51+'Historical FS'!K52))/2 -> 9419.78
B62: Return on Equity | D62: =D60/D61 -> 0.20217341 | E62: =E60/E61 -> 0.21598843 | F62: =F60/F61 -> 0.20308676 | G62: =G60/G61 -> 0.19197325 | H62: =H60/H61 -> 0.17876662 | I62: =I60/I61 -> 0.1447389 | J62: =J60/J61 -> 0.14107548
B64: ROE - Dupont Equation
D65: =D59 -> 43190 | E65: =E59 -> 43555 | F65: =F59 -> 43921 | G65: =G59 -> 44286 | H65: =H59 -> 44651 | I65: =I59 -> 45016 | J65: =J59 -> 45382
B66: Net Profit | D66: =D60 -> 1066.86 | E66: =E60 -> 1224.46 | F66: =F60 -> 1242.63 | G66: =G60 -> 1369.66 | H66: =H60 -> 1434.14 | I66: =I60 -> 1255.94 | J66: =J60 -> 1328.9
B67: Revenue | D67: ='Data Sheet'!E17 -> 7721.85 | E67: ='Data Sheet'!F17 -> 8514.99 | F67: ='Data Sheet'!G17 -> 8684.64 | G67: ='Data Sheet'!H17 -> 9561.65 | H67: ='Data Sheet'!I17 -> 10888.68 | I67: ='Data Sheet'!J17 -> 11529.89 | J67: ='Data Sheet'!K17 -> 12404.01
B68: Net Profit Margin (A) | D68: =D66/D67 -> 0.13816119 | E68: =E66/E67 -> 0.14380052 | F68: =F66/F67 -> 0.14308365 | G68: =G66/G67 -> 0.14324515 | H68: =H66/H67 -> 0.13170926 | I68: =I66/I67 -> 0.10892905 | J68: =J66/J67 -> 0.10713471
B70: Revenue | D70: =D67 -> 7721.85 | E70: =E67 -> 8514.99 | F70: =F67 -> 8684.64 | G70: =G67 -> 9561.65 | H70: =H67 -> 10888.68 | I70: =I67 -> 11529.89 | J70: =J67 -> 12404.01
B71: Average Total Assets | D71: =('Historical FS'!F68+'Historical FS'!E68)/2 -> 8216.935 | E71: =('Historical FS'!G68+'Historical FS'!F68)/2 -> 8569.135 | F71: =('Historical FS'!H68+'Historical FS'!G68)/2 -> 8886.61 | G71: =('Historical FS'!I68+'Historical FS'!H68)/2 -> 10084.9 | H71: =('Historical FS'!J68+'Historical FS'!I68)/2 -> 11558.54 | I71: =('Historical FS'!K68+'Historical FS'!J68)/2 -> 12968.07 | J71: =('Historical FS'!L68+'Historical FS'!K68)/2 -> 14384.32
B72: Asset Turnover Ratio (B) | D72: =D70/D71 -> 0.93974822 | E72: =E70/E71 -> 0.99368139 | F72: =F70/F71 -> 0.97727255 | G72: =G70/G71 -> 0.9481155 | H72: =H70/H71 -> 0.94204631 | I72: =I70/I71 -> 0.88909838 | J72: =J70/J71 -> 0.86232856
B74: =B71 -> Average Total Assets | D74: =D71 -> 8216.935 | E74: =E71 -> 8569.135 | F74: =F71 -> 8886.61 | G74: =G71 -> 10084.9 | H74: =H71 -> 11558.54 | I74: =I71 -> 12968.07 | J74: =J71 -> 14384.32
B75: =B61 -> Average Shareholder's Equity | D75: =D61 -> 5276.955 | E75: =E61 -> 5669.1 | F75: =F61 -> 6118.715 | G75: =G61 -> 7134.64 | H75: =H61 -> 8022.415 | I75: =I61 -> 8677.28 | J75: =J61 -> 9419.78
B76: Equity Multiplier (C) | D76: =D74/D75 -> 1.5571357 | E76: =E74/E75 -> 1.5115512 | F76: =F74/F75 -> 1.4523654 | G76: =G74/G75 -> 1.4135121 | H76: =H74/H75 -> 1.4407806 | I76: =I74/I75 -> 1.4944856 | J76: =J74/J75 -> 1.5270335
B78: Return on Equity (A*B*C) | D78: =D76*D72*D68 -> 0.20217341 | E78: =E76*E72*E68 -> 0.21598843 | F78: =F76*F72*F68 -> 0.20308676 | G78: =G76*G72*G68 -> 0.19197325 | H78: =H76*H72*H68 -> 0.17876662 | I78: =I76*I72*I68 -> 0.1447389 | J78: =J76*J72*J68 -> 0.14107548
B80: Return on Assets (ROA)
D81: =D65 -> 43190 | E81: =E65 -> 43555 | F81: =F65 -> 43921 | G81: =G65 -> 44286 | H81: =H65 -> 44651 | I81: =I65 -> 45016 | J81: =J65 -> 45382
B82: Net Profit | D82: =D66 -> 1066.86 | E82: =E66 -> 1224.46 | F82: =F66 -> 1242.63 | G82: =G66 -> 1369.66 | H82: =H66 -> 1434.14 | I82: =I66 -> 1255.94 | J82: =J66 -> 1328.9
B83: =B74 -> Average Total Assets | D83: =D71 -> 8216.935 | E83: =E71 -> 8569.135 | F83: =F71 -> 8886.61 | G83: =G71 -> 10084.9 | H83: =H71 -> 11558.54 | I83: =I71 -> 12968.07 | J83: =J71 -> 14384.32
B84: Return on Assets | D84: =D82/D83 -> 0.12983673 | E84: =E82/E83 -> 0.1428919 | F84: =F82/F83 -> 0.13983172 | G84: =G82/G83 -> 0.13581295 | H84: =H82/H83 -> 0.12407622 | I84: =I82/I83 -> 0.096848644 | J84: =J82/J83 -> 0.09238532
B86: ROA - Dupont Equation
D87: =D81 -> 43190 | E87: =E81 -> 43555 | F87: =F81 -> 43921 | G87: =G81 -> 44286 | H87: =H81 -> 44651 | I87: =I81 -> 45016 | J87: =J81 -> 45382
B88: Net Profit | D88: =D82 -> 1066.86 | E88: =E82 -> 1224.46 | F88: =F82 -> 1242.63 | G88: =G82 -> 1369.66 | H88: =H82 -> 1434.14 | I88: =I82 -> 1255.94 | J88: =J82 -> 1328.9
B89: =B70 -> Revenue | D89: =D70 -> 7721.85 | E89: =E70 -> 8514.99 | F89: =F70 -> 8684.64 | G89: =G70 -> 9561.65 | H89: =H70 -> 10888.68 | I89: =I70 -> 11529.89 | J89: =J70 -> 12404.01
B90: Net Profit Margin (A) | D90: =D88/D89 -> 0.13816119 | E90: =E88/E89 -> 0.14380052 | F90: =F88/F89 -> 0.14308365 | G90: =G88/G89 -> 0.14324515 | H90: =H88/H89 -> 0.13170926 | I90: =I88/I89 -> 0.10892905 | J90: =J88/J89 -> 0.10713471
B92: =B89 -> Revenue | D92: =D89 -> 7721.85 | E92: =E89 -> 8514.99 | F92: =F89 -> 8684.64 | G92: =G89 -> 9561.65 | H92: =H89 -> 10888.68 | I92: =I89 -> 11529.89 | J92: =J89 -> 12404.01
B93: =B74 -> Average Total Assets | D93: =D74 -> 8216.935 | E93: =E74 -> 8569.135 | F93: =F74 -> 8886.61 | G93: =G74 -> 10084.9 | H93: =H74 -> 11558.54 | I93: =I74 -> 12968.07 | J93: =J74 -> 14384.32
B94: Asset Turnover Ratio (B) | D94: =D92/D93 -> 0.93974822 | E94: =E92/E93 -> 0.99368139 | F94: =F92/F93 -> 0.97727255 | G94: =G92/G93 -> 0.9481155 | H94: =H92/H93 -> 0.94204631 | I94: =I92/I93 -> 0.88909838 | J94: =J92/J93 -> 0.86232856
B96: Return on Assets (A*B) | D96: =D90*D94 -> 0.12983673 | E96: =E90*E94 -> 0.1428919 | F96: =F90*F94 -> 0.13983172 | G96: =G90*G94 -> 0.13581295 | H96: =H90*H94 -> 0.12407622 | I96: =I90*I94 -> 0.096848644 | J96: =J90*J94 -> 0.09238532

Sheet Altman's Z-Score
B2: DABUR INDIA LTD
B4: BSE : 500096 | NSE : DABUR
B6: Altman's Z Score Analysis
B34: Altman's Z Score Analysis Calculation
B36: Working Capital / Total Assets
E37: ='Dupont Analysis'!D81 -> 43190 | F37: ='Dupont Analysis'!E81 -> 43555 | G37: ='Dupont Analysis'!F81 -> 43921 | H37: ='Dupont Analysis'!G81 -> 44286 | I37: ='Dupont Analysis'!H81 -> 44651 | J37: ='Dupont Analysis'!I81 -> 45016 | K37: ='Dupont Analysis'!J81 -> 45382
B38: Working Capital | E38: ='Data Sheet'!E65-'Data Sheet'!E60 -> 769.32 | F38: ='Data Sheet'!F65-'Data Sheet'!F60 -> 939.47 | G38: ='Data Sheet'!G65-'Data Sheet'!G60 -> 1928.23 | H38: ='Data Sheet'!H65-'Data Sheet'!H60 -> 1622.74 | I38: ='Data Sheet'!I65-'Data Sheet'!I60 -> 716.38 | J38: ='Data Sheet'!J65-'Data Sheet'!J60 -> 128.01 | K38: ='Data Sheet'!K65-'Data Sheet'!K60 -> 251.47
B39: Total Assets | E39: ='Data Sheet'!E66 -> 8701.63 | F39: ='Data Sheet'!F66 -> 8436.64 | G39: ='Data Sheet'!G66 -> 9336.58 | H39: ='Data Sheet'!H66 -> 10833.22 | I39: ='Data Sheet'!I66 -> 12283.86 | J39: ='Data Sheet'!J66 -> 13652.28 | K39: ='Data Sheet'!K66 -> 15116.36
B40: Working Capital / Total Assets (A) | E40: =E38/E39 -> 0.088411022 | F40: =F38/F39 -> 0.11135594 | G40: =G38/G39 -> 0.20652423 | H40: =H38/H39 -> 0.14979295 | I40: =I38/I39 -> 0.058318802 | J40: =J38/J39 -> 0.0093764558 | K40: =K38/K39 -> 0.016635619
B42: Retained Earnings / Total Assets
E43: =E37 -> 43190 | F43: =F37 -> 43555 | G43: =G37 -> 43921 | H43: =H37 -> 44286 | I43: =I37 -> 44651 | J43: =J37 -> 45016 | K43: =K37 -> 45382
B44: Retained Earnings | E44: ='Historical FS'!F48*'Historical FS'!F37 -> 0 | F44: ='Historical FS'!G48*'Historical FS'!G37 -> 738.73 | G44: ='Historical FS'!H48*'Historical FS'!H37 -> 712.5 | H44: ='Historical FS'!I48*'Historical FS'!I37 -> 530.14 | I44: ='Historical FS'!J48*'Historical FS'!J37 -> 514.83 | J44: ='Historical FS'!K48*'Historical FS'!K37 -> 334.6 | K44: ='Historical FS'!L48*'Historical FS'!L37 -> 354.3
B45: Total Assets | E45: =E39 -> 8701.63 | F45: =F39 -> 8436.64 | G45: =G39 -> 9336.58 | H45: =H39 -> 10833.22 | I45: =I39 -> 12283.86 | J45: =J39 -> 13652.28 | K45: =K39 -> 15116.36
B46: Retained Earnings / Total Assets (B) | E46: =E44/E45 -> 0 | F46: =F44/F45 -> 0.08756211 | G46: =G44/G45 -> 0.07631274 | H46: =H44/H45 -> 0.048936512 | I46: =I44/I45 -> 0.041911093 | J46: =J44/J45 -> 0.024508727 | K46: =K44/K45 -> 0.023438182
B48: EBIT / Total Assets
E49: =E43 -> 43190 | F49: =F43 -> 43555 | G49: =G43 -> 43921 | H49: =H43 -> 44286 | I49: =I43 -> 44651 | J49: =J43 -> 45016 | K49: =K43 -> 45382
B50: EBIT | E50: ='Historical FS'!F31+'Historical FS'!F25 -> 1455.26 | F50: ='Historical FS'!G31+'Historical FS'!G25 -> 1562.66 | G50: ='Historical FS'!H31+'Historical FS'!H25 -> 1571.89 | H50: ='Historical FS'!I31+'Historical FS'!I25 -> 1761.54 | I50: ='Historical FS'!J31+'Historical FS'!J25 -> 1999.12 | J50: ='Historical FS'!K31+'Historical FS'!K25 -> 1851.53 | K50: ='Historical FS'!L31+'Historical FS'!L25 -> 2000.51
B51: Total Assets | E51: =E45 -> 8701.63 | F51: =F45 -> 8436.64 | G51: =G45 -> 9336.58 | H51: =H45 -> 10833.22 | I51: =I45 -> 12283.86 | J51: =J45 -> 13652.28 | K51: =K45 -> 15116.36
B52: EBIT / Total Assets (C) | E52: =E50/E51 -> 0.16723993 | F52: =F50/F51 -> 0.18522303 | G52: =G50/G51 -> 0.16835822 | H52: =H50/H51 -> 0.16260539 | I52: =I50/I51 -> 0.16274363 | J52: =J50/J51 -> 0.13562057 | K52: =K50/K51 -> 0.13234072
B54: Market Capitalization / Long-Term Liabilities
E55: =E43 -> 43190 | F55: =F43 -> 43555 | G55: =G43 -> 43921 | H55: =H43 -> 44286 | I55: =I43 -> 44651 | J55: =J43 -> 45016 | K55: =K43 -> 45382
B56: Market Cap. | E56: ='Data Sheet'!E93*'Data Sheet'!E90 -> 57847.66 | F56: ='Data Sheet'!F93*'Data Sheet'!F90 -> 72206.344 | G56: ='Data Sheet'!G93*'Data Sheet'!G90 -> 79528.336 | H56: ='Data Sheet'!H93*'Data Sheet'!H90 -> 95527.97 | I56: ='Data Sheet'!I93*'Data Sheet'!I90 -> 94794.798 | J56: ='Data Sheet'!J93*'Data Sheet'!J90 -> 96545.382 | K56: ='Data Sheet'!K93*'Data Sheet'!K90 -> 92702.18
B57: Long Term Liabilities | E57: ='Data Sheet'!E60 -> 2057.52 | F57: ='Data Sheet'!F60 -> 2105.59 | G57: ='Data Sheet'!G60 -> 2208.84 | H57: ='Data Sheet'!H60 -> 2660.63 | I57: ='Data Sheet'!I60 -> 2872.46 | J57: ='Data Sheet'!J60 -> 3505.23 | K57: ='Data Sheet'!K60 -> 3884.97
B58: Market Cap /Long-Term Liabilities (D) | E58: =E56/E57 -> 28.115236 | F58: =F56/F57 -> 34.292689 | G58: =G56/G57 -> 36.00457 | H58: =H56/H57 -> 35.904267 | I58: =I56/I57 -> 33.00126 | J58: =J56/J57 -> 27.543237 | K58: =K56/K57 -> 23.861749
B60: Sales / Total Assets
E61: =E55 -> 43190 | F61: =F55 -> 43555 | G61: =G55 -> 43921 | H61: =H55 -> 44286 | I61: =I55 -> 44651 | J61: =J55 -> 45016 | K61: =K55 -> 45382
B62: Sales | E62: ='Dupont Analysis'!D89 -> 7721.85 | F62: ='Dupont Analysis'!E89 -> 8514.99 | G62: ='Dupont Analysis'!F89 -> 8684.64 | H62: ='Dupont Analysis'!G89 -> 9561.65 | I62: ='Dupont Analysis'!H89 -> 10888.68 | J62: ='Dupont Analysis'!I89 -> 11529.89 | K62: ='Dupont Analysis'!J89 -> 12404.01
B63: Total Assets | E63: ='Data Sheet'!E66 -> 8701.63 | F63: ='Data Sheet'!F66 -> 8436.64 | G63: ='Data Sheet'!G66 -> 9336.58 | H63: ='Data Sheet'!H66 -> 10833.22 | I63: ='Data Sheet'!I66 -> 12283.86 | J63: ='Data Sheet'!J66 -> 13652.28 | K63: ='Data Sheet'!K66 -> 15116.36
B64: Sales / Total Assets (E) | E64: =E62/E63 -> 0.88740271 | F64: =F62/F63 -> 1.0092869 | G64: =G62/G63 -> 0.93017358 | H64: =H62/H63 -> 0.88262308 | I64: =I62/I63 -> 0.88642169 | J64: =J62/J63 -> 0.84453952 | K64: =K62/K63 -> 0.82056858
B66: Altman's Z Score
E67: =E61 -> 43190 | F67: =F61 -> 43555 | G67: =G61 -> 43921 | H67: =H61 -> 44286 | I67: =I61 -> 44651 | J67: =J61 -> 45016 | K67: =K61 -> 45382
B68: =B66 -> Altman's Z Score | E68: =(E40*1.2)+(E46*1.4)+(E52*3.3)+(E58*0.6)+(E64*1) -> 18.414529 | F68: =(F40*1.2)+(F46*1.4)+(F52*3.3)+(F58*0.6)+(F64*1) -> 22.452351 | G68: =(G40*1.2)+(G46*1.4)+(G52*3.3)+(G58*0.6)+(G64*1) -> 23.443165 | H68: =(H40*1.2)+(H46*1.4)+(H52*3.3)+(H58*0.6)+(H64*1) -> 23.210044 | I68: =(I40*1.2)+(I46*1.4)+(I52*3.3)+(I58*0.6)+(I64*1) -> 21.35289 | J68: =(J40*1.2)+(J46*1.4)+(J52*3.3)+(J58*0.6)+(J64*1) -> 17.863594 | K68: =(K40*1.2)+(K46*1.4)+(K52*3.3)+(K58*0.6)+(K64*1) -> 15.627119
B69: Financial Stability | E69: =IF(E68<3,"Distressed",IF(E68>3,"Strong","Grey Zone")) -> Strong | F69: =IF(F68<3,"Distressed",IF(F68>3,"Strong","Grey Zone")) -> Strong | G69: =IF(G68<3,"Distressed",IF(G68>3,"Strong","Grey Zone")) -> Strong | H69: =IF(H68<3,"Distressed",IF(H68>3,"Strong","Grey Zone")) -> Strong | I69: =IF(I68<3,"Distressed",IF(I68>3,"Strong","Grey Zone")) -> Strong | J69: =IF(J68<3,"Distressed",IF(J68>3,"Strong","Grey Zone")) -> Strong | K69: =IF(K68<3,"Distressed",IF(K68>3,"Strong","Grey Zone")) -> Strong

Sheet one page report
B2: DABUR INDIA LTD. - One Page Profile
E3: Dabur Ltd is an Indian multinational consumer goods company, founded by S. K. Burman and headquartered in Ghaziabad. It manufactures Ayurvedic products and fast-moving consumer goods. Dabur derives around 60% of its revenue from the consumer care business, 11% from the food business and remaining from the international business unit.
B9: Key Financial Metrics | E9: =E22 -> 43921 | F9: =F22 -> 44286 | G9: =G22 -> 44651 | H9: =H22 -> 45016 | I9: =I22 -> 45382 | K9: Share Price - 5Y
B11: Total Sales | E11: ='Data Sheet'!G17 -> 8684.64 | F11: ='Data Sheet'!H17 -> 9561.65 | G11: ='Data Sheet'!I17 -> 10888.68 | H11: ='Data Sheet'!J17 -> 11529.89 | I11: ='Data Sheet'!K17 -> 12404.01
B12: Sales Growth (y-o-y) (%) | E12: ='Historical FS'!H11 -> 0.019923688 | F12: ='Historical FS'!I11 -> 0.10098404 | G12: ='Historical FS'!J11 -> 0.13878672 | H12: ='Historical FS'!K11 -> 0.058887762 | I12: ='Historical FS'!L11 -> 0.075813386
B13: Gross Profit Margins (%) | E13: ='Historical FS'!H17 -> 0.36465875 | F13: ='Historical FS'!I17 -> 0.3679595 | G13: ='Historical FS'!J17 -> 0.35761451 | H13: ='Historical FS'!K17 -> 0.32868657 | I13: ='Historical FS'!L17 -> 0.3538517
B14: EBITDA Margins (%) | E14: ='Historical FS'!H23 -> 0.20638046 | F14: ='Historical FS'!I23 -> 0.20934358 | G14: ='Historical FS'!J23 -> 0.20682121 | H14: ='Historical FS'!K23 -> 0.18755513 | I14: ='Historical FS'!L23 -> 0.19346324 | O14: `
B15: EBIT Margins (%) | E15: =('Historical FS'!H31+'Historical FS'!H25)/'Historical FS'!H10 -> 0.18099656 | F15: =('Historical FS'!I31+'Historical FS'!I25)/'Historical FS'!I10 -> 0.18422971 | G15: =('Historical FS'!J31+'Historical FS'!J25)/'Historical FS'!J10 -> 0.18359618 | H15: =('Historical FS'!K31+'Historical FS'!K25)/'Historical FS'!K10 -> 0.16058523 | I15: =('Historical FS'!L31+'Historical FS'!L25)/'Historical FS'!L10 -> 0.1612793
B16: Net Profit Margins (%) | E16: ='Historical FS'!H38 -> 0.14308365 | F16: ='Historical FS'!I38 -> 0.14324515 | G16: ='Historical FS'!J38 -> 0.13170926 | H16: ='Historical FS'!K38 -> 0.10892905 | I16: ='Historical FS'!L38 -> 0.10713471
B17: Earnings per Share (in Rs.) | E17: ='Historical FS'!H42 -> 7.0320299 | F17: ='Historical FS'!I42 -> 7.7495756 | G17: ='Historical FS'!J42 -> 8.1121104 | H17: ='Historical FS'!K42 -> 7.0884976 | I17: ='Historical FS'!L42 -> 7.4994357
B18: EPS Growth (y-o-y) (%) | E18: ='Historical FS'!H43 -> 0.014379757 | F18: ='Historical FS'!I43 -> 0.10203964 | G18: ='Historical FS'!J43 -> 0.046781241 | H18: ='Historical FS'!K43 -> -0.1261833 | I18: ='Historical FS'!L43 -> 0.057972524
B19: Dividend per Share (in Rs.) | E19: ='Historical FS'!H45 -> 3 | F19: ='Historical FS'!I45 -> 4.7500283 | G19: ='Historical FS'!J45 -> 5.2000113 | H19: ='Historical FS'!K45 -> 5.2000226 | I19: ='Historical FS'!L45 -> 5.5
B20: Dividend Growth (y-o-y) (%) | E20: =E19/'Historical FS'!G45-1 -> 0.090914706 | F20: =F19/E19-1 -> 0.58334276 | G20: =G19/F19-1 -> 0.094732704 | H20: =H19/G19-1 -> 2.1659673e-06 | I20: =I19/H19-1 -> 0.057687716
B22: Key Financial Ratios | E22: ='Altman''s Z-Score'!G67 -> 43921 | F22: ='Altman''s Z-Score'!H67 -> 44286 | G22: ='Altman''s Z-Score'!I67 -> 44651 | H22: ='Altman''s Z-Score'!J67 -> 45016 | I22: ='Altman''s Z-Score'!K67 -> 45382 | K22: Volumes - 5Y
B24: Price to Earning | E24: ='Data Sheet'!G90/'Historical FS'!H42 -> 64.000012 | F24: ='Data Sheet'!H90/'Historical FS'!I42 -> 69.745754 | G24: ='Data Sheet'!I90/'Historical FS'!J42 -> 66.098706 | H24: ='Data Sheet'!J90/'Historical FS'!K42 -> 76.871015 | I24: ='Data Sheet'!K90/'Historical FS'!L42 -> 69.758582
B25: EV/EBITDA | E25: ='Data Sheet'!G97/'Historical FS'!H22 -> 44.371233 | F25: ='Data Sheet'!H97/'Historical FS'!I22 -> 47.724135 | G25: ='Data Sheet'!I97/'Historical FS'!J22 -> 42.093418 | H25: ='Data Sheet'!J97/'Historical FS'!K22 -> 44.64547 | I25: ='Data Sheet'!K97/'Historical FS'!L22 -> 38.630415
B26: EV/Total Sales | E26: ='Data Sheet'!G97/'Data Sheet'!G17 -> 9.1573555 | F26: ='Data Sheet'!H97/'Data Sheet'!H17 -> 9.9907411 | G26: ='Data Sheet'!I97/'Data Sheet'!I17 -> 8.7058117 | H26: ='Data Sheet'!J97/'Data Sheet'!J17 -> 8.3734868 | I26: ='Data Sheet'!K97/'Data Sheet'!K17 -> 7.4735654
B27: Price to Book Value | E27: ='Data Sheet'!G97/'Data Sheet'!G77 -> 12.039259 | F27: ='Data Sheet'!H97/'Data Sheet'!H77 -> 12.46527 | G27: ='Data Sheet'!I97/'Data Sheet'!I77 -> 11.310274 | H27: ='Data Sheet'!J97/'Data Sheet'!J77 -> 10.759232 | I27: ='Data Sheet'!K97/'Data Sheet'!K77 -> 9.3958404
B28: Return on Equity | E28: =Ratios!H27 -> 0.18811339 | F28: =Ratios!I27 -> 0.17872443 | G28: =Ratios!J27 -> 0.17111188 | H28: =Ratios!K27 -> 0.13996474 | I28: =Ratios!L27 -> 0.13469082
B29: Return on Capital Employed | E29: =Ratios!H25 -> 0.22053133 | F29: =Ratios!I25 -> 0.21554244 | G29: =Ratios!J25 -> 0.21241473 | H29: =Ratios!K25 -> 0.18246978 | I29: =Ratios!L25 -> 0.17811776
B31: Top 10 Shareholders | E31: No. of Shares (in Crs.) | G31: % Holding | H31: Market Value (in Crs.) | K31: Shareholding Pattern
B33: =Rough!U38 -> VIC ENTERPRISES PRIVATE LIMITED | E33: =Rough!V38 -> 21.7794 | G33: =Rough!W38 -> 12.29 | H33: =Rough!X38 -> 13627.371
B34: =Rough!U39 -> CHOWDRY ASSOCIATES | E34: =Rough!V39 -> 20.90838 | G34: =Rough!W39 -> 11.8 | H34: =Rough!X39 -> 13082.373
B35: =Rough!U40 -> GYAN ENTERPRISES PRIVATE LIMITED | E35: =Rough!V40 -> 19.337998 | G35: =Rough!W40 -> 10.91 | H35: =Rough!X40 -> 12099.785
B36: =Rough!U41 -> PURAN ASSOCIATES PRIVATE LIMITED | E36: =Rough!V41 -> 18.9212 | G36: =Rough!W41 -> 10.68 | H36: =Rough!X41 -> 11838.995
B37: =Rough!U42 -> RATNA COMMERCIAL ENTERPRISES PRIVATE LIMITED | E37: =Rough!V42 -> 15.86556 | G37: =Rough!W42 -> 8.95 | H37: =Rough!X42 -> 9927.0811
B38: =Rough!U43 -> MILKY INVESTMENT AND TRADING COMPANY | E38: =Rough!V43 -> 10.61475 | G38: =Rough!W43 -> 5.99 | H38: =Rough!X43 -> 6641.6493
B39: =Rough!U44 -> LIFE INSURANCE CORPORATION OF INDIA | E39: =Rough!V44 -> 6.5828461 | G39: =Rough!W44 -> 3.71 | H39: =Rough!X44 -> 4118.8868
B40: =Rough!U45 -> BURMANS FINVEST PRIVATE LIMITED | E40: =Rough!V45 -> 5.3012986 | G40: =Rough!W45 -> 2.99 | H40: =Rough!X45 -> 3317.0225
B41: =Rough!U46 -> M.B. FINMART PRIVATE LIMITED | E41: =Rough!V46 -> 2.6506492 | G41: =Rough!W46 -> 1.5 | H41: =Rough!X46 -> 1658.5112
B42: =Rough!U47 -> ICICI PRUDENTIAL REGULAR SAVINGS FUND | E42: =Rough!V47 -> 1.9236104 | G42: =Rough!W47 -> 1.09 | H42: =Rough!X47 -> 1203.603
B44: Managerial Remuneration | E44: Designation | F44: Remuneration (in Crs.) | H44: Times of median salary | K44: Capital Structure
B46: Mr. Ajit Mohan Sharan | E46: Chairman | F46: 0.216 | H46: 2 | K46: Share Price as 30-9-24 | N46: 625
B47: Mr. P.D. Narang | E47: Executive Director | F47: 16.250484 | H47: 256 | K47: No. of Shares O/S | N47: ='Data Sheet'!B6 -> 177.23104
B48: Mr. Mohit Malhotra | E48: Executive Director | F48: 14.63843 | H48: 228 | K48: Market Capitalization | N48: =N46*N47 -> 110769.4
B49: Dr. Ajay Dua | E49: Chairman | F49: 0.14 | H49: 1 | K49: Less : Cash and Equivalents | N49: =-'Data Sheet'!K69 -> -666.36
B50: Recent Updates | K50: Add : Total Debt | N50: ='Data Sheet'!K59 -> 1365.09
B51: The percentage increase in the median remuneration of employees in the financial year was 8%. | K51: Add : Minority Interest | N51: ='Raw FS'!L11 -> 437
B52: The number of permanent employees on the rolls of the company was 5,369. | K52: Enterprise Value | N52: =SUM(N48:N51) -> 111905.13
B54: Recent Updates
B56: Dabur India shares slipped into the red in the morning session after Swiss brokerage UBS downgraded the FMCG major to 'hold' from 'buy' earlier.
B57: Dabur India Shares Fall 4.48%, Dividend Announcement Likely On Oct 30; LIC Stake Rises
B58: Dabur India on Thursday reported 16% growth in its consolidated net profit at Rs 350 crore for the quarter ended March 2024. It was Rs 301 crore
B59: a year ago.
B60: Revenue from operations increased 5% year-on-year (YoY) to Rs 2,815 crore for the reporting period.
B61: EBITDA for the quarter increased 14% year-on-year to Rs 467 crore against Rs 410 crore in the same quarter last year. Meanwhile, consolidated
B62: margins improved to 16.6%.
B63: Riding on strong demand for the highly differentiated product portfolio, Dabur oral care penetration now stands at 52%. The quarter saw the oral
B64: care business swell by 22% with the toothpaste business reporting a 23% jump.
B65: In the reporting period, the Egypt business rose 63%. while the Turkey business was up 39% and the Middle East & North Africa (MENA) markets
B66: posted a growth of 6.3%. The Sub-Saharan Africa business rose 23.8%.
B68: Sources : The Valuation School, Screener.in, Dabur India's Website, Yahoo Finance, Equity Masters and economictimes.indiatimes.com

Sheet Rough
B5: Date | C5: Adj Close | D5: Volume | O5: Sep 30, 2024 | P5: 625.2 | Q5: 2475325
B6: Sep 30, 2024 | C6: 625.2 | D6: 2475325 | O6: Sep 23, 2024 | P6: 633 | Q6: 17868760
B7: Sep 23, 2024 | C7: 633 | D7: 17868760 | O7: Sep 16, 2024 | P7: 667.55 | Q7: 7632637
B8: Sep 16, 2024 | C8: 667.55 | D8: 7632637 | O8: Sep 9, 2024 | P8: 660.9 | Q8: 18256985
B9: Sep 9, 2024 | C9: 660.9 | D9: 18256985 | O9: Sep 2, 2024 | P9: 644.4 | Q9: 9667567
B10: Sep 2, 2024 | C10: 644.4 | D10: 9667567 | O10: Aug 26, 2024 | P10: 637.15 | Q10: 9894879
B11: Aug 26, 2024 | C11: 637.15 | D11: 9894879 | O11: Aug 19, 2024 | P11: 643.25 | Q11: 12691816
B12: Aug 19, 2024 | C12: 643.25 | D12: 12691816 | O12: Aug 12, 2024 | P12: 617.6 | Q12: 7102525
B13: Aug 12, 2024 | C13: 617.6 | D13: 7102525 | O13: Aug 5, 2024 | P13: 623.95 | Q13: 12623277
B14: Aug 5, 2024 | C14: 623.95 | D14: 12623277 | O14: Jul 29, 2024 | P14: 627.55 | Q14: 19007259
B15: Jul 29, 2024 | C15: 627.55 | D15: 19007259 | O15: Jul 22, 2024 | P15: 632.45 | Q15: 20203634
B16: Jul 22, 2024 | C16: 632.45 | D16: 20203634 | O16: Jul 15, 2024 | P16: 630.2 | Q16: 9390369
B17: Jul 15, 2024 | C17: 630.2 | D17: 9390369 | O17: Jul 8, 2024 | P17: 627.31 | Q17: 16046668
... B35: Mar 11, 2024 | C35: 524.3 | D35: 8421159 | O35: Mar 4, 2024 | P35: 532.97 | Q35: 5472280
B36: Mar 4, 2024 | C36: 532.97 | D36: 5472280 | O36: Feb 26, 2024 | P36: 538.79 | Q36: 10048023 | W36: 10000000
B37: Feb 26, 2024 | C37: 538.79 | D37: 10048023 | O37: Feb 19, 2024 | P37: 533.02 | Q37: 6472648 | X37: Market Value
B38: Feb 19, 2024 | C38: 533.02 | D38: 6472648 | O38: Feb 12, 2024 | P38: 542.18 | Q38: 4854761 | U38: VIC ENTERPRISES PRIVATE LIMITED | V38: 21.7794 | W38: 12.29 | X38: =V38*'Data Sheet'!$B$8 -> 13627.371
B39: Feb 12, 2024 | C39: 542.18 | D39: 4854761 | O39: Feb 5, 2024 | P39: 536.9 | Q39: 7724595 | U39: CHOWDRY ASSOCIATES | V39: 20.90838 | W39: 11.8 | X39: =V39*'Data Sheet'!$B$8 -> 13082.373 | Z39: s
B40: Feb 5, 2024 | C40: 536.9 | D40: 7724595 | O40: Jan 29, 2024 | P40: 542.33 | Q40: 20831947 | U40: GYAN ENTERPRISES PRIVATE LIMITED | V40: 19.337998 | W40: 10.91 | X40: =V40*'Data Sheet'!$B$8 -> 12099.785
B41: Jan 29, 2024 | C41: 542.33 | D41: 20831947 | O41: Jan 22, 2024 | P41: 529.33 | Q41: 4095201 | U41: PURAN ASSOCIATES PRIVATE LIMITED | V41: 18.9212 | W41: 10.68 | X41: =V41*'Data Sheet'!$B$8 -> 11838.995
B42: Jan 22, 2024 | C42: 529.33 | D42: 4095201 | O42: Jan 15, 2024 | P42: 539.99 | Q42: 9113123 | U42: RATNA COMMERCIAL ENTERPRISES PRIVATE LIMITED | V42: 15.86556 | W42: 8.95 | X42: =V42*'Data Sheet'!$B$8 -> 9927.0811
B43: Jan 15, 2024 | C43: 539.99 | D43: 9113123 | O43: Jan 8, 2024 | P43: 547.36 | Q43: 9137067 | U43: MILKY INVESTMENT AND TRADING COMPANY | V43: 10.61475 | W43: 5.99 | X43: =V43*'Data Sheet'!$B$8 -> 6641.6493
B44: Jan 8, 2024 | C44: 547.36 | D44: 9137067 | O44: Jan 1, 2024 | P44: 566.62 | Q44: 11252183 | U44: LIFE INSURANCE CORPORATION OF INDIA | V44: 6.5828461 | W44: 3.71 | X44: =V44*'Data Sheet'!$B$8 -> 4118.8868
B45: Jan 1, 2024 | C45: 566.62 | D45: 11252183 | O45: Dec 25, 2023 | P45: 554.82 | Q45: 12597273 | U45: BURMANS FINVEST PRIVATE LIMITED | V45: 5.3012986 | W45: 2.99 | X45: =V45*'Data Sheet'!$B$8 -> 3317.0225
B46: Dec 25, 2023 | C46: 554.82 | D46: 12597273 | O46: Dec 18, 2023 | P46: 527.04 | Q46: 18562244 | U46: M.B. FINMART PRIVATE LIMITED | V46: 2.6506492 | W46: 1.5 | X46: =V46*'Data Sheet'!$B$8 -> 1658.5112
B47: Dec 18, 2023 | C47: 527.04 | D47: 18562244 | O47: Dec 11, 2023 | P47: 537.4 | Q47: 9059804 | U47: ICICI PRUDENTIAL REGULAR SAVINGS FUND | V47: 1.9236104 | W47: 1.09 | X47: =V47*'Data Sheet'!$B$8 -> 1203.603
B48: Dec 11, 2023 | C48: 537.4 | D48: 9059804 | O48: Dec 4, 2023 | P48: 545.17 | Q48: 8507384
B49: Dec 4, 2023 | C49: 545.17 | D49: 8507384 | O49: Nov 27, 2023 | P49: 538.84 | Q49: 8819300
B50: Nov 27, 2023 | C50: 538.84 | D50: 8819300 | O50: Nov 20, 2023 | P50: 535.06 | Q50: 5212091
B51: Nov 20, 2023 | C51: 535.06 | D51: 5212091 | O51: Nov 13, 2023 | P51: 538.39 | Q51: 7503185 | U51: Promoters | V51: 0.6625
B52: Nov 13, 2023 | C52: 538.39 | D52: 7503185 | O52: Nov 6, 2023 | P52: 528.34 | Q52: 4807078 | U52: FII | V52: 0.1499
B53: Nov 6, 2023 | C53: 528.34 | D53: 4807078 | O53: Oct 30, 2023 | P53: 530.47 | Q53: 9367669 | U53: DII | V53: 0.1345
B54: Oct 30, 2023 | C54: 530.47 | D54: 9367669 | O54: Oct 23, 2023 | P54: 519.63 | Q54: 8077126 | U54: Public & Government | V54: =W55+W54 -> 0.0533 | W54: 0.0007
B55: Oct 23, 2023 | C55: 519.63 | D55: 8077126 | O55: Oct 16, 2023 | P55: 519.88 | Q55: 16792857 | W55: 0.0526
B56: Oct 16, 2023 | C56: 519.88 | D56: 16792857 | O56: Oct 9, 2023 | P56: 533.79 | Q56: 5442815
B57: Oct 9, 2023 | C57: 533.79 | D57: 5442815 | O57: Oct 2, 2023 | P57: 542.02 | Q57: 5592439
B58: Oct 2, 2023 | C58: 542.02 | D58: 5592439 | O58: Sep 25, 2023 | P58: 546.42 | Q58: 7112583
B59: Sep 25, 2023 | C59: 546.42 | D59: 7112583 | O59: Sep 18, 2023 | P59: 556.03 | Q59: 7063951
B60: Sep 18, 2023 | C60: 556.03 | D60: 7063951 | O60: Sep 11, 2023 | P60: 560.19 | Q60: 6446255
B61: Sep 11, 2023 | C61: 560.19 | D61: 6446255 | O61: Sep 4, 2023 | P61: 561.78 | Q61: 4620822
B62: Sep 4, 2023 | C62: 561.78 | D62: 4620822 | O62: Aug 28, 2023 | P62: 548.16 | Q62: 10630873
B63: Aug 28, 2023 | C63: 548.16 | D63: 10630873 | O63: Aug 21, 2023 | P63: 552.81 | Q63: 7646727
B64: Aug 21, 2023 | C64: 552.81 | D64: 7646727 | O64: Aug 14, 2023 | P64: 560.19 | Q64: 5223657
B65: Aug 14, 2023 | C65: 560.19 | D65: 5223657 | O65: Aug 7, 2023 | P65: 557.87 | Q65: 7585120
B66: Aug 7, 2023 | C66: 557.87 | D66: 7585120 | O66: Jul 31, 2023 | P66: 564.35 | Q66: 17309427
B67: Jul 31, 2023 | C67: 564.35 | D67: 17309427 | O67: Jul 24, 2023 | P67: 576.24 | Q67: 8095124
... B266: Oct 7, 2019 | C266: 427.2 | D266: 4451998 | O266: Sep 30, 2019 | P266: 408.12 | Q266: 6146549
B267: Sep 30, 2019 | C267: 408.12 | D267: 6146549
